Workbook

Sheet Respostas ao formulário 1
A1: Carimbo de data/hora | B1: Pergunta sem título

Sheet Stakeholders
A1: Região | B1: =SUM(B2:B872) -> 8.0796891 | C1: País | D1: =SUM(D2:D872) -> 55.520166 | E1: Instituição | F1: # stakeholders | G1: Órgão Associado | H1: Link | I1: Observações | J1: Relatórios por instituição | K1: Chave | L1: ID Único Base Projeto OTAN
A2: África | B2: =1/(COUNTIF($A$2:$A$310,A2)) -> 0.5 | C2: África do Sul | D2: =IF(C2="Não se aplica",0,1/(COUNTIF($C$2:$C$310,C2))) -> 1 | E2: Institute for Security Studies (ISS) | F2: =IF(E2="",0,1) -> 1 | H2: https://issafrica.org/ | J2: =COUNTIF(Relatórios!F:F,E2) -> 25 | K2: 1
A3: América do Norte | B3: =1/(COUNTIF($A$2:$A$310,A3)) -> 0.015625 | C3: EUA | D3: =IF(C3="Não se aplica",0,1/(COUNTIF($C$2:$C$310,C3))) -> 0.017857143 | E3: United States African Command (AFRICOM) | F3: =IF(E3="",0,1) -> 1 | H3: https://www.africom.mil/ | J3: =COUNTIF(Relatórios!F:F,E3) -> 1 | K3: 2
A4: Organismo Internacional | B4: =1/(COUNTIF($A$2:$A$310,A4)) -> 0.055555556 | C4: União Europeia | D4: =IF(C4="Não se aplica",0,1/(COUNTIF($C$2:$C$310,C4))) -> 0.14285714 | E4: European Parliament (EUROPARL) | F4: =IF(E4="",0,1) -> 1 | H4: https://www.europarl.europa.eu/portal/en | J4: =COUNTIF(Relatórios!F:F,E4) -> 1 | K4: 3
A5: Europa | B5: =1/(COUNTIF($A$2:$A$310,A5)) -> 0.011494253 | C5: França | D5: =IF(C5="Não se aplica",0,1/(COUNTIF($C$2:$C$310,C5))) -> 0.2 | E5: Report Linker | F5: =IF(E5="",0,1) -> 1 | H5: https://www.reportlinker.com/ | J5: =COUNTIF(Relatórios!F:F,E5) -> 1 | K5: 4
A6: Organismo Internacional | B6: =1/(COUNTIF($A$2:$A$310,A6)) -> 0.055555556 | C6: United Nations Peacekeeping | D6: =IF(C6="Não se aplica",0,1/(COUNTIF($C$2:$C$310,C6))) -> 1 | E6: United Nations Peacekeeping | F6: =IF(E6="",0,1) -> 1 | H6: https://peacekeeping.un.org/en | J6: =COUNTIF(Relatórios!F:F,E6) -> 5 | K6: 5
A7: América Central | B7: =1/(COUNTIF($A$2:$A$310,A7)) -> 0.5 | C7: Honduras | D7: =IF(C7="Não se aplica",0,1/(COUNTIF($C$2:$C$310,C7))) -> 1 | E7: Facultad de Ciencias Espaciales | F7: =IF(E7="",0,1) -> 1 | H7: https://cienciasespaciales.unah.edu.hn/ | J7: =COUNTIF(Relatórios!F:F,E7) -> 1 | K7: 6
A8: América Central | B8: =1/(COUNTIF($A$2:$A$310,A8)) -> 0.5 | C8: Jamaica | D8: =IF(C8="Não se aplica",0,1/(COUNTIF($C$2:$C$310,C8))) -> 1 | E8: Planning Institute of Jamaica | F8: =IF(E8="",0,1) -> 1 | H8: https://www.pioj.gov.jm/ | I8: Com a implementação da visão Jamaica 2030, desenvolveu-se o plano de metas do desenvolvimento sustentável que utiliza a estratégia de ROAD MAP para apresentar as estratégias. | J8: =COUNTIF(Relatórios!F:F,E8) -> 0 | K8: 7
A9: América do Norte | B9: =1/(COUNTIF($A$2:$A$310,A9)) -> 0.015625 | C9: Canadá | D9: =IF(C9="Não se aplica",0,1/(COUNTIF($C$2:$C$310,C9))) -> 0.11111111 | E9: Defense and Security Foresight Group | F9: =IF(E9="",0,1) -> 1 | G9: University of Waterloo | H9: https://uwaterloo.ca/defence-security-foresight-group/ | I9: É um grupo de pesquisa vinculado a faculdade que pesquisa sobre o assunto. | J9: =COUNTIF(Relatórios!F:F,E9) -> 0 | K9: 8
A10: América do Norte | B10: =1/(COUNTIF($A$2:$A$310,A10)) -> 0.015625 | C10: Canadá | D10: =IF(C10="Não se aplica",0,1/(COUNTIF($C$2:$C$310,C10))) -> 0.11111111 | E10: Centre for the Study of Security and Development | F10: =IF(E10="",0,1) -> 1 | G10: Dalhousie University | H10: https://www.dal.ca/sites/cssd.html | I10: É um grupo de pesquisa vinculado a faculdade que pesquisa sobre o assunto. | J10: =COUNTIF(Relatórios!F:F,E10) -> 0 | K10: 9
A11: América do Norte | B11: =1/(COUNTIF($A$2:$A$310,A11)) -> 0.015625 | C11: Canadá | D11: =IF(C11="Não se aplica",0,1/(COUNTIF($C$2:$C$310,C11))) -> 0.11111111 | E11: Canadian Network for Defence and Security Analysis | F11: =IF(E11="",0,1) -> 1 | G11: Basileia School of International Affairs | H11: https://www.balsillieschool.ca/research/cndsa/ | I11: https://www.balsillieschool.ca/wp-content/uploads/2019/02/CNDSA-Report-2019.pdf | J11: =COUNTIF(Relatórios!F:F,E11) -> 1 | K11: 10
A12: América do Norte | B12: =1/(COUNTIF($A$2:$A$310,A12)) -> 0.015625 | C12: Canadá | D12: =IF(C12="Não se aplica",0,1/(COUNTIF($C$2:$C$310,C12))) -> 0.11111111 | E12: North American and Arctic Defence and Security Network | F12: =IF(E12="",0,1) -> 1 | G12: Trent University | H12: https://www.naadsn.ca/ | I12: https://www.naadsn.ca/wp-content/uploads/2020/09/20-Sept-15-NAADSN-Canadian-Arctic-Security-Strategic-Foresight-Analysis-2020-DRAFT-FOR-DISCUSSION-2.pdf | J12: =COUNTIF(Relatórios!F:F,E12) -> 5 | K12: 11
A13: América do Norte | B13: =1/(COUNTIF($A$2:$A$310,A13)) -> 0.015625 | C13: Canadá | D13: =IF(C13="Não se aplica",0,1/(COUNTIF($C$2:$C$310,C13))) -> 0.11111111 | E13: Canadian Army | F13: =IF(E13="",0,1) -> 1 | G13: Government of Canada | H13: http://www.army-armee.forces.gc.ca/en/index.page | J13: =COUNTIF(Relatórios!F:F,E13) -> 1 | K13: 12
A14: América do Norte | B14: =1/(COUNTIF($A$2:$A$310,A14)) -> 0.015625 | C14: Canadá | D14: =IF(C14="Não se aplica",0,1/(COUNTIF($C$2:$C$310,C14))) -> 0.11111111 | E14: Policy Horizons Canada | F14: =IF(E14="",0,1) -> 1 | G14: Government of Canada | H14: https://horizons.gc.ca/en/home/ | J14: =COUNTIF(Relatórios!F:F,E14) -> 1 | K14: 13
A15: América do Norte | B15: =1/(COUNTIF($A$2:$A$310,A15)) -> 0.015625 | C15: EUA | D15: =IF(C15="Não se aplica",0,1/(COUNTIF($C$2:$C$310,C15))) -> 0.017857143 | E15: International Institute of Forecasters | F15: =IF(E15="",0,1) -> 1 | H15: https://forecasters.org/ | J15: =COUNTIF(Relatórios!F:F,E15) -> 0 | K15: 14
A16: América do Norte | B16: =1/(COUNTIF($A$2:$A$310,A16)) -> 0.015625 | C16: EUA | D16: =IF(C16="Não se aplica",0,1/(COUNTIF($C$2:$C$310,C16))) -> 0.017857143 | E16: Center for Global Development | F16: =IF(E16="",0,1) -> 1 | H16: https://www.cgdev.org/ | J16: =COUNTIF(Relatórios!F:F,E16) -> 1 | K16: 15
A17: América do Norte | B17: =1/(COUNTIF($A$2:$A$310,A17)) -> 0.015625 | C17: EUA | D17: =IF(C17="Não se aplica",0,1/(COUNTIF($C$2:$C$310,C17))) -> 0.017857143 | E17: German Marshal Fund | F17: =IF(E17="",0,1) -> 1 | H17: https://www.gmfus.org/ | I17: A GMF é uma instituição com parcetias transatlântica. Apesar de a matriz ser em Washington DC, trabalha em conjunto com países Europeus | J17: =COUNTIF(Relatórios!F:F,E17) -> 0 | K17: 16
A18: América do Norte | B18: =1/(COUNTIF($A$2:$A$310,A18)) -> 0.015625 | C18: EUA | D18: =IF(C18="Não se aplica",0,1/(COUNTIF($C$2:$C$310,C18))) -> 0.017857143 | E18: Center for Strategic & International Studies (CSIS) | F18: =IF(E18="",0,1) -> 1 | H18: https://www.csis.org/ | I18: ir na seção "Programs" | J18: =COUNTIF(Relatórios!F:F,E18) -> 5 | K18: 17
A19: América do Norte | B19: =1/(COUNTIF($A$2:$A$310,A19)) -> 0.015625 | C19: EUA | D19: =IF(C19="Não se aplica",0,1/(COUNTIF($C$2:$C$310,C19))) -> 0.017857143 | E19: Global Risk Intel | F19: =IF(E19="",0,1) -> 1 | H19: https://www.globalriskintel.com/ | J19: =COUNTIF(Relatórios!F:F,E19) -> 1 | K19: 18
A20: América do Norte | B20: =1/(COUNTIF($A$2:$A$310,A20)) -> 0.015625 | C20: EUA | D20: =IF(C20="Não se aplica",0,1/(COUNTIF($C$2:$C$310,C20))) -> 0.017857143 | E20: Air Force Warfighting Integration Capability | F20: =IF(E20="",0,1) -> 1 | G20: United States Air Force | H20: https://www.afwic.af.mil/ | J20: =COUNTIF(Relatórios!F:F,E20) -> 1 | K20: 19
A21: América do Norte | B21: =1/(COUNTIF($A$2:$A$310,A21)) -> 0.015625 | C21: EUA | D21: =IF(C21="Não se aplica",0,1/(COUNTIF($C$2:$C$310,C21))) -> 0.017857143 | E21: RAND Corporation | F21: =IF(E21="",0,1) -> 1 | H21: https://www.rand.org/ | J21: =COUNTIF(Relatórios!F:F,E21) -> 25 | K21: 20
A22: América do Norte | B22: =1/(COUNTIF($A$2:$A$310,A22)) -> 0.015625 | C22: EUA | D22: =IF(C22="Não se aplica",0,1/(COUNTIF($C$2:$C$310,C22))) -> 0.017857143 | E22: National Intelligence Council | F22: =IF(E22="",0,1) -> 1 | G22: OFFICE of the DIRECTOR of NATIONAL INTELLIGENCE | H22: https://www.dni.gov/index.php | J22: =COUNTIF(Relatórios!F:F,E22) -> 1 | K22: 21
A23: América do Norte | B23: =1/(COUNTIF($A$2:$A$310,A23)) -> 0.015625 | C23: EUA | D23: =IF(C23="Não se aplica",0,1/(COUNTIF($C$2:$C$310,C23))) -> 0.017857143 | E23: National Counterproliferation Center (NCPC) | F23: =IF(E23="",0,1) -> 1 | G23: OFFICE of the DIRECTOR of NATIONAL INTELLIGENCE | H23: https://www.dni.gov/index.php/ncpc-home | J23: =COUNTIF(Relatórios!F:F,E23) -> 0 | K23: 22
A24: América do Norte | B24: =1/(COUNTIF($A$2:$A$310,A24)) -> 0.015625 | C24: EUA | D24: =IF(C24="Não se aplica",0,1/(COUNTIF($C$2:$C$310,C24))) -> 0.017857143 | E24: National Counterintelligence and Security Center (NCSC) | F24: =IF(E24="",0,1) -> 1 | G24: OFFICE of the DIRECTOR of NATIONAL INTELLIGENCE | H24: https://www.dni.gov/index.php/ncsc-home | J24: =COUNTIF(Relatórios!F:F,E24) -> 0 | K24: 23
A25: América do Norte | B25: =1/(COUNTIF($A$2:$A$310,A25)) -> 0.015625 | C25: EUA | D25: =IF(C25="Não se aplica",0,1/(COUNTIF($C$2:$C$310,C25))) -> 0.017857143 | E25: National Counterterrorism Center (NCTC) | F25: =IF(E25="",0,1) -> 1 | G25: OFFICE of the DIRECTOR of NATIONAL INTELLIGENCE | H25: https://www.dni.gov/index.php/nctc-home | J25: =COUNTIF(Relatórios!F:F,E25) -> 0 | K25: 24
A26: América do Norte | B26: =1/(COUNTIF($A$2:$A$310,A26)) -> 0.015625 | C26: EUA | D26: =IF(C26="Não se aplica",0,1/(COUNTIF($C$2:$C$310,C26))) -> 0.017857143 | E26: Institute for the Future | F26: =IF(E26="",0,1) -> 1 | H26: https://www.iftf.org/home/ | I26: Não encontrei um relatório anual sobre segurança, mas há alguns tópicos sobre estudos do futuro. | J26: =COUNTIF(Relatórios!F:F,E26) -> 0 | K26: 25
A27: América do Norte | B27: =1/(COUNTIF($A$2:$A$310,A27)) -> 0.015625 | C27: EUA | D27: =IF(C27="Não se aplica",0,1/(COUNTIF($C$2:$C$310,C27))) -> 0.017857143 | E27: House Armed Service Committee | F27: =IF(E27="",0,1) -> 1 | H27: https://armedservices.house.gov/2020/9/future-of-defense-task-force-releases-final-report | I27: https://armedservices.house.gov/_cache/files/2/6/26129500-d208-47ba-a9f7-25a8f82828b0/424EB2008281A3C79BA8C7EA71890AE9.future-of-defense-task-force-report.pdf | J27: =COUNTIF(Relatórios!F:F,E27) -> 1 | K27: 26
A28: América do Norte | B28: =1/(COUNTIF($A$2:$A$310,A28)) -> 0.015625 | C28: EUA | D28: =IF(C28="Não se aplica",0,1/(COUNTIF($C$2:$C$310,C28))) -> 0.017857143 | E28: All Partner Access Network | F28: =IF(E28="",0,1) -> 1 | H28: https://www.apan.org/ | J28: =COUNTIF(Relatórios!F:F,E28) -> 1 | K28: 27
A29: América do Norte | B29: =1/(COUNTIF($A$2:$A$310,A29)) -> 0.015625 | C29: EUA | D29: =IF(C29="Não se aplica",0,1/(COUNTIF($C$2:$C$310,C29))) -> 0.017857143 | E29: Middle East Institute | F29: =IF(E29="",0,1) -> 1 | H29: https://www.mei.edu/programs/strategic-foresight-initiative | I29: É um Think Tank focado na região do Oriente Médio, tendo algumas publicações sobre o tema. | J29: =COUNTIF(Relatórios!F:F,E29) -> 2 | K29: 28
A30: América do Norte | B30: =1/(COUNTIF($A$2:$A$310,A30)) -> 0.015625 | C30: EUA | D30: =IF(C30="Não se aplica",0,1/(COUNTIF($C$2:$C$310,C30))) -> 0.017857143 | E30: Futures and Concepts Center | F30: =IF(E30="",0,1) -> 1 | G30: United States Army | H30: https://www.army.mil/FuturesandConceptsCenter | I30: FCC develops concepts, determines requirements, conducts experimentation, and begins integration of the future force to ensure the Army wins in 2035 and beyond. Contact: USARMY.JBLE.AFC-FCC.MBX.FCC-PAO-Media@mail.mil | J30: =COUNTIF(Relatórios!F:F,E30) -> 0 | K30: 29
A31: América do Norte | B31: =1/(COUNTIF($A$2:$A$310,A31)) -> 0.015625 | C31: EUA | D31: =IF(C31="Não se aplica",0,1/(COUNTIF($C$2:$C$310,C31))) -> 0.017857143 | E31: The brookings Africa Growth Initiative | F31: =IF(E31="",0,1) -> 1 | G31: The brookings | H31: https://www.brookings.edu/series/foresight-africa/ | I31: "The Foresight Africa project is a series of reports, commentaries and events that aim to help policymakers and Africa watchers stay ahead of the trends and developments impacting the continent. Since 2011, the Brookings Africa Growth Initiative has used the occasion of the new year to assess Africa’s top priorities for the year." | J31: =COUNTIF(Relatórios!F:F,E31) -> 4 | K31: 30
A32: América do Norte | B32: =1/(COUNTIF($A$2:$A$310,A32)) -> 0.015625 | C32: EUA | D32: =IF(C32="Não se aplica",0,1/(COUNTIF($C$2:$C$310,C32))) -> 0.017857143 | E32: The brookings | F32: =IF(E32="",0,1) -> 1 | H32: https://www.brookings.edu | J32: =COUNTIF(Relatórios!F:F,E32) -> 4 | K32: 31
A33: América do Norte | B33: =1/(COUNTIF($A$2:$A$310,A33)) -> 0.015625 | C33: EUA | D33: =IF(C33="Não se aplica",0,1/(COUNTIF($C$2:$C$310,C33))) -> 0.017857143 | E33: Atlantic Council | F33: =IF(E33="",0,1) -> 1 | H33: https://www.atlanticcouncil.org/ | I33: O Atlantic Council tem programas especializados em estudar regiões específicas do globo. destaque para o programa "Foresight, Strategy, and Risks Initiative" e "Scowcroft Center for Strategy and Security" | J33: =COUNTIF(Relatórios!F:F,E33) -> 6 | K33: 32
A34: América do Norte | B34: =1/(COUNTIF($A$2:$A$310,A34)) -> 0.015625 | C34: EUA | D34: =IF(C34="Não se aplica",0,1/(COUNTIF($C$2:$C$310,C34))) -> 0.017857143 | E34: Federal Emergency Management Agency | F34: =IF(E34="",0,1) -> 1 | H34: https://www.fema.gov/pt-br | J34: =COUNTIF(Relatórios!F:F,E34) -> 1 | K34: 33
A35: América do Norte | B35: =1/(COUNTIF($A$2:$A$310,A35)) -> 0.015625 | C35: EUA | D35: =IF(C35="Não se aplica",0,1/(COUNTIF($C$2:$C$310,C35))) -> 0.017857143 | E35: Center for Strategic and Budgetary Assessments | F35: =IF(E35="",0,1) -> 1 | H35: https://csbaonline.org/ | J35: =COUNTIF(Relatórios!F:F,E35) -> 1 | K35: 34
A36: América do Norte | B36: =1/(COUNTIF($A$2:$A$310,A36)) -> 0.015625 | C36: México | D36: =IF(C36="Não se aplica",0,1/(COUNTIF($C$2:$C$310,C36))) -> 1 | E36: Revista del Centro de Estudios Superiores Navales | F36: =IF(E36="",0,1) -> 1 | G36: Centro de Estudios Superiores Navales | H36: https://biblat.unam.mx/pt/revista/revista-del-centro-de-estudios-superiores-navales | J36: =COUNTIF(Relatórios!F:F,E36) -> 2 | K36: 35
A37: América do Norte | B37: =1/(COUNTIF($A$2:$A$310,A37)) -> 0.015625 | C37: EUA | D37: =IF(C37="Não se aplica",0,1/(COUNTIF($C$2:$C$310,C37))) -> 0.017857143 | E37: Mad Scientist Laboratory | F37: =IF(E37="",0,1) -> 1 | G37: United States Army | H37: https://madsciblog.tradoc.army.mil/ | I37: Iniciativa do exército norte-americano - uma comunidade de exploração contínua através de parcerias colaborativas e diálogo com academia, indústria e governo. | J37: =COUNTIF(Relatórios!F:F,E37) -> 0 | K37: 36
A38: América do Norte | B38: =1/(COUNTIF($A$2:$A$310,A38)) -> 0.015625 | C38: EUA | D38: =IF(C38="Não se aplica",0,1/(COUNTIF($C$2:$C$310,C38))) -> 0.017857143 | E38: PriceWaterHouseCoopers (PwC) | F38: =IF(E38="",0,1) -> 1 | H38: https://www.pwc.com/gx/en/ceo-agenda/ceosurvey/2020/trends/defence.html | I38: Consultoria global com enfoque especializado em defesa. | J38: =COUNTIF(Relatórios!F:F,E38) -> 1 | K38: 37
A39: América do Norte | B39: =1/(COUNTIF($A$2:$A$310,A39)) -> 0.015625 | C39: EUA | D39: =IF(C39="Não se aplica",0,1/(COUNTIF($C$2:$C$310,C39))) -> 0.017857143 | E39: The Heritage Foundation | F39: =IF(E39="",0,1) -> 1 | H39: https://www.heritage.org/defense | I39: OSC que aborda temas de cibersegurança, política espacial, tecnologia, defesa, segurança nacional, terrorismo, imigração, energia, com vistas à proteção dos princípios norte-americanos. | J39: =COUNTIF(Relatórios!F:F,E39) -> 1 | K39: 38
A40: América do Norte | B40: =1/(COUNTIF($A$2:$A$310,A40)) -> 0.015625 | C40: EUA | D40: =IF(C40="Não se aplica",0,1/(COUNTIF($C$2:$C$310,C40))) -> 0.017857143 | E40: Deloitte | F40: =IF(E40="",0,1) -> 1 | G40: Defense and National Security | H40: https://www2.deloitte.com/global/en/pages/public-sector/articles/gx-national-security-industry-outlook.html | I40: Grupo de trabalho da consultoria global, neste caso representada por seu head regional especializado em defesa e segurança nacional, Nathan Houser. | J40: =COUNTIF(Relatórios!F:F,E40) -> 0 | K40: 39
A41: América do Norte | B41: =1/(COUNTIF($A$2:$A$310,A41)) -> 0.015625 | C41: EUA | D41: =IF(C41="Não se aplica",0,1/(COUNTIF($C$2:$C$310,C41))) -> 0.017857143 | E41: Market Study Report, LLC | F41: =IF(E41="",0,1) -> 1 | G41: Defense and Security Market Report 2020 | H41: https://www.express-journal.com/request-sample/380846?utm=AG | I41: MSR, LLC é um hub de inteligência de mercado e serviços. | J41: =COUNTIF(Relatórios!F:F,E41) -> 1 | K41: 40
A42: América do Norte | B42: =1/(COUNTIF($A$2:$A$310,A42)) -> 0.015625 | C42: EUA | D42: =IF(C42="Não se aplica",0,1/(COUNTIF($C$2:$C$310,C42))) -> 0.017857143 | E42: Forecast International | F42: =IF(E42="",0,1) -> 1 | G42: - | H42: https://www.forecastinternational.com/ | I42: Empresa de pesquisa de mercado e análise com mais de 45 anos para as indústrias aeroespacial, eletrônica, geopolítica, naval, energia e armamento. Projeções para mais de 120 países. | J42: =COUNTIF(Relatórios!F:F,E42) -> 2 | K42: 41
A43: América do Norte | B43: =1/(COUNTIF($A$2:$A$310,A43)) -> 0.015625 | C43: EUA | D43: =IF(C43="Não se aplica",0,1/(COUNTIF($C$2:$C$310,C43))) -> 0.017857143 | E43: NASA - National Aeronautics and Space Administration | F43: =IF(E43="",0,1) -> 1 | G43: Armstrong Flight Research Center | H43: https://www.nasa.gov/centers/armstrong/tech-dev/index.html | I43: Departamento governamental da NASA focada em tecnologias sobre voo e assuntos relacionados, assim como algumas perspectivas futuras. | J43: =COUNTIF(Relatórios!F:F,E43) -> 2 | K43: 42
A44: América do Norte | B44: =1/(COUNTIF($A$2:$A$310,A44)) -> 0.015625 | C44: EUA | D44: =IF(C44="Não se aplica",0,1/(COUNTIF($C$2:$C$310,C44))) -> 0.017857143 | E44: NASA - National Aeronautics and Space Administration | F44: =IF(E44="",0,1) -> 1 | G44: Langley Research Center | H44: https://www.nasa.gov/langley/overview/2020-annual-report/ | I44: Departamento governamental da NASA focada em tecnologias dos setores de ciências da terra, aeronáutica e aeroespacial. | J44: =COUNTIF(Relatórios!F:F,E44) -> 2 | K44: 43
A45: América do Norte | B45: =1/(COUNTIF($A$2:$A$310,A45)) -> 0.015625 | C45: EUA | D45: =IF(C45="Não se aplica",0,1/(COUNTIF($C$2:$C$310,C45))) -> 0.017857143 | E45: CNAS - Center for a New American Security | F45: =IF(E45="",0,1) -> 1 | G45: - | H45: https://www.cnas.org/ | I45: OSC fundada por democratas, embora autodeclaradamente apartidária, sobre defesa, segurança, tecnologia, dentre outros. | J45: =COUNTIF(Relatórios!F:F,E45) -> 1 | K45: 44
A46: América do Norte | B46: =1/(COUNTIF($A$2:$A$310,A46)) -> 0.015625 | C46: EUA | D46: =IF(C46="Não se aplica",0,1/(COUNTIF($C$2:$C$310,C46))) -> 0.017857143 | E46: Defense Innovation Baord | F46: =IF(E46="",0,1) -> 1 | G46: - | H46: https://innovation.defense.gov/ | I46: Departamento governamental norte-americano que produz relatórios e recomendações sobre a temática de defesa. | J46: =COUNTIF(Relatórios!F:F,E46) -> 1 | K46: 45
A47: América do Norte | B47: =1/(COUNTIF($A$2:$A$310,A47)) -> 0.015625 | C47: EUA | D47: =IF(C47="Não se aplica",0,1/(COUNTIF($C$2:$C$310,C47))) -> 0.017857143 | E47: DARPA - Defense Advanced Research Projects Agency | F47: =IF(E47="",0,1) -> 1 | G47: DSO - Defense Sciences Office | H47: https://www.darpa.mil/about-us/offices/dso // https://www.darpa.mil/about-us/offices/i2o | I47: Estudos fronteiriços em matemática, computação e design; limites de sensores e sensitividade; sistemas sociais complexos; antecipação de surpresas. Resumos de projetos que podem servir de tópicos base de pesquisa. // Estudos visando assegurar vantagem para os EUA e aliados utilizando tecnologia da informação por intermédio do avanço dos fundamentos técnicos, dentre outros. Resumos de projetos que podem servir de tópicos base de pesquisa. | J47: =COUNTIF(Relatórios!F:F,E47) -> 0 | K47: 46
A48: América do Norte | B48: =1/(COUNTIF($A$2:$A$310,A48)) -> 0.015625 | C48: EUA | D48: =IF(C48="Não se aplica",0,1/(COUNTIF($C$2:$C$310,C48))) -> 0.017857143 | E48: NTI - Nuclear Threat Initiative | F48: =IF(E48="",0,1) -> 1 | G48: - | H48: https://www.nti.org/ | I48: Think Tank com produção intelectual visando impedir ataques com WMDs - nucleares, biológicas, radiológicas, químicas e cibernéticas. (um artigo: https://www.jstor.org/publisher/nti?refreqid=excelsior%3A6eceda2d52d14a2c4624e86dd162be6e) | J48: =COUNTIF(Relatórios!F:F,E48) -> 4 | K48: 47
A49: América do Norte | B49: =1/(COUNTIF($A$2:$A$310,A49)) -> 0.015625 | C49: EUA | D49: =IF(C49="Não se aplica",0,1/(COUNTIF($C$2:$C$310,C49))) -> 0.017857143 | E49: Defense Counterintelligence and Security Agency | F49: =IF(E49="",0,1) -> 1 | G49: - | H49: https://www.dcsa.mil/about/err/ | J49: =COUNTIF(Relatórios!F:F,E49) -> 1 | K49: 48
A50: América do Norte | B50: =1/(COUNTIF($A$2:$A$310,A50)) -> 0.015625 | C50: EUA | D50: =IF(C50="Não se aplica",0,1/(COUNTIF($C$2:$C$310,C50))) -> 0.017857143 | E50: National Intelligence University | F50: =IF(E50="",0,1) -> 1 | G50: - | H50: https://ni-u.edu/wp/ni-press-publications/ | J50: =COUNTIF(Relatórios!F:F,E50) -> 1 | K50: 49
A51: América do Norte | B51: =1/(COUNTIF($A$2:$A$310,A51)) -> 0.015625 | C51: EUA | D51: =IF(C51="Não se aplica",0,1/(COUNTIF($C$2:$C$310,C51))) -> 0.017857143 | E51: Defense Business Board | F51: =IF(E51="",0,1) -> 1 | H51: https://dbb.defense.gov/Reports/ | I51: Excelência de negócios em defesa da nação norte-americana. | J51: =COUNTIF(Relatórios!F:F,E51) -> 0 | K51: 50
A52: América do Norte | B52: =1/(COUNTIF($A$2:$A$310,A52)) -> 0.015625 | C52: Canadá | D52: =IF(C52="Não se aplica",0,1/(COUNTIF($C$2:$C$310,C52))) -> 0.11111111 | E52: Center for International Governance Innovation | F52: =IF(E52="",0,1) -> 1 | H52: https://www.cigionline.org/about/funding | J52: =COUNTIF(Relatórios!F:F,E52) -> 1 | K52: 51
A53: América do Norte | B53: =1/(COUNTIF($A$2:$A$310,A53)) -> 0.015625 | C53: Canadá | D53: =IF(C53="Não se aplica",0,1/(COUNTIF($C$2:$C$310,C53))) -> 0.11111111 | E53: Centre for Defence and Security Studies | F53: =IF(E53="",0,1) -> 1 | G53: University of Manitoba | H53: https://umanitoba.ca/centres/cdss/papers/CDSS-Related%20articles.html | J53: =COUNTIF(Relatórios!F:F,E53) -> 0 | K53: 52
A54: América do Norte | B54: =1/(COUNTIF($A$2:$A$310,A54)) -> 0.015625 | C54: EUA | D54: =IF(C54="Não se aplica",0,1/(COUNTIF($C$2:$C$310,C54))) -> 0.017857143 | E54: National Defense University | F54: =IF(E54="",0,1) -> 1 | H54: https://www.ndu.edu/ | J54: =COUNTIF(Relatórios!F:F,E54) -> 1 | K54: 53
A55: América do Norte | B55: =1/(COUNTIF($A$2:$A$310,A55)) -> 0.015625 | C55: EUA | D55: =IF(C55="Não se aplica",0,1/(COUNTIF($C$2:$C$310,C55))) -> 0.017857143 | E55: Air Command and Staff College | F55: =IF(E55="",0,1) -> 1 | G55: Air University | H55: https://www.airuniversity.af.edu/ACSC/ | J55: =COUNTIF(Relatórios!F:F,E55) -> 1 | K55: 54
A56: América do Norte | B56: =1/(COUNTIF($A$2:$A$310,A56)) -> 0.015625 | C56: EUA | D56: =IF(C56="Não se aplica",0,1/(COUNTIF($C$2:$C$310,C56))) -> 0.017857143 | E56: Africa Center for Strategic Studies | F56: =IF(E56="",0,1) -> 1 | G56: National Defense University | H56: https://africacenter.org/ | I56: Forum de pesquisa, programas acadêmicos e intercâmbio de ideias visando aperfeiçoar a segurança dos cidadãos através do fortalecimento da efetividade e responsabilidade de instituições africanas. | J56: =COUNTIF(Relatórios!F:F,E56) -> 1 | K56: 55
A57: América do Sul | B57: =1/(COUNTIF($A$2:$A$310,A57)) -> 0.5 | C57: Brasil | D57: =IF(C57="Não se aplica",0,1/(COUNTIF($C$2:$C$310,C57))) -> 0.5 | E57: Instituto de Pesquisa Econômica Aplicada | F57: =IF(E57="",0,1) -> 1 | H57: https://www.ipea.gov.br/portal/ | J57: =COUNTIF(Relatórios!F:F,E57) -> 3 | K57: 56
A58: Ásia | B58: =1/(COUNTIF($A$2:$A$310,A58)) -> 0.045454545 | C58: Singapura | D58: =IF(C58="Não se aplica",0,1/(COUNTIF($C$2:$C$310,C58))) -> 1 | E58: S. Rajaratnam School of International Studies | F58: =IF(E58="",0,1) -> 1 | G58: Nanyand Technological University | H58: https://www.rsis.edu.sg/ | I58: The S. Rajaratnam School of International Studies (RSIS) is a global think tank and school of graduate education offering Master of Science Programmes in Strategic Studies, International Relations, International Political Economy, and Asian Studies. | J58: =COUNTIF(Relatórios!F:F,E58) -> 2 | K58: 57
A59: Organismo Internacional | B59: =1/(COUNTIF($A$2:$A$310,A59)) -> 0.055555556 | C59: União Europeia | D59: =IF(C59="Não se aplica",0,1/(COUNTIF($C$2:$C$310,C59))) -> 0.14285714 | E59: Comissão Europeia | F59: =IF(E59="",0,1) -> 1 | G59: União Europeia | H59: https://ec.europa.eu/info/index_pt | J59: =COUNTIF(Relatórios!F:F,E59) -> 1 | K59: 58
A60: Europa | B60: =1/(COUNTIF($A$2:$A$310,A60)) -> 0.011494253 | C60: Alemanha | D60: =IF(C60="Não se aplica",0,1/(COUNTIF($C$2:$C$310,C60))) -> 0.11111111 | E60: German Development Institute | F60: =IF(E60="",0,1) -> 1 | H60: https://www.die-gdi.de/en/ | J60: =COUNTIF(Relatórios!F:F,E60) -> 0 | K60: 59
A61: Europa | B61: =1/(COUNTIF($A$2:$A$310,A61)) -> 0.011494253 | C61: Alemanha | D61: =IF(C61="Não se aplica",0,1/(COUNTIF($C$2:$C$310,C61))) -> 0.11111111 | E61: Friedrich Ebert Stiftung | F61: =IF(E61="",0,1) -> 1 | H61: https://www.fes.de/ | I61: A FES é uma instituição com braçoes em diversos países. | J61: =COUNTIF(Relatórios!F:F,E61) -> 1 | K61: 60
A62: Europa | B62: =1/(COUNTIF($A$2:$A$310,A62)) -> 0.011494253 | C62: Alemanha | D62: =IF(C62="Não se aplica",0,1/(COUNTIF($C$2:$C$310,C62))) -> 0.11111111 | E62: Munich Security Conference | F62: =IF(E62="",0,1) -> 1 | H62: https://securityconference.org/en/news/ | J62: =COUNTIF(Relatórios!F:F,E62) -> 1 | K62: 61
A63: Europa | B63: =1/(COUNTIF($A$2:$A$310,A63)) -> 0.011494253 | C63: Alemanha | D63: =IF(C63="Não se aplica",0,1/(COUNTIF($C$2:$C$310,C63))) -> 0.11111111 | E63: Federam Ministry of Education and Research | F63: =IF(E63="",0,1) -> 1 | G63: Governo Federal | H63: https://www.bmbf.de/en/bmbf-foresight-1419.html | I63: Buscar por "BMBF Foresight". Não envolve específicamente Segurança e Defesa | J63: =COUNTIF(Relatórios!F:F,E63) -> 0 | K63: 62
A64: Europa | B64: =1/(COUNTIF($A$2:$A$310,A64)) -> 0.011494253 | C64: Alemanha | D64: =IF(C64="Não se aplica",0,1/(COUNTIF($C$2:$C$310,C64))) -> 0.11111111 | E64: Foresight Intelligence | F64: =IF(E64="",0,1) -> 1 | H64: https://www.foresightintelligence.de/index.html | I64: Empresa prvvada de consultoria | J64: =COUNTIF(Relatórios!F:F,E64) -> 0 | K64: 63
A65: Europa | B65: =1/(COUNTIF($A$2:$A$310,A65)) -> 0.011494253 | C65: Alemanha | D65: =IF(C65="Não se aplica",0,1/(COUNTIF($C$2:$C$310,C65))) -> 0.11111111 | E65: Partnership For Peace Consortium | F65: =IF(E65="",0,1) -> 1 | H65: http://www.pfp-consortium.org/articles/cybersecurity-switzerland-challenges-and-way-forward-swiss-armed-forces | I65: É uma organização de cooperação em segurança e defesa. | J65: =COUNTIF(Relatórios!F:F,E65) -> 0 | K65: 64
A66: Europa | B66: =1/(COUNTIF($A$2:$A$310,A66)) -> 0.011494253 | C66: Áustria | D66: =IF(C66="Não se aplica",0,1/(COUNTIF($C$2:$C$310,C66))) -> 1 | E66: ETH Zurich Center for Security Studies | F66: =IF(E66="",0,1) -> 1 | H66: https://css.ethz.ch/en/ | J66: =COUNTIF(Relatórios!F:F,E66) -> 2 | K66: 65
A67: Europa | B67: =1/(COUNTIF($A$2:$A$310,A67)) -> 0.011494253 | C67: Bruxelas | D67: =IF(C67="Não se aplica",0,1/(COUNTIF($C$2:$C$310,C67))) -> 1 | E67: Solvay Brussels School of Economics and Management - Center Emile Bernheim | F67: =IF(E67="",0,1) -> 1 | G67: Université Libre de Bruxelles | H67: https://sbsem.ulb.be/research/research-centres/ceb | I67: (Não membro da ONU) | J67: =COUNTIF(Relatórios!F:F,E67) -> 0 | K67: 66
A68: Europa | B68: =1/(COUNTIF($A$2:$A$310,A68)) -> 0.011494253 | C68: Dinamarca | D68: =IF(C68="Não se aplica",0,1/(COUNTIF($C$2:$C$310,C68))) -> 0.25 | E68: Center for Military Studies | F68: =IF(E68="",0,1) -> 1 | G68: University of Copenhagen | H68: https://cms.polsci.ku.dk/english/ | J68: =COUNTIF(Relatórios!F:F,E68) -> 0 | K68: 67
A69: Europa | B69: =1/(COUNTIF($A$2:$A$310,A69)) -> 0.011494253 | C69: Estônia | D69: =IF(C69="Não se aplica",0,1/(COUNTIF($C$2:$C$310,C69))) -> 1 | E69: International Centre for Defence and Security | F69: =IF(E69="",0,1) -> 1 | H69: https://icds.ee/en/ | J69: =COUNTIF(Relatórios!F:F,E69) -> 0 | K69: 68
A70: Europa | B70: =1/(COUNTIF($A$2:$A$310,A70)) -> 0.011494253 | C70: Finlândia | D70: =IF(C70="Não se aplica",0,1/(COUNTIF($C$2:$C$310,C70))) -> 0.25 | E70: Finland Futures Research Centre | F70: =IF(E70="",0,1) -> 1 | G70: University of Turku | H70: https://www.utu.fi/en/university/turku-school-of-economics/finland-futures-research-centre | J70: =COUNTIF(Relatórios!F:F,E70) -> 0 | K70: 69
A71: Europa | B71: =1/(COUNTIF($A$2:$A$310,A71)) -> 0.011494253 | C71: Finlândia | D71: =IF(C71="Não se aplica",0,1/(COUNTIF($C$2:$C$310,C71))) -> 0.25 | E71: Comittee for the Future | F71: =IF(E71="",0,1) -> 1 | G71: Parliament of Finland | H71: https://www.eduskunta.fi/EN/valiokunnat/tulevaisuusvaliokunta/Pages/default.aspx | J71: =COUNTIF(Relatórios!F:F,E71) -> 1 | K71: 70
A72: Europa | B72: =1/(COUNTIF($A$2:$A$310,A72)) -> 0.011494253 | C72: Finlândia | D72: =IF(C72="Não se aplica",0,1/(COUNTIF($C$2:$C$310,C72))) -> 0.25 | E72: Finish Institute of International Affairs | F72: =IF(E72="",0,1) -> 1 | H72: https://www.fiia.fi/en/ | J72: =COUNTIF(Relatórios!F:F,E72) -> 0 | K72: 71
A73: Europa | B73: =1/(COUNTIF($A$2:$A$310,A73)) -> 0.011494253 | C73: França | D73: =IF(C73="Não se aplica",0,1/(COUNTIF($C$2:$C$310,C73))) -> 0.2 | E73: Fondation pour la Recherche Stratégique | F73: =IF(E73="",0,1) -> 1 | H73: https://www.frstrategie.org/en | J73: =COUNTIF(Relatórios!F:F,E73) -> 0 | K73: 72
A74: Europa | B74: =1/(COUNTIF($A$2:$A$310,A74)) -> 0.011494253 | C74: França | D74: =IF(C74="Não se aplica",0,1/(COUNTIF($C$2:$C$310,C74))) -> 0.2 | E74: Institut Français des Relations Internationales | F74: =IF(E74="",0,1) -> 1 | H74: https://www.ifri.org/en | J74: =COUNTIF(Relatórios!F:F,E74) -> 0 | K74: 73
A75: Europa | B75: =1/(COUNTIF($A$2:$A$310,A75)) -> 0.011494253 | C75: França | D75: =IF(C75="Não se aplica",0,1/(COUNTIF($C$2:$C$310,C75))) -> 0.2 | E75: Institut de Relations Internationales et Stratégiques | F75: =IF(E75="",0,1) -> 1 | H75: https://www.iris-france.org/ | J75: =COUNTIF(Relatórios!F:F,E75) -> 0 | K75: 74
A76: Europa | B76: =1/(COUNTIF($A$2:$A$310,A76)) -> 0.011494253 | C76: Grécia | D76: =IF(C76="Não se aplica",0,1/(COUNTIF($C$2:$C$310,C76))) -> 0.5 | E76: Hellenic Foundation for European and Foreign Policy | F76: =IF(E76="",0,1) -> 1 | H76: https://www.eliamep.gr/en/ | J76: =COUNTIF(Relatórios!F:F,E76) -> 0 | K76: 75
A77: Europa | B77: =1/(COUNTIF($A$2:$A$310,A77)) -> 0.011494253 | C77: Itália | D77: =IF(C77="Não se aplica",0,1/(COUNTIF($C$2:$C$310,C77))) -> 0.5 | E77: Istituto Affari Internazionali | F77: =IF(E77="",0,1) -> 1 | H77: https://www.iai.it/it | J77: =COUNTIF(Relatórios!F:F,E77) -> 0 | K77: 76
A78: Europa | B78: =1/(COUNTIF($A$2:$A$310,A78)) -> 0.011494253 | C78: Moldávia | D78: =IF(C78="Não se aplica",0,1/(COUNTIF($C$2:$C$310,C78))) -> 1 | E78: North Atlantic Treaty Organization | F78: =IF(E78="",0,1) -> 1 | G78: Organização das Nações Unidas (ONU) | H78: https://www.nato.int/cps/en/natohq/news_180758.htm?selectedLocale=en | I78: Coopera em questões relacionadas à defesa e à segurança para resolver problemas, construir confiança e, a longo prazo, evitar conflitos. | J78: =COUNTIF(Relatórios!F:F,E78) -> 0 | K78: 77
A79: Europa | B79: =1/(COUNTIF($A$2:$A$310,A79)) -> 0.011494253 | C79: Noruega | D79: =IF(C79="Não se aplica",0,1/(COUNTIF($C$2:$C$310,C79))) -> 0.2 | E79: Agency for Public Management and eGovernment | F79: =IF(E79="",0,1) -> 1 | H79: https://cids.no/difi/ | J79: =COUNTIF(Relatórios!F:F,E79) -> 1 | K79: 78
A80: Europa | B80: =1/(COUNTIF($A$2:$A$310,A80)) -> 0.011494253 | C80: Noruega | D80: =IF(C80="Não se aplica",0,1/(COUNTIF($C$2:$C$310,C80))) -> 0.2 | E80: Norwegian Ministry of defence | F80: =IF(E80="",0,1) -> 1 | H80: https://www.regjeringen.no/en/dep/fd/id380/ | J80: =COUNTIF(Relatórios!F:F,E80) -> 1 | K80: 79
A81: Europa | B81: =1/(COUNTIF($A$2:$A$310,A81)) -> 0.011494253 | C81: Noruega | D81: =IF(C81="Não se aplica",0,1/(COUNTIF($C$2:$C$310,C81))) -> 0.2 | E81: European Army Interoperability Centre | F81: =IF(E81="",0,1) -> 1 | G81: Institute for Security Studies | H81: https://finabel.org/ | I81: Não produz relatórios, mas produz análises e formato de estudos que são publicadas em formato online | J81: =COUNTIF(Relatórios!F:F,E81) -> 0 | K81: 80
A82: Europa | B82: =1/(COUNTIF($A$2:$A$310,A82)) -> 0.011494253 | C82: Países Baixos | D82: =IF(C82="Não se aplica",0,1/(COUNTIF($C$2:$C$310,C82))) -> 0.25 | E82: The Netherlands Institute of International Relations Clingendael | F82: =IF(E82="",0,1) -> 1 | H82: https://www.clingendael.org/ | J82: =COUNTIF(Relatórios!F:F,E82) -> 0 | K82: 81
A83: Europa | B83: =1/(COUNTIF($A$2:$A$310,A83)) -> 0.011494253 | C83: Portugal | D83: =IF(C83="Não se aplica",0,1/(COUNTIF($C$2:$C$310,C83))) -> 0.25 | E83: Serviço de Informação de Segurança | F83: =IF(E83="",0,1) -> 1 | H83: https://www.sis.pt/ | J83: =COUNTIF(Relatórios!F:F,E83) -> 1 | K83: 82
A84: Europa | B84: =1/(COUNTIF($A$2:$A$310,A84)) -> 0.011494253 | C84: Reino Unido | D84: =IF(C84="Não se aplica",0,1/(COUNTIF($C$2:$C$310,C84))) -> 0.125 | E84: Government of UK | F84: =IF(E84="",0,1) -> 1 | H84: https://www.gov.uk/ | J84: =COUNTIF(Relatórios!F:F,E84) -> 1 | K84: 83
A85: Europa | B85: =1/(COUNTIF($A$2:$A$310,A85)) -> 0.011494253 | C85: República Tcheca | D85: =IF(C85="Não se aplica",0,1/(COUNTIF($C$2:$C$310,C85))) -> 0.5 | E85: Ministry of Defence of the Czech Republic | F85: =IF(E85="",0,1) -> 1 | H85: https://www.army.cz/en/ | J85: =COUNTIF(Relatórios!F:F,E85) -> 1 | K85: 84
A86: Europa | B86: =1/(COUNTIF($A$2:$A$310,A86)) -> 0.011494253 | C86: Sérvia | D86: =IF(C86="Não se aplica",0,1/(COUNTIF($C$2:$C$310,C86))) -> 1 | E86: International Security Sector Advisory Team | F86: =IF(E86="",0,1) -> 1 | H86: https://issat.dcaf.ch/Learn/SSR-in-Practice/Countries-Regions/Serbia?view=resources | I86: Contribui para melhorar a segurança e a justiça como um meio de ajudar a prevenir conflitos violentos, construir uma paz sustentável e estabelecer um ambiente propício para alcançar os Objetivos de Desenvolvimento Sustentável (ODS). | J86: =COUNTIF(Relatórios!F:F,E86) -> 0 | K86: 85
A87: Europa | B87: =1/(COUNTIF($A$2:$A$310,A87)) -> 0.011494253 | C87: Suécia | D87: =IF(C87="Não se aplica",0,1/(COUNTIF($C$2:$C$310,C87))) -> 0.14285714 | E87: Swedish Defence Research Agency | F87: =IF(E87="",0,1) -> 1 | H87: https://www.foi.se/en/foi.html | J87: =COUNTIF(Relatórios!F:F,E87) -> 1 | K87: 86
A88: Europa | B88: =1/(COUNTIF($A$2:$A$310,A88)) -> 0.011494253 | C88: Suécia | D88: =IF(C88="Não se aplica",0,1/(COUNTIF($C$2:$C$310,C88))) -> 0.14285714 | E88: Government offices of sweden | F88: =IF(E88="",0,1) -> 1 | H88: https://www.government.se/ | J88: =COUNTIF(Relatórios!F:F,E88) -> 1 | K88: 87
A89: Europa | B89: =1/(COUNTIF($A$2:$A$310,A89)) -> 0.011494253 | C89: Suécia | D89: =IF(C89="Não se aplica",0,1/(COUNTIF($C$2:$C$310,C89))) -> 0.14285714 | E89: Stockholm International Peace Research Institute | F89: =IF(E89="",0,1) -> 1 | H89: https://www.sipri.org/ | I89: É um instituto internacional independente dedicado à pesquisa sobre conflitos, armamentos, controle de armas e desarmamento. | J89: =COUNTIF(Relatórios!F:F,E89) -> 5 | K89: 88
A90: Organismo Internacional | B90: =1/(COUNTIF($A$2:$A$310,A90)) -> 0.055555556 | C90: União Europeia | D90: =IF(C90="Não se aplica",0,1/(COUNTIF($C$2:$C$310,C90))) -> 0.14285714 | E90: European Foresight Plataform | F90: =IF(E90="",0,1) -> 1 | G90: Comissão Europeia | H90: http://www.foresight-platform.eu/ | I90: Descontinuada e substituída pela "European Foresight Monitoring Network" | J90: =COUNTIF(Relatórios!F:F,E90) -> 0 | K90: 89
A91: Organismo Internacional | B91: =1/(COUNTIF($A$2:$A$310,A91)) -> 0.055555556 | C91: União Europeia | D91: =IF(C91="Não se aplica",0,1/(COUNTIF($C$2:$C$310,C91))) -> 0.14285714 | E91: European Foresight Monitoring Network | F91: =IF(E91="",0,1) -> 1 | G91: Comissão Europeia | H91: https://op.europa.eu/en/publication-detail/-/publication/91db75a7-dbdb-49e9-a5ee-2c75c0fd83ac | J91: =COUNTIF(Relatórios!F:F,E91) -> 0 | K91: 90
A92: Organismo Internacional | B92: =1/(COUNTIF($A$2:$A$310,A92)) -> 0.055555556 | C92: União Europeia | D92: =IF(C92="Não se aplica",0,1/(COUNTIF($C$2:$C$310,C92))) -> 0.14285714 | E92: European Union Institute for Security Studies | F92: =IF(E92="",0,1) -> 1 | H92: https://www.iss.europa.eu/topics/strategic-foresight | J92: =COUNTIF(Relatórios!F:F,E92) -> 0 | K92: 91
A93: Organismo Internacional | B93: =1/(COUNTIF($A$2:$A$310,A93)) -> 0.055555556 | C93: União Europeia | D93: =IF(C93="Não se aplica",0,1/(COUNTIF($C$2:$C$310,C93))) -> 0.14285714 | E93: Foresight Europe Network | F93: =IF(E93="",0,1) -> 1 | H93: http://www.feneu.org/ | J93: =COUNTIF(Relatórios!F:F,E93) -> 0 | K93: 92
A94: Organismo Internacional | B94: =1/(COUNTIF($A$2:$A$310,A94)) -> 0.055555556 | C94: União Europeia | D94: =IF(C94="Não se aplica",0,1/(COUNTIF($C$2:$C$310,C94))) -> 0.14285714 | E94: European Regional Foresight College | F94: =IF(E94="",0,1) -> 1 | H94: https://foresight-college.eu/ | J94: =COUNTIF(Relatórios!F:F,E94) -> 0 | K94: 93
A95: Europa | B95: =1/(COUNTIF($A$2:$A$310,A95)) -> 0.011494253 | C95: Reino Unido | D95: =IF(C95="Não se aplica",0,1/(COUNTIF($C$2:$C$310,C95))) -> 0.125 | E95: RUSI - Royal United Services Institute for Defence and Security Studies | F95: =IF(E95="",0,1) -> 1 | H95: https://www.rusi.org/ | I95: Think tank | J95: =COUNTIF(Relatórios!F:F,E95) -> 2 | K95: 94
A96: Oceania | B96: =1/(COUNTIF($A$2:$A$310,A96)) -> 0.090909091 | C96: Austrália | D96: =IF(C96="Não se aplica",0,1/(COUNTIF($C$2:$C$310,C96))) -> 0.090909091 | E96: Army Knowledge Centre (The cove) | F96: =IF(E96="",0,1) -> 1 | H96: https://cove.army.gov.au/bio/army-knowledge-centre | J96: =COUNTIF(Relatórios!F:F,E96) -> 1 | K96: 95
A97: Oceania | B97: =1/(COUNTIF($A$2:$A$310,A97)) -> 0.090909091 | C97: Austrália | D97: =IF(C97="Não se aplica",0,1/(COUNTIF($C$2:$C$310,C97))) -> 0.090909091 | E97: Institute for Regional Security | F97: =IF(E97="",0,1) -> 1 | H97: https://regionalsecurity.org.au/ | I97: We promote the peace, stability and prosperity of the peoples of the Indo-Pacific region through policy research, policy advice and advocacy, international dialogues, and the professional development of policy-makers | J97: =COUNTIF(Relatórios!F:F,E97) -> 1 | K97: 96
A98: Oceania | B98: =1/(COUNTIF($A$2:$A$310,A98)) -> 0.090909091 | C98: Austrália | D98: =IF(C98="Não se aplica",0,1/(COUNTIF($C$2:$C$310,C98))) -> 0.090909091 | E98: Lowy Institute for International Policy | F98: =IF(E98="",0,1) -> 1 | H98: https://www.lowyinstitute.org/ | I98: The Lowy Institute is an Australian think tank with a global outlook. Our research interests are as broad as Australia’s interests, and we host distinguished speakers from around the globe on foreign policy, defence, politics, aid and development, journalism, sport, science and the arts. | J98: =COUNTIF(Relatórios!F:F,E98) -> 3 | K98: 97
A99: Oceania | B99: =1/(COUNTIF($A$2:$A$310,A99)) -> 0.090909091 | C99: Austrália | D99: =IF(C99="Não se aplica",0,1/(COUNTIF($C$2:$C$310,C99))) -> 0.090909091 | E99: Australian Strategic Policy Institute | F99: =IF(E99="",0,1) -> 1 | H99: https://www.aspi.org.au/ | I99: ASPI is an independent, non-partisan think tank that produces expert and timely advice for Australian and global leaders. ASPI generates new ideas for policy makers, allowing them to make better-informed decisions. | J99: =COUNTIF(Relatórios!F:F,E99) -> 5 | K99: 98
A100: Oceania | B100: =1/(COUNTIF($A$2:$A$310,A100)) -> 0.090909091 | C100: Austrália | D100: =IF(C100="Não se aplica",0,1/(COUNTIF($C$2:$C$310,C100))) -> 0.090909091 | E100: Sea power Centre | F100: =IF(E100="",0,1) -> 1 | G100: Royal Australian Navy | H100: https://www.navy.gov.au/ | I100: The Sea Power Centre - Australia (SPC–A) was established in the early 1990s to act as an autonomous research centre in order to foster and encourage development of maritime strategic thought by providing intellectual rigour to the public debate on maritime strategy and other maritime issues | J100: =COUNTIF(Relatórios!F:F,E100) -> 2 | K100: 99
...

Sheet Relatórios
A1: Ano | B1: Região | C1: País Solicitante | D1: País Objeto | E1: País / Org. Int. | F1: Instituição | G1: Check instituição | H1: Nome do Estudo | I1: Link | J1: Trata de def/seg | K1: Sementes | L1: Político/geopolítico | M1: Econômico | N1: Social | O1: Tecnológico | P1: Ambiental | Q1: Legal | R1: Militar | S1: Marítimo | T1: Terrestre | U1: Aeroespacial | V1: Macrotema? | W1: Método | X1: Palavra Chave 1 | Y1: Palavra Chave 2 | Z1: Palavra Chave 3 | AA1: Observações | AB1: Inserido por | AC1: inserido em | AD1: Chave Relatório | AE1: Chave_Instituicao | AF1: Chave_Pais | AG1: Indicação grupo LCS? | AH1: Ciclo de Atualizacao | AK1: Email do Responsável | AL1: Data de Atualização
A2: 2020 | B2: Organismo Internacional | C2: Comissão Europeia | D2: Europa | E2: União Europeia | F2: Comissão Europeia | G2: =COUNTIF(Stakeholders!$E$2:$E960,F2) -> 1 | H2: 2020 strategic foresight report | I2: https://ec.europa.eu/info/sites/info/files/strategic_foresight_report_2020_1.pdf | J2: sim | K2: sim | L2: sim | M2: sim | N2: sim | O2: sim | P2: sim | Q2: sim | R2: sim | S2: sim | T2: sim | U2: sim | V2: Globalização político-jurídica | W2: sim | X2: Cooperação transnacional interblocos | Y2: Resiliência em bloco | Z2: Monitoramento integrado | AB2: Vj | AC2: 44315 | AD2: 1 | AE2: =VLOOKUP(F2,Stakeholders!E:K,7,0) -> 58 | AF2: =VLOOKUP(B2&D2,Areas!$D:$E,2,FALSE) -> #N/A | AH2: 1 - Projeto Prospecta Parte 02 - 2022 | AI2: =COUNTIF(Stakeholders!$E$2:$E$114,F2) -> 1
A3: 2018 | B3: América do Norte | C3: EUA | D3: Global | E3: EUA | F3: Global Risk Intel | G3: =COUNTIF(Stakeholders!$E$2:$E960,F3) -> 1 | H3: Forecasting Future Space Risks: Environmental, commercial, and military aspects | I3: https://www.globalriskintel.com/reports/forecasting-future-space-risks-environmental-commercial-and-military-aspects | J3: sim | K3: sim | M3: sim | P3: sim | R3: sim | U3: sim | W3: não | AB3: Yasmim | AD3: 2 | AE3: =VLOOKUP(F3,Stakeholders!E:K,7,0) -> 18 | AF3: =VLOOKUP(B3&D3,Areas!$D:$E,2,FALSE) -> 283 | AH3: 1 - Projeto Prospecta Parte 02 - 2022 | AI3: =COUNTIF(Stakeholders!$E$2:$E$114,F3) -> 1
A4: 2020 | B4: América do Norte | C4: Canadá | D4: Região do Ártico | E4: Canadá | F4: North American and Arctic Defence and Security Network | G4: =COUNTIF(Stakeholders!$E$2:$E960,F4) -> 1 | H4: Understanding The Future Arctic Security Environment; Applying NATO Strategic Foresight Analysis to Canadian Arctic Defense and Security | I4: https://www.naadsn.ca/wp-content/uploads/2020/09/20-Sept-15-NAADSN-Canadian-Arctic-Security-Strategic-Foresight-Analysis-2020-DRAFT-FOR-DISCUSSION-2.pdf | J4: sim | K4: não | W4: sim | AA4: O relatório possui uma parte sobre a metodologia usada, como também da estratégia que a NATO utiliza para fazer análises. | AB4: Yasmim | AD4: 3 | AE4: =VLOOKUP(F4,Stakeholders!E:K,7,0) -> 11 | AF4: =VLOOKUP(B4&D4,Areas!$D:$E,2,FALSE) -> #N/A | AH4: 1 - Projeto Prospecta Parte 02 - 2022 | AI4: =COUNTIF(Stakeholders!$E$2:$E$114,F4) -> 1
A5: 2021 | B5: América do Norte | C5: EUA | D5: Oriente Médio | E5: EUA | F5: RAND Corporation | G5: =COUNTIF(Stakeholders!$E$2:$E960,F5) -> 1 | H5: Reimagining U.S. Strategy in the Middle East: Sustainable Partnerships, Strategic Investiments | I5: https://www.rand.org/pubs/research_reports/RRA958-2.html | J5: sim | K5: sim | L5: sim | M5: sim | N5: sim | O5: sim | P5: não | Q5: não | R5: sim | S5: não | T5: sim | U5: não | W5: não | X5: Política estratégica dos EUA | Y5: Oriente Médio | Z5: Liderança Internacional | AA5: Primeiramente, é válido iniciar esta observação notando que o projeto foi financiado através de uma doação da The Broad Reach Foundation. Isto posto, o relatório tem como objetivo avaliar a política externa dos EUA para com a região do Oriente Médio que passou sucessivas administrações na Casa Branca, os resultados produzidos para a região e/ou para os interesses norte americanos não têm tido saldo positivo. Bem como, este salienta que após anos de intervenções na região, a mesma continua mergulhada na instabilidade que afeta os interesses estadunidenses. Além disso, o trabalho se inicia com a seguinte pergunta: “é hora de repensar algumas das premissas fundamentais subjacentes à formulação de políticas dos EUA nesta região?”. A partir disso, o relatório tem como base a avaliação das vantagens e dos trade-offs de “uma estratégia regional alternativa na qual os objetivos estratégicos se ligam a uma compreensão mais ampla da estabilidade que prioriza a redução de conflitos, melhor governança, e maior crescimento e desenvolvimento”. Ainda, foi possível a observância de uma certa preocupação com o Irã. Como também, destaca que “devido a pandemia, mudanças climáticas e perturbações nos mercados petrolíferos - combinadas com os múltiplos conflitos e falhas de governança da região - a estratégia dos EUA não podem mais se dar ao luxo de se concentrar no nível do estado e da liderança, negligenciando os males da sociedade e da população da região”. Em resumo, ao finalizar o relatório, os pesquisadores apontam algumas recomendações para um redirecionamento nos objetivos estratégicos dos EUA. | AB5: Yasmim | AD5: 4 | AE5: =VLOOKUP(F5,Stakeholders!E:K,7,0) -> 20 | AF5: =VLOOKUP(B5&D5,Areas!$D:$E,2,FALSE) -> #N/A | AH5: 1 - Projeto Prospecta Parte 02 - 2022 | AI5: =COUNTIF(Stakeholders!$E$2:$E$114,F5) -> 1
A6: 2018 | B6: América do Norte | C6: EUA | D6: Global | E6: EUA | F6: RAND Corporation | G6: =COUNTIF(Stakeholders!$E$2:$E960,F6) -> 1 | H6: Discontinuities and Distractions - Rethinking Security for the Year 2040 | I6: https://www.rand.org/pubs/conf_proceedings/CF384.html | J6: sim | K6: sim | W6: não | AB6: Yasmim | AD6: 5 | AE6: =VLOOKUP(F6,Stakeholders!E:K,7,0) -> 20 | AF6: =VLOOKUP(B6&D6,Areas!$D:$E,2,FALSE) -> 283 | AH6: 1 - Projeto Prospecta Parte 02 - 2022 | AI6: =COUNTIF(Stakeholders!$E$2:$E$114,F6) -> 1
A7: 2021 | B7: América do Norte | C7: Israel | D7: Oriente Médio | E7: EUA | F7: Middle East Institute | G7: =COUNTIF(Stakeholders!$E$2:$E960,F7) -> 1 | H7: What will the Middle East Look Like in 2030? An Israeli Perspective | I7: https://www.mei.edu/sites/default/files/2021-02/%20What%20will%20the%20Middle%20East%20look%20like%20in%202030%3F%20An%20Israeli%20Perspective.pdf | J7: sim | K7: sim | W7: sim | AB7: Yasmim | AD7: 6 | AE7: =VLOOKUP(F7,Stakeholders!E:K,7,0) -> 28 | AF7: =VLOOKUP(B7&D7,Areas!$D:$E,2,FALSE) -> #N/A | AH7: 1 - Projeto Prospecta Parte 02 - 2022 | AI7: =COUNTIF(Stakeholders!$E$2:$E$114,F7) -> 1
A8: 2020 | B8: América do Norte | C8: EUA | D8: EUA - China | E8: EUA | F8: Center for Strategic & International Studies (CSIS) | G8: =COUNTIF(Stakeholders!$E$2:$E960,F8) -> 1 | H8: Four Scenarios for Geopolitical Order in 2025-2030: What Will Great Power Competition Look Like? | I8: https://www.csis.org/analysis/four-scenarios-geopolitical-order-2025-2030-what-will-great-power-competition-look | J8: sim | K8: sim | L8: sim | M8: sim | N8: não | O8: sim | P8: não | Q8: não | R8: sim | S8: sim | T8: sim | U8: não | W8: sim | X8: Geopolítica | Y8: Influência Global | Z8: Relação bilateral | AB8: Yasmim | AD8: 7 | AE8: =VLOOKUP(F8,Stakeholders!E:K,7,0) -> 17 | AF8: =VLOOKUP(B8&D8,Areas!$D:$E,2,FALSE) -> #N/A | AH8: 1 - Projeto Prospecta Parte 02 - 2022 | AI8: =COUNTIF(Stakeholders!$E$2:$E$114,F8) -> 1
A9: 2015 | B9: América do Norte | C9: EUA | D9: Ásia - Pacífico | E9: EUA | F9: Center for Strategic & International Studies (CSIS) | G9: =COUNTIF(Stakeholders!$E$2:$E960,F9) -> 1 | H9: Defense 2045: Assessing the Future Security Environment and Implications for Defense Policymakers | I9: https://csis-website-prod.s3.amazonaws.com/s3fs-public/legacy_files/files/publication/151106_Miller_Defense2045_Web.pdf | J9: sim | K9: não | W9: sim | AB9: Yasmim | AD9: 8 | AE9: =VLOOKUP(F9,Stakeholders!E:K,7,0) -> 17 | AF9: =VLOOKUP(B9&D9,Areas!$D:$E,2,FALSE) -> #N/A | AH9: 1 - Projeto Prospecta Parte 02 - 2022 | AI9: =COUNTIF(Stakeholders!$E$2:$E$114,F9) -> 1
A10: 2018 | B10: América Central | C10: Honduras | D10: Honduras | E10: Honduras | F10: Facultad de Ciencias Espaciales | G10: =COUNTIF(Stakeholders!$E$2:$E960,F10) -> 1 | H10: Proyeccción de operaciones aéreas al año 2030 aeródromo de Tela, Atlántida, Honduras | I10: https://www.lamjol.info/index.php/CE/article/view/7170/6735 | J10: sim | K10: sim | W10: não | AB10: Yasmim | AD10: 9 | AE10: =VLOOKUP(F10,Stakeholders!E:K,7,0) -> 6 | AF10: =VLOOKUP(B10&D10,Areas!$D:$E,2,FALSE) -> 71 | AH10: 1 - Projeto Prospecta Parte 02 - 2022 | AI10: =COUNTIF(Stakeholders!$E$2:$E$114,F10) -> 1
A11: 2020 | B11: Organismo Internacional | C11: Sem país específico | D11: Não se aplica | E11: International Renewable Energy Agency | F11: International Renewable Energy Agency | G11: =COUNTIF(Stakeholders!$E$2:$E960,F11) -> 1 | H11: Global Renewables Outlook: Energy Transformation 2050 | I11: https://www.irena.org/-/media/Files/IRENA/Agency/Publication/2020/Apr/IRENA_Global_Renewables_Outlook_2020.pdf | J11: não | K11: sim | W11: não | AB11: Yasmim | AD11: 10 | AE11: =VLOOKUP(F11,Stakeholders!E:K,7,0) -> 105 | AF11: =VLOOKUP(B11&D11,Areas!$D:$E,2,FALSE) -> #N/A | AH11: 1 - Projeto Prospecta Parte 02 - 2022 | AI11: =COUNTIF(Stakeholders!$E$2:$E$114,F11) -> 1
A12: 2019 | B12: América do Norte | C12: EUA | D12: China | E12: EUA | F12: The brookings Africa Growth Initiative | G12: =COUNTIF(Stakeholders!$E$2:$E960,F12) -> 1 | H12: The US-China Nuclear Relationship: why competition is likely to intensify | I12: https://www.brookings.edu/wp-content/uploads/2019/09/FP_20190930_china_nuclear_weapons_talmadge-2.pdf | J12: sim | K12: sim | L12: sim | M12: não | N12: não | O12: sim | P12: não | Q12: não | R12: sim | S12: sim | T12: sim | U12: sim | W12: não | X12: Arsenal nuclear | Y12: US-China | Z12: Mutually Assured Destruction (MAD) | AA12: O relatório se inicia realizando um pequeno panorama sobre como as armas nucleares têm se expandindo nas relações periféricas entre EUA-China. Além disso, a preocupação dos EUA é fazer com que a China fique preocupada, caso esta se engaje em um conflito de escalada nuclear, uma vez que na perspectiva estadunidense, os EUA estaria mais propenso a suportar os riscos que seriam ocasionados do que a China. Visto que, esta última teria capacidade menor quando comparada com os EUA que dotaria de vantagens de barganha para com a China, caso uma guerra eclodisse. O documento analisado nos elucida sobre a deterioração da relação entre EUA-China aumentou a preocupação com as possíveis consequências da intensificação militar entre esses dois Estados. Apesar de alguns analistas enfatizarem que o conflito está longe de ser inevitável, outros analistas observam que há uma possibilidade crescente de os conflitos ou até mesmo guerra possam ocorrer nos mares do Leste ou do Sul da China, ou sobre Taiwan. nalisando pela perspectiva Chinesa, o país “está buscando uma capacidade de second-strike capability (capacidade de segundo ataque) mais seguro - uma força que possa garantir um nível inaceitável de retaliação nuclear contra qualquer estado que lance um primeiro ataque contra a China, e assim impedir que tal ataque seja lançado”. (p. 2). Todavia, esta movimentação Chinesa que não é considerada como nova, está preocupando Washington à medida que durante a administração Obama, os EUA evitam descrever a relação nuclear como uma relação de destruição mútua assegurada (MAD - Mutual Assured Destruction). O MAD pressupõe que não há uma prerrogativa que evite que ambos os lados sofram com os danos, não importando quem ataque primeiro. Em suma, o documento irá demonstrar como os formuladores de políticas estadunidenses poderiam gerenciar uma relação nuclear mais competitiva. | AB12: Yasmim | AD12: 11 | AE12: =VLOOKUP(F12,Stakeholders!E:K,7,0) -> 30 | AF12: =VLOOKUP(B12&D12,Areas!$D:$E,2,FALSE) -> #N/A | AH12: 1 - Projeto Prospecta Parte 02 - 2022 | AI12: =COUNTIF(Stakeholders!$E$2:$E$114,F12) -> 1
A13: 2020 | B13: América do Norte | C13: EUA | D13: Global | E13: EUA | F13: Center for Global Development | G13: =COUNTIF(Stakeholders!$E$2:$E960,F13) -> 1 | H13: Horizon 2025 - End of the Beginning; Development Cooperation in the Pandemic Age | I13: https://www.cgdev.org/sites/default/files/horizon-2025-end-beginning-development-cooperation-pandemic-age.pdf | J13: não | K13: sim | W13: não | AB13: Yasmim | AD13: 12 | AE13: =VLOOKUP(F13,Stakeholders!E:K,7,0) -> 15 | AF13: =VLOOKUP(B13&D13,Areas!$D:$E,2,FALSE) -> 283 | AH13: 1 - Projeto Prospecta Parte 02 - 2022 | AI13: =COUNTIF(Stakeholders!$E$2:$E$114,F13) -> 1
A14: 2017 | B14: América do Norte | C14: EUA | D14: Global | E14: EUA | F14: The brookings Africa Growth Initiative | G14: =COUNTIF(Stakeholders!$E$2:$E960,F14) -> 1 | H14: Securing Global Cities - Best practices, innovation, and the path ahead | I14: https://www.brookings.edu/research/securing-global-cities-2/ | J14: não | K14: sim | W14: não | AB14: Yasmim | AD14: 13 | AE14: =VLOOKUP(F14,Stakeholders!E:K,7,0) -> 30 | AF14: =VLOOKUP(B14&D14,Areas!$D:$E,2,FALSE) -> 283 | AH14: 1 - Projeto Prospecta Parte 02 - 2022 | AI14: =COUNTIF(Stakeholders!$E$2:$E$114,F14) -> 1
A15: 2020 | B15: América do Norte | C15: México | D15: México | E15: México | F15: Revista del Centro de Estudios Superiores Navales | G15: =COUNTIF(Stakeholders!$E$2:$E960,F15) -> 1 | H15: Planteamientos para el desarrollo de la Estrategia Marítima 2020 - 2040 - Revista de Centro de Estudios Superiores Navales, México, 2020, Vol. 41 Núm. 1 Enemar, pág 187 - 229. | I15: https://cesnav.uninav.edu.mx/cesnav/revista_pdf/2020/2020-1.pdf | J15: sim | AB15: Yasmim | AD15: 14 | AE15: =VLOOKUP(F15,Stakeholders!E:K,7,0) -> 35 | AF15: =VLOOKUP(B15&D15,Areas!$D:$E,2,FALSE) -> 106 | AH15: 1 - Projeto Prospecta Parte 02 - 2022 | AI15: =COUNTIF(Stakeholders!$E$2:$E$114,F15) -> 1
A16: 2019 | B16: América do Norte | C16: México | D16: México | E16: México | F16: Revista del Centro de Estudios Superiores Navales | G16: =COUNTIF(Stakeholders!$E$2:$E960,F16) -> 1 | H16: Desafíos a las Estrategias de Ciberseguridad en América - Revista de Centro de Estudios Superiores Navales, México, 2019 Vol. 40 Núm. 4. 4oct-Dic, pág. 25 - 53 | I16: https://cesnav.uninav.edu.mx/cesnav/revista_pdf/2019/2019-4.pdf | J16: sim | AB16: Yasmim | AD16: 15 | AE16: =VLOOKUP(F16,Stakeholders!E:K,7,0) -> 35 | AF16: =VLOOKUP(B16&D16,Areas!$D:$E,2,FALSE) -> 106 | AH16: 1 - Projeto Prospecta Parte 02 - 2022 | AI16: =COUNTIF(Stakeholders!$E$2:$E$114,F16) -> 1
A17: 2012 | B17: América do Norte | C17: EUA | D17: EUA | E17: EUA | F17: Federal Emergency Management Agency | G17: =COUNTIF(Stakeholders!$E$2:$E960,F17) -> 1 | H17: Crisis Reposnse and Disaster Resilience 2030: Forging Strategic Action in an Age of Uncertainty | I17: https://fas.org/irp/agency/dhs/fema/crisis.pdf | J17: não | K17: sim | W17: não | AB17: Yasmim | AD17: 16 | AE17: =VLOOKUP(F17,Stakeholders!E:K,7,0) -> 33 | AF17: =VLOOKUP(B17&D17,Areas!$D:$E,2,FALSE) -> 56 | AH17: 1 - Projeto Prospecta Parte 02 - 2022 | AI17: =COUNTIF(Stakeholders!$E$2:$E$114,F17) -> 1
A18: 2020 | B18: América do Norte | C18: Canadá | D18: Canadá | E18: Canadá | F18: Policy Horizons Canada | G18: =COUNTIF(Stakeholders!$E$2:$E960,F18) -> 1 | H18: Foresight on Covid-19 - Possible shifts and implications | I18: https://horizons.gc.ca/en/2021/03/05/foresight-on-covid-19-possible-shifts-and-implications/ | J18: não | AB18: Yasmim | AD18: 17 | AE18: =VLOOKUP(F18,Stakeholders!E:K,7,0) -> 13 | AF18: =VLOOKUP(B18&D18,Areas!$D:$E,2,FALSE) -> 80 | AH18: 1 - Projeto Prospecta Parte 02 - 2022 | AI18: =COUNTIF(Stakeholders!$E$2:$E$114,F18) -> 1
A19: 2017 | B19: América do Norte | C19: Canadá | D19: Canadá | E19: Canadá | F19: Canadian Army | G19: =COUNTIF(Stakeholders!$E$2:$E960,F19) -> 1 | H19: Alternate Worlds and Implocations, Vol. 3 | I19: http://publications.gc.ca/collections/collection_2018/mdn-dnd/D2-354-3-2017-eng.pdf | AB19: Yasmim | AD19: 18 | AE19: =VLOOKUP(F19,Stakeholders!E:K,7,0) -> 12 | AF19: =VLOOKUP(B19&D19,Areas!$D:$E,2,FALSE) -> 80 | AH19: 1 - Projeto Prospecta Parte 02 - 2022 | AI19: =COUNTIF(Stakeholders!$E$2:$E$114,F19) -> 1
A20: 2020 | B20: América do Norte | C20: EUA | D20: Global | E20: EUA | F20: Atlantic Council | G20: =COUNTIF(Stakeholders!$E$2:$E960,F20) -> 1 | H20: What World Post-Covid-19? Three Scenarios | I20: https://www.atlanticcouncil.org/content-series/shaping-post-covid-world-together/what-world-post-covid-19-three-scenarios/ | J20: não | K20: sim | L20: sim | M20: não | N20: não | O20: não | P20: não | Q20: não | R20: não | S20: não | T20: não | U20: não | W20: não | X20: Balança de poder | Y20: geopolítica | AA20: Apesar de dedicar a pergunta do título à COVID-19 (what world post-covid-19?), não se deve deixar enganar: o “mundo pós-covid” é apenas o ponto de partida dos cenários. O relatório até considera a influência da COVID, mas com o mesmo grau de importância que dá a quaisquer outras questões como commodities, desastre humanitário, dentre outros. Na verdade, o ponto fundamental deste estudo é a mudança do equilíbrio geopolítico do mundo (com preocupação especial voltada à China), abordando superficialmente para impactos originados de questões econômicas e sociais. Há um trecho dedicado à América Latina. A avaliação geral é a de que a região está fragilizada por conta 1) dos impactos da covid e 2) por depender majoritariamente dos ciclos de commodities, mais especificamente o petróleo. Por isso, o relatório diz que , apesar de a região não ser um campo de disputa competitivo entre EUA e China, os EUA devem se preocupar com a tentativa de inserção da China na região através de auxílio para recuperação econômica. Os 3 cenários 1 Acelerando para baixo: “a desglobalização está se acelerando, produzindo um crescimento econômico lento em todos os lugares. Os níveis de pobreza estão aumentando no mundo em desenvolvimento e há potencial para um conflito aberto entre os Estados Unidos e uma aliança China-Rússia.” 2 China primeiro: “Para muitos países fora da Europa, os Estados Unidos aparecem em declínio acentuado. Apesar da responsabilidade da China pelo surto, a pandemia inclinou a balança geopolítica a seu favor.” 3 nova renascença: "Com a redução das tensões interestaduais, o crescimento econômico é retomado e, para a maioria da população mundial, os Objetivos de Desenvolvimento Sustentável de eliminação da pobreza e disseminação da educação estão mais uma vez ao alcance." | AB20: Yasmim | AD20: 19 | AE20: =VLOOKUP(F20,Stakeholders!E:K,7,0) -> 32 | AF20: =VLOOKUP(B20&D20,Areas!$D:$E,2,FALSE) -> 283 | AH20: 1 - Projeto Prospecta Parte 02 - 2022 | AI20: =COUNTIF(Stakeholders!$E$2:$E$114,F20) -> 1
A21: 2019 | B21: América do Norte | C21: EUA | D21: Global | E21: EUA | F21: Atlantic Council | G21: =COUNTIF(Stakeholders!$E$2:$E960,F21) -> 1 | H21: Global risks 2035 update: Decline or new renaissance? | I21: https://www.atlanticcouncil.org/in-depth-research-reports/report/global-risks-2035-update/ | J21: sim | K21: sim | W21: não | AB21: Yasmim | AD21: 20 | AE21: =VLOOKUP(F21,Stakeholders!E:K,7,0) -> 32 | AF21: =VLOOKUP(B21&D21,Areas!$D:$E,2,FALSE) -> 283 | AH21: 1 - Projeto Prospecta Parte 02 - 2022 | AI21: =COUNTIF(Stakeholders!$E$2:$E$114,F21) -> 1
A22: 2016 | B22: América do Norte | C22: EUA | D22: América Latina/ Caribe | E22: EUA | F22: Atlantic Council | G22: =COUNTIF(Stakeholders!$E$2:$E960,F22) -> 1 | H22: Latin America and the Caribbean 2030: futures scenarios | I22: https://www.atlanticcouncil.org/in-depth-research-reports/report/latin-america-and-the-caribbean-2030-future-scenarios/ | J22: não | K22: sim | W22: não | AB22: Yasmim | AD22: 21 | AE22: =VLOOKUP(F22,Stakeholders!E:K,7,0) -> 32 | AF22: =VLOOKUP(B22&D22,Areas!$D:$E,2,FALSE) -> #N/A | AH22: 1 - Projeto Prospecta Parte 02 - 2022 | AI22: =COUNTIF(Stakeholders!$E$2:$E$114,F22) -> 1
A23: 2019 | B23: América do Norte | C23: Canadá | D23: Global | E23: Canadá | F23: Canadian Network for Defence and Security Analysis | G23: =COUNTIF(Stakeholders!$E$2:$E960,F23) -> 1 | H23: Foresight & Analysis: In Canadian Defense and Security Policy | I23: https://www.balsillieschool.ca/wp-content/uploads/2019/02/CNDSA-Report-2019.pdf | J23: sim | K23: não | L23: sim | M23: não | N23: não | O23: sim | P23: não | Q23: não | R23: sim | S23: sim | T23: não | U23: não | W23: não | X23: segurança/defesa | Y23: geopilítica | Z23: Canadá | AA23: O relatóro fala majoritáriamente sobre como o Canadá deve se portar – sob o aspecto da segurança e defesa – frente ao cenário geopolítcio onde estão inseridos. Relatam alguma preocupação com terrorismos, mas apresentam maiores dados sobre suas questões com a Rússia e a China, além de preocupação com sa segurança cibernética (por isso foi sinalizado com sim o campo tecnológico). O aspecto militar é recorrentemente mecionado, com a sugestão de aquiseção de novos equipamentos, sobretudo para a marinha, o que levou a marcar os campos militar e marítimo nesta planilha. Ainda assim o texto não se aprfunda nestes aspectos. Apesar do relatório abordar brevemente a possibilidade de problemas futuros, como embates no Mar do Sul da China, disputas pesqueiras e também a respeito dos interesses canadenses no Ártico ( e possíveis dificuldades que possam advir neste campo), não pareceu trazer nenhum aspecto novo que indique qualquer semente de futuro. | AB23: Yasmim | AD23: 22 | AE23: =VLOOKUP(F23,Stakeholders!E:K,7,0) -> 10 | AF23: =VLOOKUP(B23&D23,Areas!$D:$E,2,FALSE) -> 283 | AH23: 1 - Projeto Prospecta Parte 02 - 2022 | AI23: =COUNTIF(Stakeholders!$E$2:$E$114,F23) -> 1
A24: 2020 | B24: América do Norte | C24: EUA | D24: EUA | E24: EUA | F24: RAND Corporation | G24: =COUNTIF(Stakeholders!$E$2:$E960,F24) -> 1 | H24: Developing New Futures Scenarios for the U.S. Coast Guard's Evergreen Strategic Foresight Program | I24: https://www.rand.org/pubs/research_reports/RR3147.html | J24: sim | K24: não | W24: sim | AB24: Yasmim | AC24: 44315 | AD24: 23 | AE24: =VLOOKUP(F24,Stakeholders!E:K,7,0) -> 20 | AF24: =VLOOKUP(B24&D24,Areas!$D:$E,2,FALSE) -> 56 | AH24: 1 - Projeto Prospecta Parte 02 - 2022 | AI24: =COUNTIF(Stakeholders!$E$2:$E$114,F24) -> 1
A25: 2020 | B25: América do Norte | C25: EUA | D25: Global | E25: EUA | F25: Center for Strategic & International Studies (CSIS) | G25: =COUNTIF(Stakeholders!$E$2:$E960,F25) -> 1 | H25: Global Security Forum 2020: A New Era for U.S. Alliances | I25: https://www.csis.org/analysis/global-security-forum-2020-new-era-us-alliances | J25: sim | K25: sim | L25: sim | M25: sim | N25: não | O25: sim | P25: sim | Q25: não | R25: sim | S25: sim | T25: sim | U25: sim | W25: não | X25: Sistema de aliança | Y25: Influência global | Z25: Indo-Pacífico | AA25: O relatório de análise inicia sua análise já evidenciando as preocupações atreladas aos EUA e seus aliados e como estes estão “minados” pela ascensão de outros atores, tal como Rússia e China. A Rússia pela anexação da Crimeia e a China pela expansão coercitiva no Mar do Sul da China. Além disso, o relatório foi produzido observando a transição entre a administração Trump para a administração de Biden e tendo isso como ponto de análise, foi pontuado que o sistema de alianças é muito mais importante nos dias de hoje como nunca foi antes. Ainda, eles notaram que dentro do “guarda-chuva” de responsabilidades empreendidas pelos EUA estão: a estabilidade econômica, não proliferação, contenção do terrorismo e a prevenção de conflito violento em larga escala. Com isso, os EUA possuem o desafio, na concepção do autor deste relatório, de gerir a pandemia da COVID-19, enquanto revigora o poder dos valores norte-americanos na competição com o crescimento coercitivo da China. 3 CENÁRIOS SÃO PROJETADOS NESSE RELATÓRIO, SÃO ELES: 1- TAIWAN 2025 → A República Popular da China Bloqueia Taiwan e usa seu poderio militar e econômico para impedir uma resposta global; 2 - CRISE CLIMÁTICA 2030 → O mundo sofre com várias catástrofes relacionadas ao clima que estão em andamento e que provocam insegurança alimentar*, migração em massa e desafios de segurança nas fronteiras; * A insegurança alimentar pode ser pensada aqui também, como no grupo de Biodefesa e Benchmarking, como uma ferramenta de conflito, visto que países já o enfrentam. 3 - RÚSSIA 2024 → A interferência russa nas eleições estadunidenses leva a uma escalada do conflito cibernético e espacial com os EUA, que ameaça se alastrar (spill over) para o conflito armado. Há uma observância de 4 temas transversais associados que podem auxiliar no fortalecimento das alianças, são eles: alianças começando do zero; As ameaças no século 21 são regional e global; as ameaças hoje ocorrem na interseção da preocupação militar, diplomática e econômica; e, por último as alianças dependem do compartilhamento do entendimento e sacrifício. | AB25: Yasmim | AC25: 44315 | AD25: 24 | AE25: =VLOOKUP(F25,Stakeholders!E:K,7,0) -> 17 | AF25: =VLOOKUP(B25&D25,Areas!$D:$E,2,FALSE) -> 283 | AH25: 1 - Projeto Prospecta Parte 02 - 2022 | AI25: =COUNTIF(Stakeholders!$E$2:$E$114,F25) -> 1
A26: 2020 | B26: América do Norte | C26: EUA | D26: Global | E26: EUA | F26: House Armed Service Committee | G26: =COUNTIF(Stakeholders!$E$2:$E960,F26) -> 1 | H26: Future od Defense Task Force - Report 2020 | I26: https://armedservices.house.gov/_cache/files/2/6/26129500-d208-47ba-a9f7-25a8f82828b0/424EB2008281A3C79BA8C7EA71890AE9.future-of-defense-task-force-report.pdf | AB26: Yasmim | AD26: 25 | AE26: =VLOOKUP(F26,Stakeholders!E:K,7,0) -> 26 | AF26: =VLOOKUP(B26&D26,Areas!$D:$E,2,FALSE) -> 283 | AH26: 1 - Projeto Prospecta Parte 02 - 2022 | AI26: =COUNTIF(Stakeholders!$E$2:$E$114,F26) -> 1
A27: 2020 | B27: América do Norte | C27: EUA | D27: Região do Ártico | E27: EUA | F27: Center for Strategic & International Studies (CSIS) | G27: =COUNTIF(Stakeholders!$E$2:$E960,F27) -> 1 | H27: America's Arctic Moment: Great Power Competition in the Arctic to 2050 | I27: https://www.csis.org/analysis/americas-arctic-moment-great-power-competition-arctic-2050 | J27: sim | K27: sim | W27: não | AB27: Yasmim | AC27: 44315 | AD27: 26 | AE27: =VLOOKUP(F27,Stakeholders!E:K,7,0) -> 17 | AF27: =VLOOKUP(B27&D27,Areas!$D:$E,2,FALSE) -> #N/A | AH27: 1 - Projeto Prospecta Parte 02 - 2022 | AI27: =COUNTIF(Stakeholders!$E$2:$E$114,F27) -> 1
A28: 2020 | B28: América do Norte | C28: EUA | D28: Global | E28: EUA | F28: Rand Corporation | G28: =COUNTIF(Stakeholders!$E$2:$E960,F28) -> 1 | H28: The Future of Warfare in 2030 - Project Overview and Conclusions | I28: https://www.rand.org/pubs/research_reports/RR2849z1.html | J28: sim | K28: sim | L28: sim | M28: sim | N28: sim | O28: sim | P28: sim | Q28: sim | R28: sim | S28: não | T28: sim | U28: não | W28: não | X28: Guerra Futura | Y28: Terrorismo | Z28: Oriente Médio | AA28: As escolhas desses termos chaves se deu pela abordagem do relatório sobre as preocupações estadunidesentes para como será as guerra futuras e seus principais atores e localidade. Para mais, é notável que o terrorismo é um dos fatores que mais preocupam os norte americanos e estes observam o Oriente Médio como Lócus de grupos não estatais para proliferação desses grupos. | AB28: Yasmim | AC28: 44315 | AD28: 27 | AE28: =VLOOKUP(F28,Stakeholders!E:K,7,0) -> 20 | AF28: =VLOOKUP(B28&D28,Areas!$D:$E,2,FALSE) -> 283 | AH28: 1 - Projeto Prospecta Parte 02 - 2022 | AI28: =COUNTIF(Stakeholders!$E$2:$E$114,F28) -> 1
A29: 2020 | B29: América do Norte | C29: EUA | D29: Global | E29: EUA | F29: Rand Corporation | G29: =COUNTIF(Stakeholders!$E$2:$E960,F29) -> 1 | H29: Measuring Power, Power Cycles, and the Risk of Great-Power War in the 21st Century | I29: https://www.rand.org/pubs/research_reports/RR2989.html | J29: sim | K29: sim | L29: sim | M29: sim | N29: não | O29: sim | P29: sim | Q29: não | R29: sim | S29: nao | T29: sim | U29: não | W29: não | X29: Terrorismo | Y29: Balança de poder | Z29: Power Cycle Theory | AA29: Estes termos foram pontuados como chaves devido a preocupação dentro de um cenário com horizonte para 2040, temas como o terrorismo, a balança de poder e a mundança climática são fatores fortes que podem impactar na reestruturação do Sistema Internacional, segundo o relatório analisado, cabendo ressaltar que há outros fatores que são pontuados na análise. Por fim, a Power Cycle Theory foi considerada termo chave devido esta ter sido a metodologia principal de análise para mensuração da balança de poder. | AB29: Yasmim | AC29: 44315 | AD29: 28 | AE29: =VLOOKUP(F29,Stakeholders!E:K,7,0) -> 20 | AF29: =VLOOKUP(B29&D29,Areas!$D:$E,2,FALSE) -> 283 | AH29: 1 - Projeto Prospecta Parte 02 - 2022 | AI29: =COUNTIF(Stakeholders!$E$2:$E$114,F29) -> 1
A30: 2020 | B30: América do Norte | C30: EUA | D30: Global | E30: EUA | F30: Air Force Warfighting Integration Capability | G30: =COUNTIF(Stakeholders!$E$2:$E960,F30) -> 1 | H30: Global Futures Reports: Alternative Futures of Geopolitical Competition in a Post-Covid-19 World | I30: https://apps.dtic.mil/sti/citations/AD1108029 | J30: sim | K30: sim | L30: sim | M30: não | N30: sim | O30: sim | P30: não | Q30: não | R30: sim | S30: não | T30: não | U30: sim | V30: competição geopolítica | W30: sim | X30: geopolítica espacial | Y30: cadeia de suprimentos | Z30: sistemas autônomos | AA30: O relatório compila uma série de análises feitas por diversos especialistas, que abordam temas que vão desde métodos para estudos de futuros até tendências, especialmente com relação à competição geopolítica do mundo pós covid COVID-19. Por ser um documento elaborado pela força aérea dos EUA, a análise tem foco nos assuntos mais afetos às questões aero espaciais. Com relação a métodos, o relatório apresenta o “four futures method”, também chamado de “manoa school method”, que é semelhante ao que conhecemos como “eixos ortogonais”, mas obrigatoriamente considera um cenário de colapso, um de crescimento, um de transformação e um disciplinado. Com relação às tendências, elas focam no aspecto geopolítico, mas também perpassam temas que envolvem cybertecnologia e competição espacial, cadeia de suprimentos e campanhas políticas nocivas. Os 4 cenários vislumbrados no relatório são: Transformação: FROM BIO-HEGEMONY TO BIO-SUPREMACY Colapso: THE NEW WARRING STATES PERIOD Disciplina: AUTHORITARIAN REGIONALISM Crescimento: ENDEMIC DISRUPTION | AB30: Yasmim | AC30: 44323 | AD30: 29 | AE30: =VLOOKUP(F30,Stakeholders!E:K,7,0) -> 19 | AF30: =VLOOKUP(B30&D30,Areas!$D:$E,2,FALSE) -> 283 | AH30: 1 - Projeto Prospecta Parte 02 - 2022 | AI30: =COUNTIF(Stakeholders!$E$2:$E$114,F30) -> 1
A31: 2021 | B31: América do Norte | C31: EUA | D31: Global | E31: EUA | F31: National intelligence council | G31: =COUNTIF(Stakeholders!$E$2:$E960,F31) -> 1 | H31: Global Trends 2040 - A More Contested World | I31: https://www.dni.gov/files/images/globalTrends/GT2040/GlobalTrends_2040_for_web1.pdf | J31: não | K31: sim | W31: não | AB31: Yasmim | AC31: 44327 | AD31: 30 | AE31: =VLOOKUP(F31,Stakeholders!E:K,7,0) -> 21 | AF31: =VLOOKUP(B31&D31,Areas!$D:$E,2,FALSE) -> 283 | AH31: 1 - Projeto Prospecta Parte 02 - 2022 | AI31: =COUNTIF(Stakeholders!$E$2:$E$114,F31) -> 1
A32: 2020 | B32: América do Norte | C32: EUA | D32: Oriente Médio | E32: EUA | F32: Middle East Institute | G32: =COUNTIF(Stakeholders!$E$2:$E960,F32) -> 1 | H32: Middle East Conflict and COVID-19 - A View from 2025. | I32: https://www.mei.edu/publications/middle-east-conflict-and-covid-19-view-2025 | J32: não | K32: sim | L32: não | M32: sim | N32: sim | O32: não | P32: não | Q32: não | R32: não | S32: não | T32: não | U32: não | W32: não | X32: Impactos da covid | Y32: Crescimento econômico | Z32: mortalidade | AA32: O relatório apresenta dois produtos: 1. Cenários a respeito dos impactos da COVID-19 África. 2. Uma comparação com um cenário pré-covid (uma projeção feita pelo FMI em outubro de 2019) Esses produtos, por sua vez, possibilitaram a sugestão de políticas públicas para reduzir a fragilidade da África perante a COVID. O relatório passa pelo método de maneira superficial e indireta. Em alguns momentos é possível apreender os processos metodológicos utilizados no estudo, que vão sendo descritos de maneira fracionada ao longo do relatório, na medida em que vão sendo utiliuzados. Contudo, o método e as ferramentas utilizados para a construção dos cenários não é descrito e maneira detalhada. Como o estudo tem como base a projeção do FMI, que leva em considerações aspectos econômicos, o relatório segue a mesma linha, e foca sua atenção no crescimento econômico. Adicionalmente, o relatório também considera o impacto social por conta da mortalidade causada pelo vírus. | AB32: Yasmim | AC32: 44334 | AD32: 31 | AE32: =VLOOKUP(F32,Stakeholders!E:K,7,0) -> 28 | AF32: =VLOOKUP(B32&D32,Areas!$D:$E,2,FALSE) -> #N/A | AH32: 1 - Projeto Prospecta Parte 02 - 2022 | AI32: =COUNTIF(Stakeholders!$E$2:$E$114,F32) -> 1
A33: 2018 | B33: América do Norte | C33: EUA | D33: Oriente Médio | E33: EUA | F33: The brookings | G33: =COUNTIF(Stakeholders!$E$2:$E960,F33) -> 1 | H33: Forecasting change in militaru technology, 2020-2040 | I33: https://www.brookings.edu/research/forecasting-change-in-military-technology-2020-2040/ | J33: sim | K33: sim | W33: não | AB33: Yasmim | AC33: 44372 | AD33: 32 | AE33: =VLOOKUP(F33,Stakeholders!E:K,7,0) -> 31 | AF33: =VLOOKUP(B33&D33,Areas!$D:$E,2,FALSE) -> #N/A | AH33: 1 - Projeto Prospecta Parte 02 - 2022 | AI33: =COUNTIF(Stakeholders!$E$2:$E$114,F33) -> 1
A34: 2020 | B34: Europa | C34: Noruega | D34: Noruega | E34: Noruega | F34: Norwegian Ministry of defence | G34: =COUNTIF(Stakeholders!$E$2:$E960,F34) -> 1 | H34: The defence of Norway: Capability and readiness | I34: https://drive.google.com/file/d/1NNrgO9zaie7enkXDuP15XpbIwCDApvYH/view?usp=drivesdk | J34: sim | K34: não | L34: não | M34: não | N34: não | O34: não | P34: não | Q34: não | R34: sim | S34: não | T34: não | U34: não | W34: não | X34: Noruega | Y34: defesa | AA34: -->Sementes: Ainda que o texto possa trazer um ou outro indício de mudança no cenário geopolítico não apresenta nenhum elemento que possa indicar o acontecimento de tais eventos. Há, contudo, uma cenarização a partir das mudanças esperadas. Este cenário, ainda contempla tanto elementos de alcance global quanto regionais; --> Política/geopolítica: Apesar de falar bastante sobre a situação geopolítica onde a Noruega está inserida, o texto não foca neste aspecto, sendo ele tão somente uma contextualização para o restante do texto; --> Econômico/Social: Apesar do documento expressar diversas vezes a necessidade das FA trabalharem em conjunto com a população civil e da importância desta para a estratégia de defesa e prontidão do país, não há nada que trate especificamente do fator social; --> Tecnológico: o documento traz referências à necessidade do crescente desenvolvimento tecnológico para a segurança do país e também à necessidade da cooperação civil-militar para que se logre tal objetivo. Entretanto, não aprofunda no assunto; —>Militar/Marítimo/Terrestre/Aeroespacial: o texto aborda assuntos militares, porém relacionados às FA norueguesas. Trata muito brevemente dos seus braços (marinha, exército, aeronáutica e forças especiais), onde apresenta objetivamente os objetivos de continuidade, modernização e substituição de alguns de seus meios além da incorporação de novos. Não trata de assuntos correlatos a nenhum dos poderes militares (Marítimo/Terrestre/Aeroespacial). Há entretanto um único apontamento ao poder marítimo, especificamente sobre a importância das linhas de comunicação marítimas no Atlântico no caso de crise ou conflito. | AB34: Laura | AD34: 33 | AE34: =VLOOKUP(F34,Stakeholders!E:K,7,0) -> 79 | AF34: =VLOOKUP(B34&D34,Areas!$D:$E,2,FALSE) -> 225 | AH34: 1 - Projeto Prospecta Parte 02 - 2022 | AI34: =COUNTIF(Stakeholders!$E$2:$E$114,F34) -> 1
A35: 2019 | B35: Europa | C35: Portugal | D35: Portugal | E35: Portugal | F35: Serviço de Informação de Segurança | G35: =COUNTIF(Stakeholders!$E$2:$E960,F35) -> 1 | H35: Relatório Anual de Segurança Interna | I35: https://drive.google.com/file/d/1Nbvycddazj4n2iSMZi1yfPzGcGvQfHgI/view?usp=drivesdk | AB35: Laura | AD35: 34 | AE35: =VLOOKUP(F35,Stakeholders!E:K,7,0) -> 82 | AF35: =VLOOKUP(B35&D35,Areas!$D:$E,2,FALSE) -> 229 | AH35: 1 - Projeto Prospecta Parte 02 - 2022 | AI35: =COUNTIF(Stakeholders!$E$2:$E$114,F35) -> 1
A36: 2015 | B36: Europa | C36: Reino Unido | D36: Reino Unido | E36: Reino Unido | F36: Government of UK | G36: =COUNTIF(Stakeholders!$E$2:$E960,F36) -> 1 | H36: National Security Strategy and Strategic Defence and Security Review 2015 | I36: https://drive.google.com/file/d/1NslfWBcFpm-5Modcur0Abed3t2ZRkVij/view?usp=drivesdk | AB36: Laura | AD36: 35 | AE36: =VLOOKUP(F36,Stakeholders!E:K,7,0) -> 83 | AF36: =VLOOKUP(B36&D36,Areas!$D:$E,2,FALSE) -> 231 | AH36: 1 - Projeto Prospecta Parte 02 - 2022 | AI36: =COUNTIF(Stakeholders!$E$2:$E$114,F36) -> 1
A37: 2012 | B37: Europa | C37: República Tcheca | D37: República Tcheca | E37: República Tcheca | F37: Ministry of Defence of the Czech Republic | G37: =COUNTIF(Stakeholders!$E$2:$E960,F37) -> 1 | H37: The Defence Strategy Of The Czech Republic | I37: https://drive.google.com/file/d/1NgvWDFjTH0oLB-GEgdeJQb5kqXv05uzw/view?usp=drivesdk | AB37: Laura | AD37: 36 | AE37: =VLOOKUP(F37,Stakeholders!E:K,7,0) -> 84 | AF37: =VLOOKUP(B37&D37,Areas!$D:$E,2,FALSE) -> 233 | AH37: 1 - Projeto Prospecta Parte 02 - 2022 | AI37: =COUNTIF(Stakeholders!$E$2:$E$114,F37) -> 1
A38: 2020 | B38: Europa | C38: Romênia | D38: Romênia | E38: Austria | F38: ETH Zurich Center for Security Studies | G38: =COUNTIF(Stakeholders!$E$2:$E960,F38) -> 1 | H38: Romania's National Cybersecurity and Defense Posture | I38: https://css.ethz.ch/content/dam/ethz/special-interest/gess/cis/center-for-securities-studies/pdfs/Cyber-Reports-2020-10-Romania.pdf | AB38: Laura | AD38: 37 | AE38: =VLOOKUP(F38,Stakeholders!E:K,7,0) -> 65 | AF38: =VLOOKUP(B38&D38,Areas!$D:$E,2,FALSE) -> 235 | AH38: 1 - Projeto Prospecta Parte 02 - 2022 | AI38: =COUNTIF(Stakeholders!$E$2:$E$114,F38) -> 1
A39: 2015 | B39: Europa | C39: Suécia | D39: Suécia | E39: Suécia | F39: Government offices of sweden | G39: =COUNTIF(Stakeholders!$E$2:$E960,F39) -> 1 | H39: Security in a new era | I39: https://drive.google.com/file/d/1NvceA155DVBBp6MD5VOCH2bbX6sy_oLu/view?usp=drivesdk | AB39: Laura | AD39: 38 | AE39: =VLOOKUP(F39,Stakeholders!E:K,7,0) -> 87 | AF39: =VLOOKUP(B39&D39,Areas!$D:$E,2,FALSE) -> 238 | AH39: 1 - Projeto Prospecta Parte 02 - 2022 | AI39: =COUNTIF(Stakeholders!$E$2:$E$114,F39) -> 1
A40: 2009 | B40: Europa | C40: Suíça | D40: Suíça | E40: Austria | F40: ETH Zurich Center for Security Studies | G40: =COUNTIF(Stakeholders!$E$2:$E960,F40) -> 1 | H40: The Swiss Security Policy Report: Key Points and Debates | I40: https://drive.google.com/file/d/1OR1b8-pI0nx6H1kfNIxhfSWtcIcUyiez/view?usp=drivesdk | AB40: Laura | AD40: 39 | AE40: =VLOOKUP(F40,Stakeholders!E:K,7,0) -> 65 | AF40: =VLOOKUP(B40&D40,Areas!$D:$E,2,FALSE) -> 240 | AH40: 1 - Projeto Prospecta Parte 02 - 2022 | AI40: =COUNTIF(Stakeholders!$E$2:$E$114,F40) -> 1
A41: 2015 | B41: Europa | C41: Noruega | D41: Montenegro | E41: Noruega | F41: Agency for Public Management and eGovernment | G41: =COUNTIF(Stakeholders!$E$2:$E960,F41) -> 1 | H41: Montenegro: Building integrity in the defence sector | I41: https://drive.google.com/file/d/1OZb4Oz_X7-CQ0hsum13M-zwaFG9RotAO/view?usp=drivesdk | AB41: Laura | AD41: 40 | AE41: =VLOOKUP(F41,Stakeholders!E:K,7,0) -> 78 | AF41: =VLOOKUP(B41&D41,Areas!$D:$E,2,FALSE) -> 224 | AH41: 1 - Projeto Prospecta Parte 02 - 2022 | AI41: =COUNTIF(Stakeholders!$E$2:$E$114,F41) -> 1
A42: 2021 | B42: África | C42: Noruega | D42: Africa | E42: África do Sul | F42: Institute for Security Studies (ISS) | G42: =COUNTIF(Stakeholders!$E$2:$E960,F42) -> 1 | H42: Africa’s combined exclusive maritime zone concept | I42: https://issafrica.org/research/africa-report/africas-combined-exclusive-maritime-zone-concept | J42: sim | K42: sim | W42: não | AB42: Giulia | AC42: 2 de maio | AD42: 41 | AE42: =VLOOKUP(F42,Stakeholders!E:K,7,0) -> 1 | AF42: =VLOOKUP(B42&D42,Areas!$D:$E,2,FALSE) -> #N/A | AH42: 1 - Projeto Prospecta Parte 02 - 2022 | AI42: =COUNTIF(Stakeholders!$E$2:$E$114,F42) -> 1
A43: 2021 | B43: África | C43: Dinamarca | D43: Africa | E43: África do Sul | F43: Institute for Security Studies (ISS) | G43: =COUNTIF(Stakeholders!$E$2:$E960,F43) -> 1 | H43: Peace and Security Council Report No 132 | I43: https://issafrica.org/research/peace-and-security-council-report/peace-and-security-council-report-no-132 | J43: sim | K43: sim | W43: não | AB43: Giulia | AC43: 2 de maio | AD43: 42 | AE43: =VLOOKUP(F43,Stakeholders!E:K,7,0) -> 1 | AF43: =VLOOKUP(B43&D43,Areas!$D:$E,2,FALSE) -> #N/A | AH43: 1 - Projeto Prospecta Parte 02 - 2022 | AI43: =COUNTIF(Stakeholders!$E$2:$E$114,F43) -> 1
A44: 2020 | B44: Europa | C44: EUA | D44: África | E44: EUA | F44: United States African Command (AFRICOM) | G44: =COUNTIF(Stakeholders!$E$2:$E960,F44) -> 1 | H44: A secure and stable Africa is an enduring American interest | I44: https://www.africom.mil/about-the-command/2020-posture-statement-to-congress | J44: sim | K44: sim | W44: não | AB44: Giulia | AC44: 2 de maio | AD44: 43 | AE44: =VLOOKUP(F44,Stakeholders!E:K,7,0) -> 2 | AF44: =VLOOKUP(B44&D44,Areas!$D:$E,2,FALSE) -> #N/A | AH44: 1 - Projeto Prospecta Parte 02 - 2022 | AI44: =COUNTIF(Stakeholders!$E$2:$E$114,F44) -> 1
A45: 2020 | B45: Europa | C45: União Europeia | D45: Senegal, Mali, Mauritania, Algeria, Niger, Camarões, República Centro Africana, Sudão do Sul, Etiopia, Eritreia, Benin, Burkina Faso, Cape Verde, Ivory Coast, Gambia, Ghana, Guinea, Guinea-Bissau, Liberia, Nigeria, Saint Helena, Ascension and Tristan da Cunha, Sierra Leone, Togo, Burundi, Djibouti, Kenya, Rwanda, Somalia, Sudan, Tanzania, Uganda | E45: União Europeia | F45: European Parliament (EUROPARL) | G45: 1 | H45: EU-African security cooperation in the Sahel region, West Africa and the Horn of Africa | I45: https://www.europarl.europa.eu/doceo/document/A-9-2020-0129_EN.html | J45: sim | K45: sim | W45: não | AB45: Giulia | AC45: 2 de maio | AD45: 44 | AE45: 3 | AF45: #N/A | AH45: 1 - Projeto Prospecta Parte 02 - 2022 | AI45: HELDERV2 | AJ45: HELDERV2
A46: 2020 | B46: América do Norte | C46: África | D46: África | E46: EUA | F46: Atlantic Council | G46: =COUNTIF(Stakeholders!$E$2:$E960,F46) -> 1 | H46: African agency in the new Cold War: Traditional power competition in the post-COVID-19 African landscape | I46: https://www.atlanticcouncil.org/in-depth-research-reports/report/african-agency-in-the-new-cold-war-traditional-power-competition-in-the-post-covid-19-african-landscape/ | J46: sim | K46: sim | W46: não | AB46: Giulia | AC46: 2 de maio | AD46: 45 | AE46: =VLOOKUP(F46,Stakeholders!E:K,7,0) -> 32 | AF46: =VLOOKUP(B46&D46,Areas!$D:$E,2,FALSE) -> #N/A | AH46: 1 - Projeto Prospecta Parte 02 - 2022 | AI46: =COUNTIF(Stakeholders!$E$2:$E$114,F46) -> 1
A47: 2020 | B47: América do Norte | C47: África | D47: África | E47: EUA | F47: Atlantic Council | G47: =COUNTIF(Stakeholders!$E$2:$E960,F47) -> 1 | H47: Why Africa matters to US national security | I47: https://www.atlanticcouncil.org/in-depth-research-reports/report/why-africa-matters-to-us-national-security/ | J47: sim | K47: sim | W47: não | AB47: Giulia | AC47: 2 de maio | AD47: 46 | AE47: =VLOOKUP(F47,Stakeholders!E:K,7,0) -> 32 | AF47: =VLOOKUP(B47&D47,Areas!$D:$E,2,FALSE) -> #N/A | AH47: 1 - Projeto Prospecta Parte 02 - 2022 | AI47: =COUNTIF(Stakeholders!$E$2:$E$114,F47) -> 1
A48: 2020 | B48: América do Norte | C48: EUA | D48: Nigéria | E48: EUA | F48: Rand Corporation | G48: =COUNTIF(Stakeholders!$E$2:$E960,F48) -> 1 | H48: Countering Violent Extremism in Nigeria | I48: https://www.rand.org/pubs/research_reports/RR4257.html | J48: sim | K48: sim | W48: não | AB48: Giulia | AC48: 2 de maio | AD48: 47 | AE48: =VLOOKUP(F48,Stakeholders!E:K,7,0) -> 20 | AF48: =VLOOKUP(B48&D48,Areas!$D:$E,2,FALSE) -> #N/A | AH48: 1 - Projeto Prospecta Parte 02 - 2022 | AI48: =COUNTIF(Stakeholders!$E$2:$E$114,F48) -> 1
A49: 2020 | B49: África | C49: Dinamarca | D49: Africa | E49: África do Sul | F49: Institute for Security Studies (ISS) | G49: =COUNTIF(Stakeholders!$E$2:$E960,F49) -> 1 | H49: Peace and Security Council Report No 131 | I49: https://issafrica.org/research/peace-and-security-council-report/peace-and-security-council-report-no-131 | J49: sim | K49: não | W49: sim | AB49: Giulia | AC49: 2 de maio | AD49: 48 | AE49: =VLOOKUP(F49,Stakeholders!E:K,7,0) -> 1 | AF49: =VLOOKUP(B49&D49,Areas!$D:$E,2,FALSE) -> #N/A | AH49: 1 - Projeto Prospecta Parte 02 - 2022 | AI49: =COUNTIF(Stakeholders!$E$2:$E$114,F49) -> 1
A50: 2020 | B50: África | C50: Sem país específico | D50: Africa | E50: África do Sul | F50: Institute for Security Studies (ISS) | G50: =COUNTIF(Stakeholders!$E$2:$E960,F50) -> 1 | H50: Impact of COVID-19 in Africa: a scenario analysis to 2030 | I50: https://issafrica.org/research/africa-report/impact-of-covid-19-in-africa-a-scenario-analysis-to-2030 | J50: sim | K50: não | W50: sim | AB50: Giulia | AC50: 2 de maio | AD50: 49 | AE50: =VLOOKUP(F50,Stakeholders!E:K,7,0) -> 1 | AF50: =VLOOKUP(B50&D50,Areas!$D:$E,2,FALSE) -> #N/A | AH50: 1 - Projeto Prospecta Parte 02 - 2022 | AI50: =COUNTIF(Stakeholders!$E$2:$E$114,F50) -> 1
A51: 2020 | B51: África | C51: Noruega | D51: Africa | E51: África do Sul | F51: Institute for Security Studies (ISS) | G51: =COUNTIF(Stakeholders!$E$2:$E960,F51) -> 1 | H51: Beyond 2020: exploring the potential for a stronger UN-AU peacebuilding partnership | I51: https://issafrica.org/research/africa-report/beyond-2020-exploring-the-potential-for-a-stronger-un-au-peacebuilding-partnership | J51: sim | K51: não | W51: sim | AB51: Giulia | AC51: 2 de maio | AD51: 50 | AE51: =VLOOKUP(F51,Stakeholders!E:K,7,0) -> 1 | AF51: =VLOOKUP(B51&D51,Areas!$D:$E,2,FALSE) -> #N/A | AH51: 1 - Projeto Prospecta Parte 02 - 2022 | AI51: =COUNTIF(Stakeholders!$E$2:$E$114,F51) -> 1
A52: 2020 | B52: África | C52: Sem país específico | D52: Tunísia | E52: África do Sul | F52: Institute for Security Studies (ISS) | G52: =COUNTIF(Stakeholders!$E$2:$E960,F52) -> 1 | H52: The rebirth: Tunisia’s potential development pathways to 2040 | I52: https://issafrica.org/research/north-africa-report/the-rebirth-tunisias-potential-development-pathways-to-2040 | J52: sim | K52: não | W52: sim | AB52: Giulia | AC52: 2 de maio | AD52: 51 | AE52: =VLOOKUP(F52,Stakeholders!E:K,7,0) -> 1 | AF52: =VLOOKUP(B52&D52,Areas!$D:$E,2,FALSE) -> #N/A | AH52: 1 - Projeto Prospecta Parte 02 - 2022 | AI52: =COUNTIF(Stakeholders!$E$2:$E$114,F52) -> 1
A53: 2020 | B53: África | C53: Reino Unido | D53: Africa do Sul | E53: África do Sul | F53: Institute for Security Studies (ISS) | G53: =COUNTIF(Stakeholders!$E$2:$E960,F53) -> 1 | H53: Looking back, looking forward: South Africa in the UN Security Council | I53: https://issafrica.org/research/africa-report/looking-back-looking-forward-south-africa-in-the-un-security-council | J53: sim | K53: não | W53: sim | AB53: Giulia | AC53: 2 de maio | AD53: 52 | AE53: =VLOOKUP(F53,Stakeholders!E:K,7,0) -> 1 | AF53: =VLOOKUP(B53&D53,Areas!$D:$E,2,FALSE) -> #N/A | AH53: 1 - Projeto Prospecta Parte 02 - 2022 | AI53: =COUNTIF(Stakeholders!$E$2:$E$114,F53) -> 1
A54: 2020 | B54: América do Norte | C54: Sem país específico | D54: África | E54: EUA | F54: The brookings Africa Growth Initiative | G54: =COUNTIF(Stakeholders!$E$2:$E960,F54) -> 1 | H54: Foresight Africa: Top priorities for the continent 2020-2030 | I54: https://www.brookings.edu/wp-content/uploads/2020/01/ForesightAfrica2020_20200110.pdf | J54: sim | K54: não | W54: sim | AB54: Giulia | AC54: 2 de maio | AD54: 53 | AE54: =VLOOKUP(F54,Stakeholders!E:K,7,0) -> 30 | AF54: =VLOOKUP(B54&D54,Areas!$D:$E,2,FALSE) -> #N/A | AH54: 1 - Projeto Prospecta Parte 02 - 2022 | AI54: =COUNTIF(Stakeholders!$E$2:$E$114,F54) -> 1
A55: 2020 | B55: Europa | C55: Sem país específico | D55: África | E55: França | F55: Report Linker | G55: =COUNTIF(Stakeholders!$E$2:$E960,F55) -> 1 | H55: Air Defense Systems Market - Growth, Trends, and Forecasts (2020 - 2025) | I55: https://www.reportlinker.com/p05893157/Air-Defense-Systems-Market-Growth-Trends-and-Forecasts.html | J55: sim | K55: não | W55: sim | AA55: Só coloquei esse que é pago mas são relatórios bem especificos e usados pelas empresas para tomada de decisão. Talvez seja interessante saber que existe esse site. | AB55: Giulia | AC55: 2 de maio | AD55: 54 | AE55: =VLOOKUP(F55,Stakeholders!E:K,7,0) -> 4 | AF55: =VLOOKUP(B55&D55,Areas!$D:$E,2,FALSE) -> #N/A | AH55: 1 - Projeto Prospecta Parte 02 - 2022 | AI55: =COUNTIF(Stakeholders!$E$2:$E$114,F55) -> 1
A56: 2020 | B56: Organismo Internacional | C56: ONU | D56: Global | E56: United Nations Peacekeeping | F56: United Nations Peacekeeping | G56: =COUNTIF(Stakeholders!$E$2:$E960,F56) -> 1 | H56: The Future of Peace Operations: A Scenario Analysis, 2020-2030 | I56: https://peacekeeping.un.org/sites/default/files/fopo_scenarios_paul_williams_final.pdf | J56: sim | K56: sim | W56: sim | AA56: Global mas com grande ênfase na Africa | AB56: Giulia | AC56: 2 de maio | AD56: 55 | AE56: =VLOOKUP(F56,Stakeholders!E:K,7,0) -> 5 | AF56: =VLOOKUP(B56&D56,Areas!$D:$E,2,FALSE) -> #N/A | AH56: 1 - Projeto Prospecta Parte 02 - 2022 | AI56: =COUNTIF(Stakeholders!$E$2:$E$114,F56) -> 1
A57: 2020 | B57: Organismo Internacional | C57: ONU | D57: Global | E57: United Nations Peacekeeping | F57: United Nations Peacekeeping | G57: =COUNTIF(Stakeholders!$E$2:$E960,F57) -> 1 | H57: THE FUTURE OF UN PEACE OPERATIONS IN A CHANGING CONFLICT ENVIRONMENT | I57: https://peacekeeping.un.org/sites/default/files/future_of_peacekeeping_operations_in_a_changing_conflict_environment.pdf | J57: sim | K57: sim | W57: não | AA57: Global mas com grande ênfase na Africa | AB57: Giulia | AC57: 2 de maio | AD57: 56 | AE57: =VLOOKUP(F57,Stakeholders!E:K,7,0) -> 5 | AF57: =VLOOKUP(B57&D57,Areas!$D:$E,2,FALSE) -> #N/A | AH57: 1 - Projeto Prospecta Parte 02 - 2022 | AI57: =COUNTIF(Stakeholders!$E$2:$E$114,F57) -> 1
A58: 2020 | B58: Organismo Internacional | C58: ONU | D58: Global | E58: United Nations Peacekeeping | F58: United Nations Peacekeeping | G58: =COUNTIF(Stakeholders!$E$2:$E960,F58) -> 1 | H58: Estimating future conflict risks and conflict prevention implications by 2030 | I58: https://peacekeeping.un.org/sites/default/files/estimating_future_conflict_risks_and_conflict_prevention_implications_by_2030.pdf | J58: sim | K58: sim | W58: não | AA58: Global mas com grande ênfase na Africa | AB58: Giulia | AC58: 2 de maio | AD58: 57 | AE58: =VLOOKUP(F58,Stakeholders!E:K,7,0) -> 5 | AF58: =VLOOKUP(B58&D58,Areas!$D:$E,2,FALSE) -> #N/A | AH58: 1 - Projeto Prospecta Parte 02 - 2022 | AI58: =COUNTIF(Stakeholders!$E$2:$E$114,F58) -> 1
A59: 2020 | B59: Organismo Internacional | C59: ONU | D59: Global | E59: United Nations Peacekeeping | F59: United Nations Peacekeeping | G59: =COUNTIF(Stakeholders!$E$2:$E960,F59) -> 1 | H59: The Future of UN Peacekeeping and Parallel Operations | I59: https://peacekeeping.un.org/sites/default/files/the_future_of_peacekeeping_and_parallel_operations.pdf | J59: sim | K59: sim | W59: não | AA59: Global mas com grande ênfase na Africa | AB59: Giulia | AC59: 2 de maio | AD59: 58 | AE59: =VLOOKUP(F59,Stakeholders!E:K,7,0) -> 5 | AF59: =VLOOKUP(B59&D59,Areas!$D:$E,2,FALSE) -> #N/A | AH59: 1 - Projeto Prospecta Parte 02 - 2022 | AI59: =COUNTIF(Stakeholders!$E$2:$E$114,F59) -> 1
A60: 2020 | B60: Organismo Internacional | C60: ONU | D60: Global | E60: United Nations Peacekeeping | F60: United Nations Peacekeeping | G60: =COUNTIF(Stakeholders!$E$2:$E960,F60) -> 1 | H60: The Future of UN Peacekeeping: Reflections on Strengthening the Role of Peacekeeping in Sustaining Peace from a Security Sector Reform Perspective1 | I60: https://peacekeeping.un.org/sites/default/files/dcaf_future_of_un_peacekeeping_from_ssr_perspective.pdf | J60: sim | K60: sim | W60: não | AA60: Global mas com grande ênfase na Africa | AB60: Giulia | AC60: 2 de maio | AD60: 59 | AE60: =VLOOKUP(F60,Stakeholders!E:K,7,0) -> 5 | AF60: =VLOOKUP(B60&D60,Areas!$D:$E,2,FALSE) -> #N/A | AH60: 1 - Projeto Prospecta Parte 02 - 2022 | AI60: =COUNTIF(Stakeholders!$E$2:$E$114,F60) -> 1
A61: 2019 | B61: Europa | C61: Sem país específico | D61: África | E61: Suécia | F61: Stockholm International Peace Research Institute | G61: =COUNTIF(Stakeholders!$E$2:$E960,F61) -> 1 | H61: The Foreign Military Presence in the Horn of Africa Region | I61: https://www.sipri.org/publications/2019/sipri-background-papers/foreign-military-presence-horn-africa-region | J61: sim | K61: não | W61: sim | AB61: Giulia | AC61: 2 de maio | AD61: 60 | AE61: =VLOOKUP(F61,Stakeholders!E:K,7,0) -> 88 | AF61: =VLOOKUP(B61&D61,Areas!$D:$E,2,FALSE) -> #N/A | AH61: 1 - Projeto Prospecta Parte 02 - 2022 | AI61: =COUNTIF(Stakeholders!$E$2:$E$114,F61) -> 1
A62: 2019 | B62: Europa | C62: Sem país específico | D62: África | E62: Suécia | F62: Stockholm International Peace Research Institute | G62: =COUNTIF(Stakeholders!$E$2:$E960,F62) -> 1 | H62: The New External Security Politics of the Horn of Africa Region | I62: https://www.sipri.org/publications/2019/sipri-insights-peace-and-security/new-external-security-politics-horn-africa-region | J62: sim | K62: não | W62: sim | AB62: Giulia | AC62: 2 de maio | AD62: 61 | AE62: =VLOOKUP(F62,Stakeholders!E:K,7,0) -> 88 | AF62: =VLOOKUP(B62&D62,Areas!$D:$E,2,FALSE) -> #N/A | AH62: 1 - Projeto Prospecta Parte 02 - 2022 | AI62: =COUNTIF(Stakeholders!$E$2:$E$114,F62) -> 1
A63: 2019 | B63: Europa | C63: Sem país específico | D63: África | E63: Suécia | F63: Stockholm International Peace Research Institute | G63: =COUNTIF(Stakeholders!$E$2:$E960,F63) -> 1 | H63: Securing Legitimate Stability in the DRC: External Assumptions and Local Perspectives | I63: https://www.sipri.org/publications/2019/other-publications/securing-legitimate-stability-drc-external-assumptions-and-local-perspectives | J63: sim | K63: não | W63: sim | AB63: Giulia | AC63: 2 de maio | AD63: 62 | AE63: =VLOOKUP(F63,Stakeholders!E:K,7,0) -> 88 | AF63: =VLOOKUP(B63&D63,Areas!$D:$E,2,FALSE) -> #N/A | AH63: 1 - Projeto Prospecta Parte 02 - 2022 | AI63: =COUNTIF(Stakeholders!$E$2:$E$114,F63) -> 1
A64: 2019 | B64: Europa | C64: Sem país específico | D64: África | E64: Suécia | F64: Stockholm International Peace Research Institute | G64: =COUNTIF(Stakeholders!$E$2:$E960,F64) -> 1 | H64: Securing Legitimate Stability in CAR: External Assumptions and Local Perspectives | I64: https://www.sipri.org/publications/2019/other-publications/securing-legitimate-stability-car-external-assumptions-and-local-perspectives | J64: sim | K64: não | W64: sim | AB64: Giulia | AC64: 2 de maio | AD64: 63 | AE64: =VLOOKUP(F64,Stakeholders!E:K,7,0) -> 88 | AF64: =VLOOKUP(B64&D64,Areas!$D:$E,2,FALSE) -> #N/A | AH64: 1 - Projeto Prospecta Parte 02 - 2022 | AI64: =COUNTIF(Stakeholders!$E$2:$E$114,F64) -> 1
A65: 2019 | B65: Europa | C65: Sem país específico | D65: África | E65: Suécia | F65: Stockholm International Peace Research Institute | G65: =COUNTIF(Stakeholders!$E$2:$E960,F65) -> 1 | H65: Towards Legitimate Stability in CAR and the DRC: External Assumptions and Local Perspectives | I65: https://www.sipri.org/publications/2019/other-publications/towards-legitimate-stability-car-and-drc-external-assumptions-and-local-perspectives | J65: sim | K65: não | W65: sim | AB65: Giulia | AC65: 2 de maio | AD65: 64 | AE65: =VLOOKUP(F65,Stakeholders!E:K,7,0) -> 88 | AF65: =VLOOKUP(B65&D65,Areas!$D:$E,2,FALSE) -> #N/A | AH65: 1 - Projeto Prospecta Parte 02 - 2022 | AI65: =COUNTIF(Stakeholders!$E$2:$E$114,F65) -> 1
A66: 2019 | B66: América do Norte | C66: EUA | D66: África | E66: EUA | F66: RAND Corporation | G66: =COUNTIF(Stakeholders!$E$2:$E960,F66) -> 1 | H66: Africa's Role in Nation-Building | I66: https://www.rand.org/pubs/research_reports/RR2978.html | J66: sim | K66: não | W66: sim | AB66: Giulia | AC66: 2 de maio | AD66: 65 | AE66: =VLOOKUP(F66,Stakeholders!E:K,7,0) -> 20 | AF66: =VLOOKUP(B66&D66,Areas!$D:$E,2,FALSE) -> #N/A | AH66: 1 - Projeto Prospecta Parte 02 - 2022 | AI66: =COUNTIF(Stakeholders!$E$2:$E$114,F66) -> 1
A67: 2019 | B67: África | C67: Sem país específico | D67: Africa | E67: África do Sul | F67: Institute for Security Studies (ISS) | G67: =COUNTIF(Stakeholders!$E$2:$E960,F67) -> 1 | H67: Prospects for the G5 Sahel countries to 2040 | I67: https://issafrica.org/research/west-africa-report/prospects-for-the-g5-sahel-countries-to-2040 | J67: sim | K67: não | W67: sim | AB67: Giulia | AC67: 2 de maio | AD67: 66 | AE67: =VLOOKUP(F67,Stakeholders!E:K,7,0) -> 1 | AF67: =VLOOKUP(B67&D67,Areas!$D:$E,2,FALSE) -> #N/A | AH67: 1 - Projeto Prospecta Parte 02 - 2022 | AI67: =COUNTIF(Stakeholders!$E$2:$E$114,F67) -> 1
A68: 2020 | B68: África | C68: Sem país específico | D68: Africa | E68: África do Sul | F68: Institute for Security Studies (ISS) | G68: =COUNTIF(Stakeholders!$E$2:$E960,F68) -> 1 | H68: Why Africa’s development models must change: understanding five dynamic trends | I68: https://issafrica.org/research/africa-report/why-africas-development-models-must-change-understanding-five-dynamic-trends | J68: não | K68: sim | W68: não | AA68: Desenvolvimento | AB68: Giulia | AC68: 17 de maio | AD68: 67 | AE68: =VLOOKUP(F68,Stakeholders!E:K,7,0) -> 1 | AF68: =VLOOKUP(B68&D68,Areas!$D:$E,2,FALSE) -> #N/A | AH68: 1 - Projeto Prospecta Parte 02 - 2022 | AI68: =COUNTIF(Stakeholders!$E$2:$E$114,F68) -> 1
A69: 2020 | B69: África | C69: Noruega | D69: Africa | E69: África do Sul | F69: Institute for Security Studies (ISS) | G69: =COUNTIF(Stakeholders!$E$2:$E960,F69) -> 1 | H69: Maritime cyber security: getting Africa ready | I69: https://issafrica.org/research/africa-report/maritime-cyber-security-getting-africa-ready | J69: sim | K69: não | W69: sim | AA69: Cybersegurança | AB69: Giulia | AC69: 17 de maio | AD69: 68 | AE69: =VLOOKUP(F69,Stakeholders!E:K,7,0) -> 1 | AF69: =VLOOKUP(B69&D69,Areas!$D:$E,2,FALSE) -> #N/A | AH69: 1 - Projeto Prospecta Parte 02 - 2022 | AI69: =COUNTIF(Stakeholders!$E$2:$E$114,F69) -> 1
A70: 2021 | B70: África | C70: Suécia | D70: República democratica do Congo | E70: África do Sul | F70: Institute for Security Studies (ISS) | G70: =COUNTIF(Stakeholders!$E$2:$E960,F70) -> 1 | H70: Specific sectoral improvements could help the DRC realise its potential as a driver of economic growth in Africa. | I70: https://issafrica.org/research/central-africa-report/waking-the-sleeping-giant-development-pathways-for-the-democratic-republic-of-the-congo-to-2050 | J70: não | K70: sim | W70: não | AA70: Desenvolvimento | AB70: Giulia | AC70: 17 de maio | AD70: 69 | AE70: =VLOOKUP(F70,Stakeholders!E:K,7,0) -> 1 | AF70: =VLOOKUP(B70&D70,Areas!$D:$E,2,FALSE) -> #N/A | AH70: 1 - Projeto Prospecta Parte 02 - 2022 | AI70: =COUNTIF(Stakeholders!$E$2:$E$114,F70) -> 1
A71: 2020 | B71: Oceania | C71: Austrália | D71: Indonésia | E71: Austrália | F71: Sea Power Centre | G71: =COUNTIF(Stakeholders!$E$2:$E960,F71) -> 1 | H71: INDONESIA-AUSTRALIA MARITIME SECURITY: CHALLENGES AND COOPERATION | I71: https://www.navy.gov.au/sites/default/files/documents/spc/Indonesia_Australia_Challenges_.pdf | J71: sim | K71: não | W71: não | AB71: Helder | AC71: 44318 | AD71: 70 | AE71: =VLOOKUP(F71,Stakeholders!E:K,7,0) -> 99 | AF71: =VLOOKUP(B71&D71,Areas!$D:$E,2,FALSE) -> #N/A | AH71: 1 - Projeto Prospecta Parte 02 - 2022 | AI71: =COUNTIF(Stakeholders!$E$2:$E$114,F71) -> 1
A72: 2019 | B72: América do Norte | C72: Sem país específico | D72: EUA | E72: EUA | F72: Defense Department of USA | G72: =COUNTIF(Stakeholders!$E$2:$E960,F72) -> 1 | H72: DEPARTMENT-OF-DEFENSE-INDO-PACIFIC-STRATEGY-REPORT-2019 | I72: https://media.defense.gov/2019/Jul/01/2002152311/-1/-1/1/DEPARTMENT-OF-DEFENSE-INDO-PACIFIC-STRATEGY-REPORT-2019.PDF | J72: sim | K72: não | W72: não | AA72: Relatório produzido pela secretaria de defesa dos EUA com informações sobre países vizinhos pelo Pacífico | AB72: Helder | AC72: 44318 | AD72: 71 | AE72: =VLOOKUP(F72,Stakeholders!E:K,7,0) -> 103 | AF72: =VLOOKUP(B72&D72,Areas!$D:$E,2,FALSE) -> 56 | AH72: 1 - Projeto Prospecta Parte 02 - 2022 | AI72: =COUNTIF(Stakeholders!$E$2:$E$114,F72) -> 1
A73: 2020 | B73: Oceania | C73: Austrália | D73: Austrália | E73: Austrália | F73: Defense Department of Australia | G73: =COUNTIF(Stakeholders!$E$2:$E960,F73) -> 1 | H73: DEFENSE ANUAL REPORT 19-20 | I73: https://defence.gov.au/annualreports/ | J73: sim | K73: não | W73: não | AA73: Relatório anual sobre as atividades de defesa produzido pela secretaria de defesa da Austrália | AB73: Helder | AC73: 44318 | AD73: 72 | AE73: =VLOOKUP(F73,Stakeholders!E:K,7,0) -> 101 | AF73: =VLOOKUP(B73&D73,Areas!$D:$E,2,FALSE) -> 249 | AH73: 1 - Projeto Prospecta Parte 02 - 2022 | AI73: =COUNTIF(Stakeholders!$E$2:$E$114,F73) -> 1
A74: 2019 | B74: Oceania | C74: Austrália | D74: Austrália | E74: Austrália | F74: Sea Power Centre | G74: =COUNTIF(Stakeholders!$E$2:$E960,F74) -> 1 | H74: An Australian vision of the Indo-Pacific – Through a Strategic and Maritime Lens | I74: https://www.navy.gov.au/sites/default/files/documents/Australian_vision_of_Indo-Pacific_Through_Strategic_and_Maritime_Lens_0.pdf | J74: sim | K74: não | W74: não | AA74: Uma visão australiana do Indo-Pacífico - por meio de uma visão estratégica e Lente Marítima | AB74: Helder | AC74: 44318 | AD74: 73 | AE74: =VLOOKUP(F74,Stakeholders!E:K,7,0) -> 99 | AF74: =VLOOKUP(B74&D74,Areas!$D:$E,2,FALSE) -> 249 | AH74: 1 - Projeto Prospecta Parte 02 - 2022 | AI74: =COUNTIF(Stakeholders!$E$2:$E$114,F74) -> 1
A75: 2020 | B75: Oceania | C75: Austrália | D75: Austrália | E75: Austrália | F75: Defense Department of Australia | G75: =COUNTIF(Stakeholders!$E$2:$E960,F75) -> 1 | H75: Australian Journal of Defence and Strategic Studies Number 2 Vol2 | I75: https://www.defence.gov.au/adc/Publications/ajdss/documents/volume2-number2/WEB-AJDSS-complete-interactive.pdf | J75: sim | K75: não | W75: não | AA75: Estudos estratégicos de Defesa da Austrália Number 2 - Vol 2 | AB75: Helder | AC75: 44318 | AD75: 74 | AE75: =VLOOKUP(F75,Stakeholders!E:K,7,0) -> 101 | AF75: =VLOOKUP(B75&D75,Areas!$D:$E,2,FALSE) -> 249 | AH75: 1 - Projeto Prospecta Parte 02 - 2022 | AI75: =COUNTIF(Stakeholders!$E$2:$E$114,F75) -> 1
A76: 2020 | B76: Oceania | C76: Austrália | D76: Austrália | E76: Austrália | F76: Defense Department of Australia | G76: =COUNTIF(Stakeholders!$E$2:$E960,F76) -> 1 | H76: Australian Journal of Defence and Strategic Studies Number 2 Vol 1 | I76: https://www.defence.gov.au/adc/Publications/ajdss/documents/volume2-number1/JUN007-20-AJDSS-text_26082020.pdf | J76: sim | K76: não | W76: não | AA76: Estudos estratégicos de Defesa da Austrália Number 2 - Vol 1 | AB76: Helder | AC76: 44318 | AD76: 75 | AE76: =VLOOKUP(F76,Stakeholders!E:K,7,0) -> 101 | AF76: =VLOOKUP(B76&D76,Areas!$D:$E,2,FALSE) -> 249 | AH76: 1 - Projeto Prospecta Parte 02 - 2022 | AI76: =COUNTIF(Stakeholders!$E$2:$E$114,F76) -> 1
A77: 2019 | B77: Oceania | C77: Austrália | D77: Austrália | E77: Austrália | F77: Defense Department of Australia | G77: =COUNTIF(Stakeholders!$E$2:$E960,F77) -> 1 | H77: Australian Journal of Defence and Strategic Studies Number 1 Vol 1 | I77: https://www.defence.gov.au/ADC/Publications/AJDSS/documents/volume1-issue1/Full.pdf | J77: sim | K77: não | W77: não | AA77: Estudos estratégicos de Defesa da Austrália Number 1 - Vol 1 | AB77: Helder | AC77: 44318 | AD77: 76 | AE77: =VLOOKUP(F77,Stakeholders!E:K,7,0) -> 101 | AF77: =VLOOKUP(B77&D77,Areas!$D:$E,2,FALSE) -> 249 | AH77: 1 - Projeto Prospecta Parte 02 - 2022 | AI77: =COUNTIF(Stakeholders!$E$2:$E$114,F77) -> 1
A78: 2017 | B78: Oceania | C78: Austrália | D78: Singapura | E78: Austrália | F78: Defense Department of Australia | G78: =COUNTIF(Stakeholders!$E$2:$E960,F78) -> 1 | H78: The future of the security relationship between Singapore and Australia | I78: https://www.defence.gov.au/ADC/Publications/documents/IndoPac/2017/Tam_feb17.pdf | J78: sim | K78: não | W78: não | AA78: Estudo sobre a relação entre Singapura e Austrália | AB78: Helder | AC78: 44318 | AD78: 77 | AE78: =VLOOKUP(F78,Stakeholders!E:K,7,0) -> 101 | AF78: =VLOOKUP(B78&D78,Areas!$D:$E,2,FALSE) -> #N/A | AH78: 1 - Projeto Prospecta Parte 02 - 2022 | AI78: =COUNTIF(Stakeholders!$E$2:$E$114,F78) -> 1
A79: 2017 | B79: Oceania | C79: Austrália | D79: Indonésia | E79: Austrália | F79: Defense Department of Australia | G79: =COUNTIF(Stakeholders!$E$2:$E960,F79) -> 1 | H79: Defence diplomacy: the right ballast for Australia’s fragile relations with Indonesia | I79: https://www.defence.gov.au/ADC/Publications/documents/IndoPac/2017/Wilson_feb17.pdf | J79: sim | K79: não | W79: não | AA79: Estudo sobre Diplomacia de Defesa | AB79: Helder | AC79: 44318 | AD79: 78 | AE79: =VLOOKUP(F79,Stakeholders!E:K,7,0) -> 101 | AF79: =VLOOKUP(B79&D79,Areas!$D:$E,2,FALSE) -> #N/A | AH79: 1 - Projeto Prospecta Parte 02 - 2022 | AI79: =COUNTIF(Stakeholders!$E$2:$E$114,F79) -> 1
A80: 2017 | B80: Oceania | C80: Austrália | D80: Austrália | E80: Austrália | F80: Defense Department of Australia | G80: =COUNTIF(Stakeholders!$E$2:$E960,F80) -> 1 | H80: AUSTRALIA’S JOINT APPROACH PAST, PRESENT AND FUTURE | I80: https://www.defence.gov.au/ADC/Publications/documents/joint_studies/JSPS_1_Australias_Joint_Approach.PDF | J80: sim | K80: sim | W80: não | AA80: Estudo sobre a abordagem de Defesa da Austrália (presente, passado e futuro) | AB80: Helder | AC80: 44318 | AD80: 79 | AE80: =VLOOKUP(F80,Stakeholders!E:K,7,0) -> 101 | AF80: =VLOOKUP(B80&D80,Areas!$D:$E,2,FALSE) -> 249 | AH80: 1 - Projeto Prospecta Parte 02 - 2022 | AI80: =COUNTIF(Stakeholders!$E$2:$E$114,F80) -> 1
A81: 2020 | B81: Oceania | C81: Austrália | D81: Austrália | E81: Austrália | F81: Defense Department of Australia | G81: =COUNTIF(Stakeholders!$E$2:$E960,F81) -> 1 | H81: A Method for Ethical AI in Defence | I81: https://www.dst.defence.gov.au/sites/default/files/publications/documents/A%20Method%20for%20Ethical%20AI%20in%20Defence.pdf | J81: sim | K81: sim | W81: sim | AA81: Estudo sobre Ética no uso de IA | AB81: Helder | AC81: 44318 | AD81: 80 | AE81: =VLOOKUP(F81,Stakeholders!E:K,7,0) -> 101 | AF81: =VLOOKUP(B81&D81,Areas!$D:$E,2,FALSE) -> 249 | AH81: 1 - Projeto Prospecta Parte 02 - 2022 | AI81: =COUNTIF(Stakeholders!$E$2:$E$114,F81) -> 1
A82: 2020 | B82: Oceania | C82: Austrália | D82: Austrália | E82: Austrália | F82: Defense Department of Australia | G82: =COUNTIF(Stakeholders!$E$2:$E960,F82) -> 1 | H82: Recent Advances in Artificial Intelligence and their Impact on Defence | I82: https://www.dst.defence.gov.au/sites/default/files/publications/documents/DST-Group-TR-3716_0.pdf | J82: sim | K82: sim | W82: não | AA82: Estudo sobre os avanços da IA e suas implicações na defesa | AB82: Helder | AC82: 44318 | AD82: 81 | AE82: =VLOOKUP(F82,Stakeholders!E:K,7,0) -> 101 | AF82: =VLOOKUP(B82&D82,Areas!$D:$E,2,FALSE) -> 249 | AH82: 1 - Projeto Prospecta Parte 02 - 2022 | AI82: =COUNTIF(Stakeholders!$E$2:$E$114,F82) -> 1
A83: 2020 | B83: Oceania | C83: Austrália | D83: Austrália | E83: Austrália | F83: Defense Department of Australia | G83: =COUNTIF(Stakeholders!$E$2:$E960,F83) -> 1 | H83: ‘Skirmishing Mist’ Dismounted Infantry 2030 Concept | I83: https://www.dst.defence.gov.au/sites/default/files/publications/documents/DST-Group-GD-1071.pdf | J83: sim | K83: sim | W83: sim | AA83: The results of these studies provide recommendations for Australian Army’s consideration in order to inform research priorities, shape the future force, stimulate thought and debate, and address future warfighting challenges. | AB83: Helder | AC83: 44318 | AD83: 82 | AE83: =VLOOKUP(F83,Stakeholders!E:K,7,0) -> 101 | AF83: =VLOOKUP(B83&D83,Areas!$D:$E,2,FALSE) -> 249 | AH83: 1 - Projeto Prospecta Parte 02 - 2022 | AI83: =COUNTIF(Stakeholders!$E$2:$E$114,F83) -> 1
A84: 2020 | B84: Oceania | C84: Austrália | D84: Austrália | E84: Austrália | F84: Defense Department of Australia | G84: =COUNTIF(Stakeholders!$E$2:$E960,F84) -> 1 | H84: Modelling Human Attributes in Autonomous Systems Operations | I84: https://www.dst.defence.gov.au/sites/default/files/publications/documents/DST-Group-GD-1056.pdf | J84: sim | K84: sim | W84: não | AA84: Unmanned Systems (UMS) have the potential to provide significant benefits when used in military operations that are dangerous, dirty, and/or dull; the principal benefit cited in a variety of literature is of reducing the risk of human casualties. | AB84: Helder | AC84: 44318 | AD84: 83 | AE84: =VLOOKUP(F84,Stakeholders!E:K,7,0) -> 101 | AF84: =VLOOKUP(B84&D84,Areas!$D:$E,2,FALSE) -> 249 | AH84: 1 - Projeto Prospecta Parte 02 - 2022 | AI84: =COUNTIF(Stakeholders!$E$2:$E$114,F84) -> 1
A85: 2018 | B85: Oceania | C85: Austrália | D85: Austrália | E85: Austrália | F85: Defense Department of Australia | G85: =COUNTIF(Stakeholders!$E$2:$E960,F85) -> 1 | H85: Advanced Materials and Manufacturing – Implications for Defence to 2040 | I85: https://www.dst.defence.gov.au/sites/default/files/publications/documents/DST-Group-GD-1022_0.pdf | J85: sim | K85: sim | W85: não | AA85: The Next Generation Technologies Fund announced in the 2016 Defence White Paper focuses on game changing capabilities that have a disruptive effect on Defence and national security. One program within the Next Generation Technologies Fund is the Emerging Disruptive Technology Assessment Symposium (EDTAS) series which is designed to provide key insights and information on emerging and potential technologies over the longer term. In this context technology foresighting is a critical function required to understand the strategic environment we find ourselves in and the opportunities that science and technology may pose in minimising or exploiting disruption. | AB85: Helder | AC85: 44318 | AD85: 84 | AE85: =VLOOKUP(F85,Stakeholders!E:K,7,0) -> 101 | AF85: =VLOOKUP(B85&D85,Areas!$D:$E,2,FALSE) -> 249 | AH85: 1 - Projeto Prospecta Parte 02 - 2022 | AI85: =COUNTIF(Stakeholders!$E$2:$E$114,F85) -> 1
A86: 2017 | B86: Oceania | C86: Austrália | D86: Austrália | E86: Austrália | F86: Defense Department of Australia | G86: =COUNTIF(Stakeholders!$E$2:$E960,F86) -> 1 | H86: Foreign Policy White Paper | I86: https://www.dfat.gov.au/publications/minisite/2017-foreign-policy-white-paper/fpwhitepaper/pdf/2017-foreign-policy-white-paper.pdf | J86: sim | K86: não | W86: não | AA86: The 2017 Foreign Policy White Paper sets out a comprehensive framework to advance Australia’s security and prosperity in a contested and competitive world | AB86: Helder | AC86: 44318 | AD86: 85 | AE86: =VLOOKUP(F86,Stakeholders!E:K,7,0) -> 101 | AF86: =VLOOKUP(B86&D86,Areas!$D:$E,2,FALSE) -> 249 | AH86: 1 - Projeto Prospecta Parte 02 - 2022 | AI86: =COUNTIF(Stakeholders!$E$2:$E$114,F86) -> 1
A87: 2020 | B87: Oceania | C87: Austrália | D87: Austrália | E87: Austrália | F87: Defense Department of Australia | G87: =COUNTIF(Stakeholders!$E$2:$E960,F87) -> 1 | H87: National Security Science and Technology Priorities | I87: https://www.dst.defence.gov.au/sites/default/files/publications/documents/National%20Security%20Science%20and%20Technology%20Priorities.pdf | J87: sim | K87: não | W87: sim | AA87: The scope of science and technology is broadening and the speed of change is unprecedented | AB87: Helder | AC87: 44318 | AD87: 86 | AE87: =VLOOKUP(F87,Stakeholders!E:K,7,0) -> 101 | AF87: =VLOOKUP(B87&D87,Areas!$D:$E,2,FALSE) -> 249 | AH87: 1 - Projeto Prospecta Parte 02 - 2022 | AI87: =COUNTIF(Stakeholders!$E$2:$E$114,F87) -> 1
A88: 2018 | B88: Oceania | C88: Austrália | D88: Austrália | E88: Austrália | F88: Defense Department of Australia | G88: =COUNTIF(Stakeholders!$E$2:$E960,F88) -> 1 | H88: Comprehensive Analysis of Strategic Force Generation Challenges in the Australian Army | I88: https://www.rand.org/content/dam/rand/pubs/research_reports/RR2300/RR2382/RAND_RR2382.pdf | J88: sim | K88: não | W88: sim | AA88: Australian Army Headquarters has tasked RAND Australia to investigate the strategiclevel challenges associated with Force Generation (FORGEN) in the wake of its adopting a cyclical 36-month FORGEN process to support its newly organised and modernised formations. | AB88: Helder | AC88: 44318 | AD88: 87 | AE88: =VLOOKUP(F88,Stakeholders!E:K,7,0) -> 101 | AF88: =VLOOKUP(B88&D88,Areas!$D:$E,2,FALSE) -> 249 | AH88: 1 - Projeto Prospecta Parte 02 - 2022 | AI88: =COUNTIF(Stakeholders!$E$2:$E$114,F88) -> 1
A89: 2018 | B89: Oceania | C89: Austrália | D89: Austrália | E89: Austrália | F89: Australian Strategic Policy Institute | G89: =COUNTIF(Stakeholders!$E$2:$E960,F89) -> 1 | H89: Forward defence in depth for Australia | I89: https://www.jstor.org/stable/pdf/resrep23031.pdf?ab_segments=0%252Fbasic_search_gsv2%252Fcontrol&refreqid=excelsior%3A50e5fca860a62cae42f32937827a7e82 | J89: sim | K89: não | W89: não | AA89: With the re-election of the Scott Morrison-led Coalition government in May 2019, the future shape of Australian defence policy needs to be examined. | AB89: Helder | AC89: 44318 | AD89: 88 | AE89: =VLOOKUP(F89,Stakeholders!E:K,7,0) -> 98 | AF89: =VLOOKUP(B89&D89,Areas!$D:$E,2,FALSE) -> 249 | AH89: 1 - Projeto Prospecta Parte 02 - 2022 | AI89: =COUNTIF(Stakeholders!$E$2:$E$114,F89) -> 1
A90: 2020 | B90: Oceania | C90: Austrália | D90: Austrália | E90: Austrália | F90: Australian Strategic Policy Institute | G90: =COUNTIF(Stakeholders!$E$2:$E960,F90) -> 1 | H90: THE DEFENCE LENS OF NORTHERN AUSTRALIA | I90: https://www.jstor.org/stable/pdf/resrep27692.8.pdf?ab_segments=0%252Fbasic_search_gsv2%252Fcontrol&refreqid=excelsior%3A5437d1981d9e8a8fc2388cdbca715644 | J90: sim | K90: não | W90: não | AA90: Northern Australia continues to be critical to the ADF as a home base and potentially as a mounting base or operating base in several different contingencies | AB90: Helder | AC90: 44318 | AD90: 89 | AE90: =VLOOKUP(F90,Stakeholders!E:K,7,0) -> 98 | AF90: =VLOOKUP(B90&D90,Areas!$D:$E,2,FALSE) -> 249 | AH90: 1 - Projeto Prospecta Parte 02 - 2022 | AI90: =COUNTIF(Stakeholders!$E$2:$E$114,F90) -> 1
A91: 2018 | B91: Oceania | C91: Austrália | D91: Indonésia | E91: Austrália | F91: Lowy Institute for International Policy | G91: =COUNTIF(Stakeholders!$E$2:$E960,F91) -> 1 | H91: Reinforcing Indonesia—Australia defence relations:: The case for maritime recalibration | I91: https://www.jstor.org/stable/pdf/resrep19788.pdf?ab_segments=0%252Fbasic_search_gsv2%252Fcontrol&refreqid=excelsior%3A449d138e05269a21305eb9e3147ed9d3 | J91: sim | K91: não | W91: não | AA91: ndonesia and Australia are increasingly important strategic anchors in the Indo-Pacific region, as recognised by the recently announced Indonesia–Australia Comprehensive Strategic Partnership. | AB91: Helder | AC91: 44318 | AD91: 90 | AE91: =VLOOKUP(F91,Stakeholders!E:K,7,0) -> 97 | AF91: =VLOOKUP(B91&D91,Areas!$D:$E,2,FALSE) -> #N/A | AH91: 1 - Projeto Prospecta Parte 02 - 2022 | AI91: =COUNTIF(Stakeholders!$E$2:$E$114,F91) -> 1
A92: 2020 | B92: Oceania | C92: Austrália | D92: Austrália | E92: Singapura | F92: S. Rajaratnam School of International Studies | G92: =COUNTIF(Stakeholders!$E$2:$E960,F92) -> 1 | H92: AUSTRALIA AS A RISING MIDDLE POWER | I92: https://www.jstor.org/stable/pdf/resrep24285.pdf?ab_segments=0%252Fbasic_search_gsv2%252Fcontrol&refreqid=excelsior%3Ad299c3b431623cf84ecc8dcf04b9b229 | J92: sim | K92: não | W92: não | AA92: This paper examines the key drivers shaping Australia’s role as a middle power in an era of intensifying US-China strategic competition | AB92: Helder | AC92: 44318 | AD92: 91 | AE92: =VLOOKUP(F92,Stakeholders!E:K,7,0) -> 57 | AF92: =VLOOKUP(B92&D92,Areas!$D:$E,2,FALSE) -> 249 | AH92: 1 - Projeto Prospecta Parte 02 - 2022 | AI92: =COUNTIF(Stakeholders!$E$2:$E$114,F92) -> 1
A93: 2019 | B93: Oceania | C93: Austrália | D93: Austrália | E93: Austrália | F93: Australian Strategic Policy Institute | G93: =COUNTIF(Stakeholders!$E$2:$E960,F93) -> 1 | H93: North of 26° south and the security of Australia: Views from The Strategist | I93: https://www.jstor.org/stable/pdf/resrep23032.pdf?ab_segments=0%252Fbasic_search_gsv2%252Fcontrol&refreqid=excelsior%3A2e7523f356188dc4407d0e0df00fb9fb | J93: sim | K93: não | W93: não | AA93: The idea of the north of Australia being central to the new concept of the defence of Australia in the 1970s derived from the key strategic fact that the only country in the region with the conventional military capabilities to threaten Australia was Indonesia. | AB93: Helder | AC93: 44318 | AD93: 92 | AE93: =VLOOKUP(F93,Stakeholders!E:K,7,0) -> 98 | AF93: =VLOOKUP(B93&D93,Areas!$D:$E,2,FALSE) -> 249 | AH93: 1 - Projeto Prospecta Parte 02 - 2022 | AI93: =COUNTIF(Stakeholders!$E$2:$E$114,F93) -> 1
A94: 2020 | B94: Oceania | C94: Austrália | D94: Austrália | E94: Austrália | F94: Australian Strategic Policy Institute | G94: =COUNTIF(Stakeholders!$E$2:$E960,F94) -> 1 | H94: North of 26° south and the security of Australia Views from The Strategist Vol. 2 | I94: https://www.jstor.org/stable/pdf/resrep25081.pdf?ab_segments=0%252Fbasic_search_gsv2%252Fcontrol&refreqid=excelsior%3A0043748d249289470843c5ec47b3a930 | J94: sim | K94: não | W94: não | AA94: The idea of the north of Australia being central to the new concept of the defence of Australia in the 1970s derived from the key strategic fact that the only country in the region with the conventional military capabilities to threaten Australia was Indonesia. | AB94: Helder | AC94: 44318 | AD94: 93 | AE94: =VLOOKUP(F94,Stakeholders!E:K,7,0) -> 98 | AF94: =VLOOKUP(B94&D94,Areas!$D:$E,2,FALSE) -> 249 | AH94: 1 - Projeto Prospecta Parte 02 - 2022 | AI94: =COUNTIF(Stakeholders!$E$2:$E$114,F94) -> 1
A95: 2020 | B95: Oceania | C95: Austrália | D95: Austrália | E95: Austrália | F95: Australian Strategic Policy Institute | G95: =COUNTIF(Stakeholders!$E$2:$E960,F95) -> 1 | H95: Defence’s use of social media | I95: https://www.jstor.org/stable/pdf/resrep25126.9.pdf?ab_segments=0%252Fbasic_search_gsv2%252Fcontrol&refreqid=excelsior%3Ad71320d81843d40f073b366fb2f9f153 | J95: sim | K95: não | W95: não | AA95: low investment and usually low reward. But some posts are quite valuable, even in locations where there’s usually little engagement, potentially serving as an economical means to exert influence with small, but repeated, effects. An examination of the types of posts and the levels of engagement they receive offers some insights. | AB95: Helder | AC95: 44318 | AD95: 94 | AE95: =VLOOKUP(F95,Stakeholders!E:K,7,0) -> 98 | AF95: =VLOOKUP(B95&D95,Areas!$D:$E,2,FALSE) -> 249 | AH95: 1 - Projeto Prospecta Parte 02 - 2022 | AI95: =COUNTIF(Stakeholders!$E$2:$E$114,F95) -> 1
A96: 2020 | B96: Oceania | C96: Nova Zelândia | D96: Nova Zelândia | E96: Nova Zelândia | F96: New Zeland Ministry of Defense | G96: =COUNTIF(Stakeholders!$E$2:$E960,F96) -> 1 | H96: 2020 BRIEFING TO INCOMING MINISTER OF DEFENCE | I96: https://www.nzdf.mil.nz/assets/publication/Defence-BIM.pdf | J96: sim | K96: não | W96: não | AA96: Briefing do trabalho a ser realizado pelo Ministro da Defesa da Nova Zelândia | AB96: Helder | AC96: 44318 | AD96: 95 | AE96: =VLOOKUP(F96,Stakeholders!E:K,7,0) -> 102 | AF96: =VLOOKUP(B96&D96,Areas!$D:$E,2,FALSE) -> 267 | AH96: 1 - Projeto Prospecta Parte 02 - 2022 | AI96: =COUNTIF(Stakeholders!$E$2:$E$114,F96) -> 1
A97: 2019 | B97: Oceania | C97: Nova Zelândia | D97: Nova Zelândia | E97: Nova Zelândia | F97: New Zeland Ministry of Defense | G97: =COUNTIF(Stakeholders!$E$2:$E960,F97) -> 1 | H97: Advanced Pacific Partenerships | I97: https://www.defence.govt.nz/assets/publication/file/5f6dd307e7/Advancing-Pacific-Partnerships-2019.pdf | J97: sim | K97: não | W97: não | AA97: This Defence Assessment translates the high-level strategic policy of the Pacific Reset and the Policy Statement into a Defence regional approach. Advancing Pacific Partnerships puts forward a vision for an inter-generational investment in a secure, stable, and resilient Pacific, achieved foremost by advancing partnerships and supporting exisiting regional security architectures. | AB97: Helder | AC97: 44318 | AD97: 96 | AE97: =VLOOKUP(F97,Stakeholders!E:K,7,0) -> 102 | AF97: =VLOOKUP(B97&D97,Areas!$D:$E,2,FALSE) -> 267 | AH97: 1 - Projeto Prospecta Parte 02 - 2022 | AI97: =COUNTIF(Stakeholders!$E$2:$E$114,F97) -> 1
A98: 2019 | B98: Oceania | C98: Nova Zelândia | D98: Nova Zelândia | E98: Nova Zelândia | F98: New Zeland Ministry of Defense | G98: =COUNTIF(Stakeholders!$E$2:$E960,F98) -> 1 | H98: STATEMENT OF INTENT 2019-2023 | I98: https://www.defence.govt.nz/assets/publication/file/1c5ca053e2/2019-MOD-Statement-of-Intent-v2.pdf | J98: sim | K98: não | W98: não | AA98: Assessment 2019 - 2023 | AB98: Helder | AC98: 44318 | AD98: 97 | AE98: =VLOOKUP(F98,Stakeholders!E:K,7,0) -> 102 | AF98: =VLOOKUP(B98&D98,Areas!$D:$E,2,FALSE) -> 267 | AH98: 1 - Projeto Prospecta Parte 02 - 2022 | AI98: =COUNTIF(Stakeholders!$E$2:$E$114,F98) -> 1
A99: 2014 | B99: Oceania | C99: Papua Nova-Guiné | D99: Papua Nova-Guiné | E99: Austrália | F99: Institute for Regional Security | G99: =COUNTIF(Stakeholders!$E$2:$E960,F99) -> 1 | H99: The Military in Papua New Guinea: A ‘Culture of Instability’ But No Coup | I99: https://www.jstor.org/stable/pdf/26467881.pdf?refreqid=excelsior%3Ac8e820b83716b232f62c298045ecf09c | J99: sim | K99: não | W99: não | AA99: In the lead-up to independence, there was debate in Papua New Guinea as to whether a defence force would safeguard national security or pose a threat to democracy. In the event, the Defence force was retained and has played a significant role in maintaining internal security and contributing to national development, as well as securing the country’s borders. But there has been some deterioration since independence in the capacity and morale of the PNGDF, and several instances of tension between the military and the government, especially during the Bougainville conflict. Civil-military relations since independence are briefly traced and the question of why Papua New Guinea has not experienced a military coup is addressed. | AB99: Helder | AC99: 44318 | AD99: 98 | AE99: =VLOOKUP(F99,Stakeholders!E:K,7,0) -> 96 | AF99: =VLOOKUP(B99&D99,Areas!$D:$E,2,FALSE) -> 270 | AH99: 1 - Projeto Prospecta Parte 02 - 2022 | AI99: =COUNTIF(Stakeholders!$E$2:$E$114,F99) -> 1
A100: 2018 | B100: Europa | C100: Finlândia | D100: Finlândia | E100: Finlândia | F100: Comittee for the Future | G100: =COUNTIF(Stakeholders!$E$2:$E960,F100) -> 1 | H100: societal transformation 2018–2037 | I100: https://www.eduskunta.fi/FI/naineduskuntatoimii/julkaisut/Documents/NETTI_TUVJ_10_2018_Societal_transformation_UUSI.pdf | AB100: Vj | AC100: 44310 | AD100: 99 | AE100: =VLOOKUP(F100,Stakeholders!E:K,7,0) -> 70 | AF100: =VLOOKUP(B100&D100,Areas!$D:$E,2,FALSE) -> 204 | AH100: 1 - Projeto Prospecta Parte 02 - 2022 | AI100: =COUNTIF(Stakeholders!$E$2:$E$114,F100) -> 1
...

Sheet Cálculos
B1: Região | C1: Instituições | D1: Em quantos descobrimos relatórios? | E1: relatórios por países cobertos | F1: países descobertos | G1: Quantos países efetivamente produzem esse tipo de material? | H1: Quantos relatórios descobrimos na região?
B2: África | C2: =SUMIF(Stakeholders!$A$2:$A999,B2,Stakeholders!$D$2:$D999) -> 2 | D2: =SUMIF('calculos 2'!$A$2:$A999,B2,'calculos 2'!$E$2:$E999) -> 26 | E2: =D2/C2 -> 13 | F2: =C2-D2 -> -24 | H2: =SUMIF(Stakeholders!$A$2:$A999,B2,Stakeholders!$J$2:$J999) -> 26 | I2: =COUNTIF(Stakeholders!A:A,B2) -> 2
B3: América Central | C3: =SUMIF(Stakeholders!$A$2:$A999,B3,Stakeholders!$D$2:$D999) -> 2 | D3: =SUMIF('calculos 2'!$A$2:$A999,B3,'calculos 2'!$E$2:$E999) -> 1 | E3: =D3/C3 -> 0.5 | F3: =C3-D3 -> 1 | H3: =SUMIF(Stakeholders!$A$2:$A999,B3,Stakeholders!$J$2:$J999) -> 1 | I3: =COUNTIF(Stakeholders!A:A,B3) -> 2
B4: América do Norte | C4: =SUMIF(Stakeholders!$A$2:$A999,B4,Stakeholders!$D$2:$D999) -> 3.166746 | D4: =SUMIF('calculos 2'!$A$2:$A999,B4,'calculos 2'!$E$2:$E999) -> 104 | E4: =D4/C4 -> 32.841282 | F4: =ABS(C4-D4) -> 100.83325 | H4: =SUMIF(Stakeholders!$A$2:$A999,B4,Stakeholders!$J$2:$J999) -> 103 | I4: =COUNTIF(Stakeholders!A:A,B4) -> 64
B5: América do Sul | C5: =SUMIF(Stakeholders!$A$2:$A999,B5,Stakeholders!$D$2:$D999) -> 1 | D5: =SUMIF('calculos 2'!$A$2:$A999,B5,'calculos 2'!$E$2:$E999) -> 5 | E5: =D5/C5 -> 5 | F5: =C5-D5 -> -4 | H5: =SUMIF(Stakeholders!$A$2:$A999,B5,Stakeholders!$J$2:$J999) -> 5 | I5: =COUNTIF(Stakeholders!A:A,B5) -> 2
B6: Ásia | C6: =SUMIF(Stakeholders!$A$2:$A999,B6,Stakeholders!$D$2:$D999) -> 6.61 | D6: =SUMIF('calculos 2'!$A$2:$A999,B6,'calculos 2'!$E$2:$E999) -> 25 | E6: =D6/C6 -> 3.7821483 | F6: =C6-D6 -> -18.39 | H6: =SUMIF(Stakeholders!$A$2:$A999,B6,Stakeholders!$J$2:$J999) -> 24 | I6: =COUNTIF(Stakeholders!A:A,B6) -> 22
B7: Europa | C7: =SUMIF(Stakeholders!$A$2:$A999,B7,Stakeholders!$D$2:$D999) -> 29.045238 | D7: =SUMIF('calculos 2'!$A$2:$A999,B7,'calculos 2'!$E$2:$E999) -> 82 | E7: =D7/C7 -> 2.8231822 | F7: =C7-D7 -> -52.954762 | H7: =SUMIF(Stakeholders!$A$2:$A999,B7,Stakeholders!$J$2:$J999) -> 89 | I7: =COUNTIF(Stakeholders!A:A,B7) -> 87
B8: Oceania | C8: =SUMIF(Stakeholders!$A$2:$A999,B8,Stakeholders!$D$2:$D999) -> 1.9081818 | D8: =SUMIF('calculos 2'!$A$2:$A999,B8,'calculos 2'!$E$2:$E999) -> 36 | E8: =D8/C8 -> 18.866127 | F8: =C8-D8 -> -34.091818 | H8: =SUMIF(Stakeholders!$A$2:$A999,B8,Stakeholders!$J$2:$J999) -> 35 | I8: =COUNTIF(Stakeholders!A:A,B8) -> 11
B9: Organismo Internacional | C9: =SUMIF(Stakeholders!$A$2:$A999,B9,Stakeholders!$D$2:$D999) -> 9.79 | D9: =SUMIF('calculos 2'!$A$2:$A999,B9,'calculos 2'!$E$2:$E999) -> 16 | E9: =D9/C9 -> 1.6343207 | F9: =C9-D9 -> -6.21 | H9: =SUMIF(Stakeholders!$A$2:$A999,B9,Stakeholders!$J$2:$J999) -> 24 | I9: =COUNTIF(Stakeholders!A:A,B9) -> 18
B10: Total | C10: =SUM(C2:C9) -> 55.520166 | D10: =SUM(D2:D9) -> 295 | E10: =D10/C10 -> 5.3133847 | F10: =C10-D10 -> -239.47983 | H10: =SUM(H2:H9) -> 307 | I10: =SUM(I2:I9) -> 208

Sheet calculos 2
A1: Região | B1: País | C1: Instituições | D1: coluna auxiliar - calculo de países cobertos | E1: Relatórios | F1: d
A2: África | B2: África do Sul | C2: =SUMIF(Stakeholders!$C$2:$C999,B2,Stakeholders!$F$2:$F999) -> 1 | D2: =IF(C2=0,0,1) -> 1 | E2: =SUMIF(Stakeholders!$C$2:$C999,B2,Stakeholders!$J$2:$J999) -> 25
A3: África | B3: Angola | C3: =SUMIF(Stakeholders!$C$2:$C999,B3,Stakeholders!$F$2:$F999) -> 0 | D3: =IF(C3=0,0,1) -> 0 | E3: =SUMIF(Stakeholders!$C$2:$C999,B3,Stakeholders!$J$2:$J999) -> 0
A4: África | B4: Argélia | C4: =SUMIF(Stakeholders!$C$2:$C999,B4,Stakeholders!$F$2:$F999) -> 0 | D4: =IF(C4=0,0,1) -> 0 | E4: =SUMIF(Stakeholders!$C$2:$C999,B4,Stakeholders!$J$2:$J999) -> 0
A5: África | B5: Benim | C5: =SUMIF(Stakeholders!$C$2:$C999,B5,Stakeholders!$F$2:$F999) -> 0 | D5: =IF(C5=0,0,1) -> 0 | E5: =SUMIF(Stakeholders!$C$2:$C999,B5,Stakeholders!$J$2:$J999) -> 0
A6: África | B6: Botswana | C6: =SUMIF(Stakeholders!$C$2:$C999,B6,Stakeholders!$F$2:$F999) -> 0 | D6: =IF(C6=0,0,1) -> 0 | E6: =SUMIF(Stakeholders!$C$2:$C999,B6,Stakeholders!$J$2:$J999) -> 0
A7: África | B7: Burkina Faso | C7: =SUMIF(Stakeholders!$C$2:$C999,B7,Stakeholders!$F$2:$F999) -> 0 | D7: =IF(C7=0,0,1) -> 0 | E7: =SUMIF(Stakeholders!$C$2:$C999,B7,Stakeholders!$J$2:$J999) -> 0
A8: África | B8: Burundi | C8: =SUMIF(Stakeholders!$C$2:$C999,B8,Stakeholders!$F$2:$F999) -> 0 | D8: =IF(C8=0,0,1) -> 0 | E8: =SUMIF(Stakeholders!$C$2:$C999,B8,Stakeholders!$J$2:$J999) -> 0
A9: África | B9: Cabo Verde | C9: =SUMIF(Stakeholders!$C$2:$C999,B9,Stakeholders!$F$2:$F999) -> 0 | D9: =IF(C9=0,0,1) -> 0 | E9: =SUMIF(Stakeholders!$C$2:$C999,B9,Stakeholders!$J$2:$J999) -> 0
A10: África | B10: Camarões | C10: =SUMIF(Stakeholders!$C$2:$C999,B10,Stakeholders!$F$2:$F999) -> 0 | D10: =IF(C10=0,0,1) -> 0 | E10: =SUMIF(Stakeholders!$C$2:$C999,B10,Stakeholders!$J$2:$J999) -> 0
A11: África | B11: Chade | C11: =SUMIF(Stakeholders!$C$2:$C999,B11,Stakeholders!$F$2:$F999) -> 0 | D11: =IF(C11=0,0,1) -> 0 | E11: =SUMIF(Stakeholders!$C$2:$C999,B11,Stakeholders!$J$2:$J999) -> 0
A12: África | B12: Comores | C12: =SUMIF(Stakeholders!$C$2:$C999,B12,Stakeholders!$F$2:$F999) -> 0 | D12: =IF(C12=0,0,1) -> 0 | E12: =SUMIF(Stakeholders!$C$2:$C999,B12,Stakeholders!$J$2:$J999) -> 0
A13: África | B13: Costa do Marfim | C13: =SUMIF(Stakeholders!$C$2:$C999,B13,Stakeholders!$F$2:$F999) -> 0 | D13: =IF(C13=0,0,1) -> 0 | E13: =SUMIF(Stakeholders!$C$2:$C999,B13,Stakeholders!$J$2:$J999) -> 0
A14: África | B14: Djibouti | C14: =SUMIF(Stakeholders!$C$2:$C999,B14,Stakeholders!$F$2:$F999) -> 0 | D14: =IF(C14=0,0,1) -> 0 | E14: =SUMIF(Stakeholders!$C$2:$C999,B14,Stakeholders!$J$2:$J999) -> 0
A15: África | B15: Egito | C15: =SUMIF(Stakeholders!$C$2:$C999,B15,Stakeholders!$F$2:$F999) -> 0 | D15: =IF(C15=0,0,1) -> 0 | E15: =SUMIF(Stakeholders!$C$2:$C999,B15,Stakeholders!$J$2:$J999) -> 0
A16: África | B16: Eritreia | C16: =SUMIF(Stakeholders!$C$2:$C999,B16,Stakeholders!$F$2:$F999) -> 0 | D16: =IF(C16=0,0,1) -> 0 | E16: =SUMIF(Stakeholders!$C$2:$C999,B16,Stakeholders!$J$2:$J999) -> 0
A17: África | B17: Etiópia | C17: =SUMIF(Stakeholders!$C$2:$C999,B17,Stakeholders!$F$2:$F999) -> 0 | D17: =IF(C17=0,0,1) -> 0 | E17: =SUMIF(Stakeholders!$C$2:$C999,B17,Stakeholders!$J$2:$J999) -> 0
A18: África | B18: Gabão | C18: =SUMIF(Stakeholders!$C$2:$C999,B18,Stakeholders!$F$2:$F999) -> 0 | D18: =IF(C18=0,0,1) -> 0 | E18: =SUMIF(Stakeholders!$C$2:$C999,B18,Stakeholders!$J$2:$J999) -> 0
A19: África | B19: Gâmbia | C19: =SUMIF(Stakeholders!$C$2:$C999,B19,Stakeholders!$F$2:$F999) -> 0 | D19: =IF(C19=0,0,1) -> 0 | E19: =SUMIF(Stakeholders!$C$2:$C999,B19,Stakeholders!$J$2:$J999) -> 0
A20: África | B20: Gana | C20: =SUMIF(Stakeholders!$C$2:$C999,B20,Stakeholders!$F$2:$F999) -> 0 | D20: =IF(C20=0,0,1) -> 0 | E20: =SUMIF(Stakeholders!$C$2:$C999,B20,Stakeholders!$J$2:$J999) -> 0
A21: África | B21: Guiné | C21: =SUMIF(Stakeholders!$C$2:$C999,B21,Stakeholders!$F$2:$F999) -> 0 | D21: =IF(C21=0,0,1) -> 0 | E21: =SUMIF(Stakeholders!$C$2:$C999,B21,Stakeholders!$J$2:$J999) -> 0
A22: África | B22: Guiné Bissau | C22: =SUMIF(Stakeholders!$C$2:$C999,B22,Stakeholders!$F$2:$F999) -> 0 | D22: =IF(C22=0,0,1) -> 0 | E22: =SUMIF(Stakeholders!$C$2:$C999,B22,Stakeholders!$J$2:$J999) -> 0
A23: África | B23: Guiné Equatorial | C23: =SUMIF(Stakeholders!$C$2:$C999,B23,Stakeholders!$F$2:$F999) -> 0 | D23: =IF(C23=0,0,1) -> 0 | E23: =SUMIF(Stakeholders!$C$2:$C999,B23,Stakeholders!$J$2:$J999) -> 0
A24: África | B24: Lesoto | C24: =SUMIF(Stakeholders!$C$2:$C999,B24,Stakeholders!$F$2:$F999) -> 0 | D24: =IF(C24=0,0,1) -> 0 | E24: =SUMIF(Stakeholders!$C$2:$C999,B24,Stakeholders!$J$2:$J999) -> 0
A25: África | B25: Libéria | C25: =SUMIF(Stakeholders!$C$2:$C999,B25,Stakeholders!$F$2:$F999) -> 0 | D25: =IF(C25=0,0,1) -> 0 | E25: =SUMIF(Stakeholders!$C$2:$C999,B25,Stakeholders!$J$2:$J999) -> 0
A26: África | B26: Líbia | C26: =SUMIF(Stakeholders!$C$2:$C999,B26,Stakeholders!$F$2:$F999) -> 0 | D26: =IF(C26=0,0,1) -> 0 | E26: =SUMIF(Stakeholders!$C$2:$C999,B26,Stakeholders!$J$2:$J999) -> 0
A27: África | B27: Madagáscar | C27: =SUMIF(Stakeholders!$C$2:$C999,B27,Stakeholders!$F$2:$F999) -> 0 | D27: =IF(C27=0,0,1) -> 0 | E27: =SUMIF(Stakeholders!$C$2:$C999,B27,Stakeholders!$J$2:$J999) -> 0
A28: África | B28: Malawi | C28: =SUMIF(Stakeholders!$C$2:$C999,B28,Stakeholders!$F$2:$F999) -> 0 | D28: =IF(C28=0,0,1) -> 0 | E28: =SUMIF(Stakeholders!$C$2:$C999,B28,Stakeholders!$J$2:$J999) -> 0
A29: África | B29: Mali | C29: =SUMIF(Stakeholders!$C$2:$C999,B29,Stakeholders!$F$2:$F999) -> 0 | D29: =IF(C29=0,0,1) -> 0 | E29: =SUMIF(Stakeholders!$C$2:$C999,B29,Stakeholders!$J$2:$J999) -> 0
A30: África | B30: Marrocos | C30: =SUMIF(Stakeholders!$C$2:$C999,B30,Stakeholders!$F$2:$F999) -> 0 | D30: =IF(C30=0,0,1) -> 0 | E30: =SUMIF(Stakeholders!$C$2:$C999,B30,Stakeholders!$J$2:$J999) -> 0
A31: África | B31: Maurícia | C31: =SUMIF(Stakeholders!$C$2:$C999,B31,Stakeholders!$F$2:$F999) -> 0 | D31: =IF(C31=0,0,1) -> 0 | E31: =SUMIF(Stakeholders!$C$2:$C999,B31,Stakeholders!$J$2:$J999) -> 0
A32: África | B32: Mauritânia | C32: =SUMIF(Stakeholders!$C$2:$C999,B32,Stakeholders!$F$2:$F999) -> 0 | D32: =IF(C32=0,0,1) -> 0 | E32: =SUMIF(Stakeholders!$C$2:$C999,B32,Stakeholders!$J$2:$J999) -> 0
A33: África | B33: Moçambique | C33: =SUMIF(Stakeholders!$C$2:$C999,B33,Stakeholders!$F$2:$F999) -> 0 | D33: =IF(C33=0,0,1) -> 0 | E33: =SUMIF(Stakeholders!$C$2:$C999,B33,Stakeholders!$J$2:$J999) -> 0
A34: África | B34: Namíbia | C34: =SUMIF(Stakeholders!$C$2:$C999,B34,Stakeholders!$F$2:$F999) -> 0 | D34: =IF(C34=0,0,1) -> 0 | E34: =SUMIF(Stakeholders!$C$2:$C999,B34,Stakeholders!$J$2:$J999) -> 0
A35: África | B35: Níger | C35: =SUMIF(Stakeholders!$C$2:$C999,B35,Stakeholders!$F$2:$F999) -> 0 | D35: =IF(C35=0,0,1) -> 0 | E35: =SUMIF(Stakeholders!$C$2:$C999,B35,Stakeholders!$J$2:$J999) -> 0
A36: África | B36: Nigéria | C36: =SUMIF(Stakeholders!$C$2:$C999,B36,Stakeholders!$F$2:$F999) -> 0 | D36: =IF(C36=0,0,1) -> 0 | E36: =SUMIF(Stakeholders!$C$2:$C999,B36,Stakeholders!$J$2:$J999) -> 0
A37: África | B37: Quênia | C37: =SUMIF(Stakeholders!$C$2:$C999,B37,Stakeholders!$F$2:$F999) -> 0 | D37: =IF(C37=0,0,1) -> 0 | E37: =SUMIF(Stakeholders!$C$2:$C999,B37,Stakeholders!$J$2:$J999) -> 0
A38: África | B38: República Centro-Africana | C38: =SUMIF(Stakeholders!$C$2:$C999,B38,Stakeholders!$F$2:$F999) -> 0 | D38: =IF(C38=0,0,1) -> 0 | E38: =SUMIF(Stakeholders!$C$2:$C999,B38,Stakeholders!$J$2:$J999) -> 0
A39: África | B39: República Democrática do Congo | C39: =SUMIF(Stakeholders!$C$2:$C999,B39,Stakeholders!$F$2:$F999) -> 0 | D39: =IF(C39=0,0,1) -> 0 | E39: =SUMIF(Stakeholders!$C$2:$C999,B39,Stakeholders!$J$2:$J999) -> 0
A40: África | B40: República do Congo | C40: =SUMIF(Stakeholders!$C$2:$C999,B40,Stakeholders!$F$2:$F999) -> 0 | D40: =IF(C40=0,0,1) -> 0 | E40: =SUMIF(Stakeholders!$C$2:$C999,B40,Stakeholders!$J$2:$J999) -> 0
A41: África | B41: Ruanda | C41: =SUMIF(Stakeholders!$C$2:$C999,B41,Stakeholders!$F$2:$F999) -> 0 | D41: =IF(C41=0,0,1) -> 0 | E41: =SUMIF(Stakeholders!$C$2:$C999,B41,Stakeholders!$J$2:$J999) -> 0
A42: África | B42: São Tomé e Príncipe | C42: =SUMIF(Stakeholders!$C$2:$C999,B42,Stakeholders!$F$2:$F999) -> 0 | D42: =IF(C42=0,0,1) -> 0 | E42: =SUMIF(Stakeholders!$C$2:$C999,B42,Stakeholders!$J$2:$J999) -> 0
A43: África | B43: Seicheles | C43: =SUMIF(Stakeholders!$C$2:$C999,B43,Stakeholders!$F$2:$F999) -> 0 | D43: =IF(C43=0,0,1) -> 0 | E43: =SUMIF(Stakeholders!$C$2:$C999,B43,Stakeholders!$J$2:$J999) -> 0
A44: África | B44: Senegal | C44: =SUMIF(Stakeholders!$C$2:$C999,B44,Stakeholders!$F$2:$F999) -> 0 | D44: =IF(C44=0,0,1) -> 0 | E44: =SUMIF(Stakeholders!$C$2:$C999,B44,Stakeholders!$J$2:$J999) -> 0
A45: África | B45: Serra Leoa | C45: =SUMIF(Stakeholders!$C$2:$C999,B45,Stakeholders!$F$2:$F999) -> 0 | D45: =IF(C45=0,0,1) -> 0 | E45: =SUMIF(Stakeholders!$C$2:$C999,B45,Stakeholders!$J$2:$J999) -> 0
A46: África | B46: Somália | C46: =SUMIF(Stakeholders!$C$2:$C999,B46,Stakeholders!$F$2:$F999) -> 0 | D46: =IF(C46=0,0,1) -> 0 | E46: =SUMIF(Stakeholders!$C$2:$C999,B46,Stakeholders!$J$2:$J999) -> 0
A47: África | B47: Suazilândia | C47: =SUMIF(Stakeholders!$C$2:$C999,B47,Stakeholders!$F$2:$F999) -> 0 | D47: =IF(C47=0,0,1) -> 0 | E47: =SUMIF(Stakeholders!$C$2:$C999,B47,Stakeholders!$J$2:$J999) -> 0
A48: África | B48: Sudão | C48: =SUMIF(Stakeholders!$C$2:$C999,B48,Stakeholders!$F$2:$F999) -> 0 | D48: =IF(C48=0,0,1) -> 0 | E48: =SUMIF(Stakeholders!$C$2:$C999,B48,Stakeholders!$J$2:$J999) -> 0
A49: África | B49: Sudão do Sul | C49: =SUMIF(Stakeholders!$C$2:$C999,B49,Stakeholders!$F$2:$F999) -> 0 | D49: =IF(C49=0,0,1) -> 0 | E49: =SUMIF(Stakeholders!$C$2:$C999,B49,Stakeholders!$J$2:$J999) -> 0
A50: África | B50: Tanzânia | C50: =SUMIF(Stakeholders!$C$2:$C999,B50,Stakeholders!$F$2:$F999) -> 0 | D50: =IF(C50=0,0,1) -> 0 | E50: =SUMIF(Stakeholders!$C$2:$C999,B50,Stakeholders!$J$2:$J999) -> 0
A51: África | B51: Togo | C51: =SUMIF(Stakeholders!$C$2:$C999,B51,Stakeholders!$F$2:$F999) -> 0 | D51: =IF(C51=0,0,1) -> 0 | E51: =SUMIF(Stakeholders!$C$2:$C999,B51,Stakeholders!$J$2:$J999) -> 0
A52: África | B52: Tunísia | C52: =SUMIF(Stakeholders!$C$2:$C999,B52,Stakeholders!$F$2:$F999) -> 0 | D52: =IF(C52=0,0,1) -> 0 | E52: =SUMIF(Stakeholders!$C$2:$C999,B52,Stakeholders!$J$2:$J999) -> 0
A53: África | B53: Turquia | C53: =SUMIF(Stakeholders!$C$2:$C999,B53,Stakeholders!$F$2:$F999) -> 0 | D53: =IF(C53=0,0,1) -> 0 | E53: =SUMIF(Stakeholders!$C$2:$C999,B53,Stakeholders!$J$2:$J999) -> 0
A54: África | B54: Uganda | C54: =SUMIF(Stakeholders!$C$2:$C999,B54,Stakeholders!$F$2:$F999) -> 1 | D54: =IF(C54=0,0,1) -> 1 | E54: =SUMIF(Stakeholders!$C$2:$C999,B54,Stakeholders!$J$2:$J999) -> 1
A55: África | B55: Zâmbia | C55: =SUMIF(Stakeholders!$C$2:$C999,B55,Stakeholders!$F$2:$F999) -> 0 | D55: =IF(C55=0,0,1) -> 0 | E55: =SUMIF(Stakeholders!$C$2:$C999,B55,Stakeholders!$J$2:$J999) -> 0
A56: África | B56: Zimbabwe | C56: =SUMIF(Stakeholders!$C$2:$C999,B56,Stakeholders!$F$2:$F999) -> 0 | D56: =IF(C56=0,0,1) -> 0 | E56: =SUMIF(Stakeholders!$C$2:$C999,B56,Stakeholders!$J$2:$J999) -> 0
A57: América Central | B57: Honduras | C57: =SUMIF(Stakeholders!$C$2:$C999,B57,Stakeholders!$F$2:$F999) -> 1 | D57: =IF(C57=0,0,1) -> 1 | E57: =SUMIF(Stakeholders!$C$2:$C999,B57,Stakeholders!$J$2:$J999) -> 1
A58: América Central | B58: Jamaica | C58: =SUMIF(Stakeholders!$C$2:$C999,B58,Stakeholders!$F$2:$F999) -> 1 | D58: =IF(C58=0,0,1) -> 1 | E58: =SUMIF(Stakeholders!$C$2:$C999,B58,Stakeholders!$J$2:$J999) -> 0
A59: América Central | B59: Antígua e Barbuda | C59: =SUMIF(Stakeholders!$C$2:$C999,B59,Stakeholders!$F$2:$F999) -> 0 | D59: =IF(C59=0,0,1) -> 0 | E59: =SUMIF(Stakeholders!$C$2:$C999,B59,Stakeholders!$J$2:$J999) -> 0
A60: América Central | B60: Bahamas | C60: =SUMIF(Stakeholders!$C$2:$C999,B60,Stakeholders!$F$2:$F999) -> 0 | D60: =IF(C60=0,0,1) -> 0 | E60: =SUMIF(Stakeholders!$C$2:$C999,B60,Stakeholders!$J$2:$J999) -> 0
A61: América Central | B61: Barbados | C61: =SUMIF(Stakeholders!$C$2:$C999,B61,Stakeholders!$F$2:$F999) -> 0 | D61: =IF(C61=0,0,1) -> 0 | E61: =SUMIF(Stakeholders!$C$2:$C999,B61,Stakeholders!$J$2:$J999) -> 0
A62: América Central | B62: Belize | C62: =SUMIF(Stakeholders!$C$2:$C999,B62,Stakeholders!$F$2:$F999) -> 0 | D62: =IF(C62=0,0,1) -> 0 | E62: =SUMIF(Stakeholders!$C$2:$C999,B62,Stakeholders!$J$2:$J999) -> 0
A63: América Central | B63: Costa Rica | C63: =SUMIF(Stakeholders!$C$2:$C999,B63,Stakeholders!$F$2:$F999) -> 0 | D63: =IF(C63=0,0,1) -> 0 | E63: =SUMIF(Stakeholders!$C$2:$C999,B63,Stakeholders!$J$2:$J999) -> 0
A64: América Central | B64: Cuba | C64: =SUMIF(Stakeholders!$C$2:$C999,B64,Stakeholders!$F$2:$F999) -> 0 | D64: =IF(C64=0,0,1) -> 0 | E64: =SUMIF(Stakeholders!$C$2:$C999,B64,Stakeholders!$J$2:$J999) -> 0
A65: América Central | B65: Dominica | C65: =SUMIF(Stakeholders!$C$2:$C999,B65,Stakeholders!$F$2:$F999) -> 0 | D65: =IF(C65=0,0,1) -> 0 | E65: =SUMIF(Stakeholders!$C$2:$C999,B65,Stakeholders!$J$2:$J999) -> 0
A66: América Central | B66: El Salvador | C66: =SUMIF(Stakeholders!$C$2:$C999,B66,Stakeholders!$F$2:$F999) -> 0 | D66: =IF(C66=0,0,1) -> 0 | E66: =SUMIF(Stakeholders!$C$2:$C999,B66,Stakeholders!$J$2:$J999) -> 0
A67: América Central | B67: Granada | C67: =SUMIF(Stakeholders!$C$2:$C999,B67,Stakeholders!$F$2:$F999) -> 0 | D67: =IF(C67=0,0,1) -> 0 | E67: =SUMIF(Stakeholders!$C$2:$C999,B67,Stakeholders!$J$2:$J999) -> 0
A68: América Central | B68: Guatemala | C68: =SUMIF(Stakeholders!$C$2:$C999,B68,Stakeholders!$F$2:$F999) -> 0 | D68: =IF(C68=0,0,1) -> 0 | E68: =SUMIF(Stakeholders!$C$2:$C999,B68,Stakeholders!$J$2:$J999) -> 0
A69: América Central | B69: Haiti | C69: =SUMIF(Stakeholders!$C$2:$C999,B69,Stakeholders!$F$2:$F999) -> 0 | D69: =IF(C69=0,0,1) -> 0 | E69: =SUMIF(Stakeholders!$C$2:$C999,B69,Stakeholders!$J$2:$J999) -> 0
A70: América Central | B70: Nicarágua | C70: =SUMIF(Stakeholders!$C$2:$C999,B70,Stakeholders!$F$2:$F999) -> 0 | D70: =IF(C70=0,0,1) -> 0 | E70: =SUMIF(Stakeholders!$C$2:$C999,B70,Stakeholders!$J$2:$J999) -> 0
A71: América Central | B71: Panamá | C71: =SUMIF(Stakeholders!$C$2:$C999,B71,Stakeholders!$F$2:$F999) -> 0 | D71: =IF(C71=0,0,1) -> 0 | E71: =SUMIF(Stakeholders!$C$2:$C999,B71,Stakeholders!$J$2:$J999) -> 0
A72: América Central | B72: República Dominicana | C72: =SUMIF(Stakeholders!$C$2:$C999,B72,Stakeholders!$F$2:$F999) -> 0 | D72: =IF(C72=0,0,1) -> 0 | E72: =SUMIF(Stakeholders!$C$2:$C999,B72,Stakeholders!$J$2:$J999) -> 0
A73: América Central | B73: Santa Lúcia | C73: =SUMIF(Stakeholders!$C$2:$C999,B73,Stakeholders!$F$2:$F999) -> 0 | D73: =IF(C73=0,0,1) -> 0 | E73: =SUMIF(Stakeholders!$C$2:$C999,B73,Stakeholders!$J$2:$J999) -> 0
A74: América Central | B74: São Cristóvão e Névis | C74: =SUMIF(Stakeholders!$C$2:$C999,B74,Stakeholders!$F$2:$F999) -> 0 | D74: =IF(C74=0,0,1) -> 0 | E74: =SUMIF(Stakeholders!$C$2:$C999,B74,Stakeholders!$J$2:$J999) -> 0
A75: América Central | B75: São Vicente e Granadinas | C75: =SUMIF(Stakeholders!$C$2:$C999,B75,Stakeholders!$F$2:$F999) -> 0 | D75: =IF(C75=0,0,1) -> 0 | E75: =SUMIF(Stakeholders!$C$2:$C999,B75,Stakeholders!$J$2:$J999) -> 0
A76: América Central | B76: Trinidad e Tobago | C76: =SUMIF(Stakeholders!$C$2:$C999,B76,Stakeholders!$F$2:$F999) -> 0 | D76: =IF(C76=0,0,1) -> 0 | E76: =SUMIF(Stakeholders!$C$2:$C999,B76,Stakeholders!$J$2:$J999) -> 0
A77: América do Norte | B77: EUA | C77: =SUMIF(Stakeholders!$C$2:$C999,B77,Stakeholders!$F$2:$F999) -> 56 | D77: =IF(C77=0,0,1) -> 1 | E77: =SUMIF(Stakeholders!$C$2:$C999,B77,Stakeholders!$J$2:$J999) -> 92
A78: América do Norte | B78: Canadá | C78: =SUMIF(Stakeholders!$C$2:$C999,B78,Stakeholders!$F$2:$F999) -> 9 | D78: =IF(C78=0,0,1) -> 1 | E78: =SUMIF(Stakeholders!$C$2:$C999,B78,Stakeholders!$J$2:$J999) -> 10
A79: América do Norte | B79: México | C79: =SUMIF(Stakeholders!$C$2:$C999,B79,Stakeholders!$F$2:$F999) -> 1 | D79: =IF(C79=0,0,1) -> 1 | E79: =SUMIF(Stakeholders!$C$2:$C999,B79,Stakeholders!$J$2:$J999) -> 2
A80: América do Sul | B80: Brasil | C80: =SUMIF(Stakeholders!$C$2:$C999,B80,Stakeholders!$F$2:$F999) -> 2 | D80: =IF(C80=0,0,1) -> 1 | E80: =SUMIF(Stakeholders!$C$2:$C999,B80,Stakeholders!$J$2:$J999) -> 5
A81: América do Sul | B81: Argentina | C81: =SUMIF(Stakeholders!$C$2:$C999,B81,Stakeholders!$F$2:$F999) -> 0 | D81: =IF(C81=0,0,1) -> 0 | E81: =SUMIF(Stakeholders!$C$2:$C999,B81,Stakeholders!$J$2:$J999) -> 0
A82: América do Sul | B82: Bolívia | C82: =SUMIF(Stakeholders!$C$2:$C999,B82,Stakeholders!$F$2:$F999) -> 0 | D82: =IF(C82=0,0,1) -> 0 | E82: =SUMIF(Stakeholders!$C$2:$C999,B82,Stakeholders!$J$2:$J999) -> 0
A83: América do Sul | B83: Chile | C83: =SUMIF(Stakeholders!$C$2:$C999,B83,Stakeholders!$F$2:$F999) -> 0 | D83: =IF(C83=0,0,1) -> 0 | E83: =SUMIF(Stakeholders!$C$2:$C999,B83,Stakeholders!$J$2:$J999) -> 0
A84: América do Sul | B84: Colômbia | C84: =SUMIF(Stakeholders!$C$2:$C999,B84,Stakeholders!$F$2:$F999) -> 0 | D84: =IF(C84=0,0,1) -> 0 | E84: =SUMIF(Stakeholders!$C$2:$C999,B84,Stakeholders!$J$2:$J999) -> 0
A85: América do Sul | B85: Equador | C85: =SUMIF(Stakeholders!$C$2:$C999,B85,Stakeholders!$F$2:$F999) -> 0 | D85: =IF(C85=0,0,1) -> 0 | E85: =SUMIF(Stakeholders!$C$2:$C999,B85,Stakeholders!$J$2:$J999) -> 0
A86: América do Sul | B86: Guiana | C86: =SUMIF(Stakeholders!$C$2:$C999,B86,Stakeholders!$F$2:$F999) -> 0 | D86: =IF(C86=0,0,1) -> 0 | E86: =SUMIF(Stakeholders!$C$2:$C999,B86,Stakeholders!$J$2:$J999) -> 0
A87: América do Sul | B87: Paraguai | C87: =SUMIF(Stakeholders!$C$2:$C999,B87,Stakeholders!$F$2:$F999) -> 0 | D87: =IF(C87=0,0,1) -> 0 | E87: =SUMIF(Stakeholders!$C$2:$C999,B87,Stakeholders!$J$2:$J999) -> 0
A88: América do Sul | B88: Peru | C88: =SUMIF(Stakeholders!$C$2:$C999,B88,Stakeholders!$F$2:$F999) -> 0 | D88: =IF(C88=0,0,1) -> 0 | E88: =SUMIF(Stakeholders!$C$2:$C999,B88,Stakeholders!$J$2:$J999) -> 0
A89: América do Sul | B89: Suriname | C89: =SUMIF(Stakeholders!$C$2:$C999,B89,Stakeholders!$F$2:$F999) -> 0 | D89: =IF(C89=0,0,1) -> 0 | E89: =SUMIF(Stakeholders!$C$2:$C999,B89,Stakeholders!$J$2:$J999) -> 0
A90: América do Sul | B90: Uruguai | C90: =SUMIF(Stakeholders!$C$2:$C999,B90,Stakeholders!$F$2:$F999) -> 0 | D90: =IF(C90=0,0,1) -> 0 | E90: =SUMIF(Stakeholders!$C$2:$C999,B90,Stakeholders!$J$2:$J999) -> 0
A91: América do Sul | B91: Venezuela | C91: =SUMIF(Stakeholders!$C$2:$C999,B91,Stakeholders!$F$2:$F999) -> 0 | D91: =IF(C91=0,0,1) -> 0 | E91: =SUMIF(Stakeholders!$C$2:$C999,B91,Stakeholders!$J$2:$J999) -> 0
A92: Ásia | B92: Singapura | C92: =SUMIF(Stakeholders!$C$2:$C999,B92,Stakeholders!$F$2:$F999) -> 1 | D92: =IF(C92=0,0,1) -> 1 | E92: =SUMIF(Stakeholders!$C$2:$C999,B92,Stakeholders!$J$2:$J999) -> 2
A93: Ásia | B93: Afeganistão | C93: =SUMIF(Stakeholders!$C$2:$C999,B93,Stakeholders!$F$2:$F999) -> 0 | D93: =IF(C93=0,0,1) -> 0 | E93: =SUMIF(Stakeholders!$C$2:$C999,B93,Stakeholders!$J$2:$J999) -> 0
A94: Ásia | B94: Arábia Saudita | C94: =SUMIF(Stakeholders!$C$2:$C999,B94,Stakeholders!$F$2:$F999) -> 0 | D94: =IF(C94=0,0,1) -> 0 | E94: =SUMIF(Stakeholders!$C$2:$C999,B94,Stakeholders!$J$2:$J999) -> 0
A95: Ásia | B95: Bahrein | C95: =SUMIF(Stakeholders!$C$2:$C999,B95,Stakeholders!$F$2:$F999) -> 0 | D95: =IF(C95=0,0,1) -> 0 | E95: =SUMIF(Stakeholders!$C$2:$C999,B95,Stakeholders!$J$2:$J999) -> 0
A96: Ásia | B96: Bangladesh | C96: =SUMIF(Stakeholders!$C$2:$C999,B96,Stakeholders!$F$2:$F999) -> 0 | D96: =IF(C96=0,0,1) -> 0 | E96: =SUMIF(Stakeholders!$C$2:$C999,B96,Stakeholders!$J$2:$J999) -> 0
A97: Ásia | B97: Brunei | C97: =SUMIF(Stakeholders!$C$2:$C999,B97,Stakeholders!$F$2:$F999) -> 0 | D97: =IF(C97=0,0,1) -> 0 | E97: =SUMIF(Stakeholders!$C$2:$C999,B97,Stakeholders!$J$2:$J999) -> 0
A98: Ásia | B98: Butão | C98: =SUMIF(Stakeholders!$C$2:$C999,B98,Stakeholders!$F$2:$F999) -> 0 | D98: =IF(C98=0,0,1) -> 0 | E98: =SUMIF(Stakeholders!$C$2:$C999,B98,Stakeholders!$J$2:$J999) -> 0
A99: Ásia | B99: Camboja | C99: =SUMIF(Stakeholders!$C$2:$C999,B99,Stakeholders!$F$2:$F999) -> 0 | D99: =IF(C99=0,0,1) -> 0 | E99: =SUMIF(Stakeholders!$C$2:$C999,B99,Stakeholders!$J$2:$J999) -> 0
A100: Ásia | B100: Catar | C100: =SUMIF(Stakeholders!$C$2:$C999,B100,Stakeholders!$F$2:$F999) -> 0 | D100: =IF(C100=0,0,1) -> 0 | E100: =SUMIF(Stakeholders!$C$2:$C999,B100,Stakeholders!$J$2:$J999) -> 0
...

Sheet Dados para dashboard
A1: Região | B1: Questão | C1: resposta
A2: África | B2: países cobertos | C2: =Cálculos!D2 -> 26
A3: América Central | B3: países cobertos | C3: =Cálculos!D3 -> 1
A4: América do Norte | B4: países cobertos | C4: =Cálculos!D4 -> 104
A5: América do Sul | B5: países cobertos | C5: =Cálculos!D5 -> 5
A6: Ásia | B6: países cobertos | C6: =Cálculos!D6 -> 25
A7: Europa | B7: países cobertos | C7: =Cálculos!D7 -> 82
A8: Oceania | B8: países cobertos | C8: =Cálculos!D8 -> 36
A9: Organismo Internacional | B9: países cobertos | C9: =Cálculos!D9 -> 16
A10: África | B10: Países não cobertos | C10: =Cálculos!F2 -> -24
A11: América Central | B11: Países não cobertos | C11: =Cálculos!F3 -> 1
A12: América do Norte | B12: Países não cobertos | C12: =Cálculos!F4 -> 100.83325
A13: América do Sul | B13: Países não cobertos | C13: =Cálculos!F5 -> -4
A14: Ásia | B14: Países não cobertos | C14: =Cálculos!F6 -> -18.39
A15: Europa | B15: Países não cobertos | C15: =Cálculos!F7 -> -52.954762
A16: Oceania | B16: Países não cobertos | C16: =Cálculos!F8 -> -34.091818
A17: Organismo Internacional | B17: Países não cobertos | C17: =Cálculos!F9 -> -6.21
A18: África | B18: relatórios por região | C18: =Cálculos!H2 -> 26
A19: América Central | B19: relatórios por região | C19: =Cálculos!H3 -> 1
A20: América do Norte | B20: relatórios por região | C20: =Cálculos!H4 -> 103
A21: América do Sul | B21: relatórios por região | C21: =Cálculos!H5 -> 5
A22: Ásia | B22: relatórios por região | C22: =Cálculos!H6 -> 24
A23: Europa | B23: relatórios por região | C23: =Cálculos!H7 -> 89
A24: Oceania | B24: relatórios por região | C24: =Cálculos!H8 -> 35
A25: Organismo Internacional | B25: relatórios por região | C25: =Cálculos!H9 -> 24
A26: África | B26: total de países | C26: =Cálculos!C2 -> 2
A27: América Central | B27: total de países | C27: =Cálculos!C3 -> 2
A28: América do Norte | B28: total de países | C28: =Cálculos!C4 -> 3.166746
A29: América do Sul | B29: total de países | C29: =Cálculos!C5 -> 1
A30: Ásia | B30: total de países | C30: =Cálculos!C6 -> 6.61
A31: Europa | B31: total de países | C31: =Cálculos!C7 -> 29.045238
A32: Oceania | B32: total de países | C32: =Cálculos!C8 -> 1.9081818
A33: Organismo Internacional | B33: total de países | C33: =Cálculos!C9 -> 9.79

Sheet Areas
A1: Região | B1: País | C1: Chave_Pais | D1: Chave_Texto | E1: Chave_Numerica
A2: Africa | B2: Africa do Sul | C2: 1 | D2: =A2&B2 -> AfricaAfrica do Sul | E2: =C2 -> 1
A3: Africa | B3: Angola | C3: 2 | D3: =A3&B3 -> AfricaAngola | E3: =C3 -> 2
A4: Africa | B4: Argélia | C4: 3 | D4: =A4&B4 -> AfricaArgélia | E4: =C4 -> 3
A5: Africa | B5: Benim | C5: 4 | D5: =A5&B5 -> AfricaBenim | E5: =C5 -> 4
A6: Africa | B6: Botswana | C6: 5 | D6: =A6&B6 -> AfricaBotswana | E6: =C6 -> 5
A7: Africa | B7: Burkina Faso | C7: 6 | D7: =A7&B7 -> AfricaBurkina Faso | E7: =C7 -> 6
A8: Africa | B8: Burundi | C8: 7 | D8: =A8&B8 -> AfricaBurundi | E8: =C8 -> 7
A9: Africa | B9: Cabo Verde | C9: 8 | D9: =A9&B9 -> AfricaCabo Verde | E9: =C9 -> 8
A10: Africa | B10: Camarões | C10: 9 | D10: =A10&B10 -> AfricaCamarões | E10: =C10 -> 9
A11: Africa | B11: Chade | C11: 10 | D11: =A11&B11 -> AfricaChade | E11: =C11 -> 10
A12: Africa | B12: Comores | C12: 11 | D12: =A12&B12 -> AfricaComores | E12: =C12 -> 11
A13: Africa | B13: Costa do Marfim | C13: 12 | D13: =A13&B13 -> AfricaCosta do Marfim | E13: =C13 -> 12
... A280: Organismo Internacional | B280: International Renewable Energy Agency | C280: 279 | D280: =A280&B280 -> Organismo InternacionalInternational Renewable Energy Agency | E280: =C280 -> 279
A281: América do Norte | B281: Alemanha | C281: 280 | D281: América do NorteAlemanha | E281: 280
A282: América do Norte | B282: Estados Unidos | C282: 281 | D282: América do NorteEstados Unidos | E282: 281
A283: América do Norte | B283: Finlândia | C283: 282 | D283: América do NorteFinlândia | E283: 282
A284: América do Norte | B284: Global | C284: 283 | D284: América do NorteGlobal | E284: 283
A285: América do Norte | B285: Letônia | C285: 284 | D285: América do NorteLetônia | E285: 284
A286: América do Norte | B286: Não Identificado | C286: 285 | D286: América do NorteNão Identificado | E286: 285
A287: América do Norte | B287: Suécia | C287: 286 | D287: América do NorteSuécia | E287: 286
A288: América do Norte | B288: Vários Países | C288: 287 | D288: América do NorteVários Países | E288: 287
A289: Ásia | B289: Vários Países | C289: 288 | D289: ÁsiaVários Países | E289: 288
A290: Europa | B290: Índia | C290: 289 | D290: EuropaÍndia | E290: 289
A291: Europa | B291: Líbia | C291: 290 | D291: EuropaLíbia | E291: 290
A292: Europa | B292: Não Identificado | C292: 291 | D292: EuropaNão Identificado | E292: 291
... A297: Organismo Internacional | B297: Vários Países | C297: 296 | D297: Organismo InternacionalVários Países | E297: 296

Sheet ChaveRelatório
A1: Objeto | B1: Chave_Relatorio
A2: Europa | B2: 1 | C2: =A2 -> Europa
A3: Global | B3: 2 | C3: =A3 -> Global
A4: Região do Ártico | B4: 3 | C4: =A4 -> Região do Ártico
A5: Oriente Médio | B5: 4 | C5: =A5 -> Oriente Médio
A6: Global | B6: 5 | C6: =A6 -> Global
A7: Oriente Médio | B7: 6 | C7: =A7 -> Oriente Médio
A8: EUA - China | B8: 7 | C8: =A8 -> EUA - China
A9: Ásia - Pacífico | B9: 8 | C9: =A9 -> Ásia - Pacífico
A10: Honduras | B10: 9 | C10: =A10 -> Honduras
A11: Não se aplica | B11: 10 | C11: =A11 -> Não se aplica
A12: China | B12: 11 | C12: =A12 -> China
A13: Global | B13: 12 | C13: =A13 -> Global
... A104: EUA | B104: 103 | C104: =A104 -> EUA
B105: 104 | C105: =A105 -> 0
B106: 105 | C106: =A106 -> 0
B107: 106 | C107: =A107 -> 0
B108: 107 | C108: =A108 -> 0
B109: 108 | C109: =A109 -> 0
A110: EUA | B110: 109 | C110: =A110 -> EUA
A111: EUA | B111: 110 | C111: =A111 -> EUA
A112: Global | B112: 111 | C112: =A112 -> Global
A113: EUA | B113: 112 | C113: =A113 -> EUA
A114: EUA | B114: 113 | C114: =A114 -> EUA
A115: Canadá | B115: 114 | C115: =A115 -> Canadá
A116: EUA | B116: 115 | C116: =A116 -> EUA
B117: 116 | C117: =A117 -> 0
B118: 117 | C118: =A118 -> 0
A119: Mundo | B119: 118 | C119: =A119 -> Mundo
A120: Mundo | B120: 119 | C120: =A120 -> Mundo
A121: Não se aplica | B121: 120 | C121: =A121 -> Não se aplica

Sheet Página9
A1: Região
A2: Qtd de países na região
A3: Qtd de países cobertos
A4: Qtd de países não cobertos
A5: Qtd de instituições na região
A6: Qtd de relatórios

Sheet Rel_por_LP
A1: Ordem | B1: Chave Relatório | C1: Ref para Calculo 1
A2: 15 | B2: 15 | C2: 1- Ameaças Eletromagnéticas
A3: 37 | B3: 37 | C3: 1- Ameaças Eletromagnéticas
A4: 68 | B4: 68 | C4: 1- Ameaças Eletromagnéticas
A5: 107 | B5: 107 | C5: 1- Ameaças Eletromagnéticas
A6: 114 | B6: 114 | C6: 1- Ameaças Eletromagnéticas
A7: 161 | B7: 161 | C7: 1- Ameaças Eletromagnéticas
A8: 210 | B8: p033 | C8: 1- Ameaças Eletromagnéticas
A9: 212 | B9: p035 | C9: 1- Ameaças Eletromagnéticas
A10: 215 | B10: p038 | C10: 1- Ameaças Eletromagnéticas
A11: 216 | B11: p039 | C11: 1- Ameaças Eletromagnéticas
A12: 241 | B12: p064 | C12: 1- Ameaças Eletromagnéticas
A13: 311 | B13: p134 | C13: 1- Ameaças Eletromagnéticas
A14: 520 | B14: p343 | C14: 1- Ameaças Eletromagnéticas
A15: 565 | B15: p388 | C15: 1- Ameaças Eletromagnéticas
A16: 566 | B16: p389 | C16: 1- Ameaças Eletromagnéticas
A17: 735 | B17: 314 | C17: 1- Ameaças Eletromagnéticas
A18: 847 | B18: 5 | C18: 2 - Biodefesa e Segurança Alimentar
A19: 848 | B19: 6 | C19: 2 - Biodefesa e Segurança Alimentar
A20: 850 | B20: 8 | C20: 2 - Biodefesa e Segurança Alimentar
A21: 852 | B21: 10 | C21: 2 - Biodefesa e Segurança Alimentar
A22: 854 | B22: 12 | C22: 2 - Biodefesa e Segurança Alimentar
A23: 859 | B23: 17 | C23: 2 - Biodefesa e Segurança Alimentar
A24: 860 | B24: 18 | C24: 2 - Biodefesa e Segurança Alimentar
A25: 861 | B25: 19 | C25: 2 - Biodefesa e Segurança Alimentar
A26: 863 | B26: 21 | C26: 2 - Biodefesa e Segurança Alimentar
A27: 865 | B27: 23 | C27: 2 - Biodefesa e Segurança Alimentar
A28: 866 | B28: 24 | C28: 2 - Biodefesa e Segurança Alimentar
... A37: 1004 | B37: 162 | C37: 2 - Biodefesa e Segurança Alimentar
A38: 1177 | B38: p158 | C38: 2 - Biodefesa e Segurança Alimentar
A39: 1445 | B39: 182 | C39: 2 - Biodefesa e Segurança Alimentar
A40: 1450 | B40: 187 | C40: 2 - Biodefesa e Segurança Alimentar
A41: 1452 | B41: 189 | C41: 2 - Biodefesa e Segurança Alimentar
A42: 1453 | B42: 190 | C42: 2 - Biodefesa e Segurança Alimentar
A43: 1681 | B43: 418 | C43: 2 - Biodefesa e Segurança Alimentar
A44: 1682 | B44: 419 | C44: 2 - Biodefesa e Segurança Alimentar
A45: 1683 | B45: 420 | C45: 2 - Biodefesa e Segurança Alimentar
A46: 1687 | B46: 3 | C46: 3 - Escassez de Recursos
A47: 1689 | B47: 5 | C47: 3 - Escassez de Recursos
A48: 1690 | B48: 6 | C48: 3 - Escassez de Recursos
A49: 1692 | B49: 8 | C49: 3 - Escassez de Recursos
A50: 1698 | B50: 14 | C50: 3 - Escassez de Recursos
... A61: 1839 | B61: 155 | C61: 3 - Escassez de Recursos
A62: 1865 | B62: p004 | C62: 3 - Escassez de Recursos
A63: 1867 | B63: p006 | C63: 3 - Escassez de Recursos
A64: 1868 | B64: p007 | C64: 3 - Escassez de Recursos
A65: 1875 | B65: p014 | C65: 3 - Escassez de Recursos
A66: 1979 | B66: p118 | C66: 3 - Escassez de Recursos
A67: 1980 | B67: p119 | C67: 3 - Escassez de Recursos
A68: 1990 | B68: p129 | C68: 3 - Escassez de Recursos
A69: 1994 | B69: p133 | C69: 3 - Escassez de Recursos
A70: 2079 | B70: p218 | C70: 3 - Escassez de Recursos
A71: 2529 | B71: 3 | C71: 4 - Energia Nuclear e Futuro
A72: 2534 | B72: 8 | C72: 4 - Energia Nuclear e Futuro
A73: 2537 | B73: 11 | C73: 4 - Energia Nuclear e Futuro
A74: 2549 | B74: 23 | C74: 4 - Energia Nuclear e Futuro
A75: 2551 | B75: 25 | C75: 4 - Energia Nuclear e Futuro
A76: 2553 | B76: 27 | C76: 4 - Energia Nuclear e Futuro
A77: 2581 | B77: 55 | C77: 4 - Energia Nuclear e Futuro
A78: 2582 | B78: 56 | C78: 4 - Energia Nuclear e Futuro
A79: 2584 | B79: 58 | C79: 4 - Energia Nuclear e Futuro
A80: 2585 | B80: 59 | C80: 4 - Energia Nuclear e Futuro
A81: 2603 | B81: 77 | C81: 4 - Energia Nuclear e Futuro
A82: 2625 | B82: 99 | C82: 4 - Energia Nuclear e Futuro
... A93: 2702 | B93: 176 | C93: 4 - Energia Nuclear e Futuro
A94: 2708 | B94: p005 | C94: 4 - Energia Nuclear e Futuro
A95: 2710 | B95: p007 | C95: 4 - Energia Nuclear e Futuro
A96: 2716 | B96: p013 | C96: 4 - Energia Nuclear e Futuro
A97: 2718 | B97: p015 | C97: 4 - Energia Nuclear e Futuro
A98: 2726 | B98: p023 | C98: 4 - Energia Nuclear e Futuro
A99: 2732 | B99: p029 | C99: 4 - Energia Nuclear e Futuro
A100: 2735 | B100: p032 | C100: 4 - Energia Nuclear e Futuro
A101: 2782 | B101: p079 | C101: 4 - Energia Nuclear e Futuro
A102: 2795 | B102: p092 | C102: 4 - Energia Nuclear e Futuro
A103: 2822 | B103: p119 | C103: 4 - Energia Nuclear e Futuro
A104: 2824 | B104: p121 | C104: 4 - Energia Nuclear e Futuro
A105: 2840 | B105: p137 | C105: 4 - Energia Nuclear e Futuro
... A146: 3123 | B146: p420 | C146: 4 - Energia Nuclear e Futuro
A147: 3127 | B147: 180 | C147: 4 - Energia Nuclear e Futuro
A148: 3128 | B148: 181 | C148: 4 - Energia Nuclear e Futuro
A149: 3134 | B149: 187 | C149: 4 - Energia Nuclear e Futuro
A150: 3135 | B150: 188 | C150: 4 - Energia Nuclear e Futuro
A151: 3136 | B151: 189 | C151: 4 - Energia Nuclear e Futuro
A152: 3151 | B152: 204 | C152: 4 - Energia Nuclear e Futuro
A153: 3159 | B153: 212 | C153: 4 - Energia Nuclear e Futuro
A154: 3196 | B154: 249 | C154: 4 - Energia Nuclear e Futuro
A155: 3199 | B155: 252 | C155: 4 - Energia Nuclear e Futuro
A156: 3207 | B156: 260 | C156: 4 - Energia Nuclear e Futuro
A157: 3211 | B157: 264 | C157: 4 - Energia Nuclear e Futuro
A158: 3217 | B158: 270 | C158: 4 - Energia Nuclear e Futuro
... A207: 4386 | B207: 176 | C207: 6 - Meio Ambiente Marítimo
A208: 4391 | B208: p004 | C208: 6 - Meio Ambiente Marítimo
A209: 4628 | B209: p241 | C209: 6 - Meio Ambiente Marítimo
A210: 4629 | B210: p242 | C210: 6 - Meio Ambiente Marítimo
A211: 4630 | B211: p243 | C211: 6 - Meio Ambiente Marítimo
A212: 4631 | B212: p244 | C212: 6 - Meio Ambiente Marítimo
A213: 4632 | B213: p245 | C213: 6 - Meio Ambiente Marítimo
A214: 4661 | B214: p274 | C214: 6 - Meio Ambiente Marítimo
A215: 4678 | B215: p291 | C215: 6 - Meio Ambiente Marítimo
A216: 4680 | B216: p293 | C216: 6 - Meio Ambiente Marítimo
...
